Workbook

Sheet IT Summary
A1: IT Summary March 2026
D3: 5 Year Contract Spend | E3: Total Spend FY 2025/2026 | F3: Total Spend FY 2024/2025 | G3: Total Spend FY 2023/2024
D4: Feb 24- Mar 26 | E4: Aug 25-Mar 26 | F4: Aug 24 - Jul 25 | G4: Feb 24 - Jul 24
A5: Filter Application Cost Breakdown | B5: Area | C5: Notes | D5: Total | E5: FY2025/26 | F5: FY 2024/25 | G5: FY 2023/24
C6: OVERALL TOTAL COSTS | D6: =SUM(D17,D39,D45) -> 11120524 | E6: =SUM(E17,E39,E45) -> 3772570.8 | F6: =SUM(F17,F39,F45) -> 5119939.1 | G6: =SUM(G17,G39,G45) -> 2228013.8 | H6: =SUM(E6,F6+G6)-D6 -> 0
A8: FILTER INTERNAL COSTS | D8: Feb 24- Mar 26 | E8: Aug 25 -Mar 26 | F8: Aug 24 - Jul 25 | G8: Feb 23 - Jul 24
A9: Programme Costs | B9: Research & Planning | C9: Includes industry research, feasibility and strategic design activities, programme management, financial management, strategic and senior meetings & reporting. | D9: =Summary!AX156 -> 707917.52 | E9: =Summary!AM156 -> 148664.79 | F9: =Summary!U156 -> 339774.37 | G9: =Summary!J156 -> 219478.36
A10: Team Management Costs | B10: Employee Related Costs | C10: Any activity relating to detailed planning, design, development, test and release of the JDW applications or changes to applications relating to People. | D10: =Summary!AX157 -> 2073989.8 | E10: =Summary!AM157 -> 744679.93 | F10: =Summary!U157 -> 954778.66 | G10: =Summary!J157 -> 374531.2
A11: Development & Delivery Costs | B11: People | C11: Any activity relating to detailed planning, design, development, test and release of the JDW applications or changes to applications relating to People. | D11: =Summary!AX158 -> 2338552.3 | E11: =Summary!AM158 -> 807986.84 | F11: =Summary!U158 -> 1078674.5 | G11: =Summary!J158 -> 451890.93
B12: Customer | C12: Any activity relating to detailed planning, design, development, test and release of the JDW applications or changes to applications relating to Customers. | D12: =Summary!AX159 -> 2582526.6 | E12: =Summary!AM159 -> 830931.13 | F12: =Summary!U159 -> 1067208.7 | G12: =Summary!J159 -> 684386.85
B13: Business & Financial Controls | C13: Any activity relating to detailed planning, design, development, test and release of the JDW applications or changes to applications which support pub or head office process or controls (e.g. Authentication, myCompliance). | D13: =Summary!AX160 -> 387667.97 | E13: =Summary!AM160 -> 89186.58 | F13: =Summary!U160 -> 240568.58 | G13: =Summary!J160 -> 57912.801
B14: Franchising | C14: Any activity relating to detailed planning, design, development, test and release of Franchise applications or changes to applications relating to Franchising. | D14: =Summary!AX161 -> 535319 | E14: =Summary!AM161 -> 265878.82 | F14: =Summary!U161 -> 249260.05 | G14: =Summary!J161 -> 20180.138
B15: Technology & Security | C15: Includes any activity relating to the introduction or improvement of common technical platforms (such as AI and Automation) or technical compliance (such as Security, DR and PCI). | D15: =Summary!AX164 -> 27709.062 | E15: =Summary!AM164 -> 11994.456 | F15: =Summary!U164 -> 14264.519 | G15: =Summary!J164 -> 1450.0867
A16: Support & Maintenance Costs | B16: All | C16: Set monthly charge for ongoing support and maintenance of the applications and services provided. | D16: =Summary!AX165 -> 349371.69 | E16: =Summary!AM165 -> 165565.46 | F16: =Summary!U165 -> 145226.6 | G16: =Summary!J165 -> 38579.626
C17: TOTAL | D17: =SUM(D9:D16) -> 9003054 | E17: =SUM(E9:E16) -> 3064888 | F17: =SUM(F9:F16) -> 4089756 | G17: =SUM(G9:G16) -> 1848410 | H17: =SUM(E17:G17)-D17 -> 0
A19: FILTER MANAGED 3rd PARTY SERVICES | D19: Feb 24 - Mar 26 | E19: Aug 25 - Mar 26 | F19: Aug 24 - Jul 25 | G19: Feb 24 - Jul 24
A20: 3rd Party Costs (variable) | B20: Apple | C20: myJDW - Developer Enterprise Program - Allows large organisations to develop and deploy proprietary, internal-use apps to their employees. | D20: =SUM(E20,F20,G20) -> 767 | E20: 249 | F20: 259 | G20: 259 | I20: Will be charged March 2026
B21: AWS | C21: Management Account - test and UAT AWS accounts. From June 2025, a gradual shift was started to move test and UAT environments to a separate Filter AWS environment, starting with Order & Pay App and progressing to People Apps. This is expected to run at c.£5,000 per month, and the JDW AWS account will adjust down accordingly. | D21: =SUM(E21,F21,G21) -> 27470.2 | E21: ='Aug 25'!G88+'Sep 25'!G88+'Oct 25'!G88+'Nov 25'!G88+'Dec 25'!G88+'Jan - 26'!G88+'Feb - 26'!G88+'Mar - 26'!G88 -> 26105.2 | F21: =596+769 -> 1365 | I21: Charged monthly dependent on usage
B22: AWS | C22: Select Tier Partnership. Annual charge. | D22: =SUM(E22,F22,G22) -> 2122.04 | E22: ='Nov 25'!G89 -> 1136.04 | F22: 986 | I22: Charged November 2025
B23: CookieYes | C23: Corporate, Hotels, Investors, Franchising Websites - Cookie Consent Solution | D23: =SUM(E23,F23,G23) -> 1302 | E23: ='Oct 25'!G90 -> 462 | F23: 420 | G23: 420
B24: CookieYes | C24: Careers Website - Cookie Consent Solution | D24: =SUM(E24,F24,G24) -> 1302 | E24: ='Oct 25'!G91 -> 462 | F24: 420 | G24: 420
B25: Cosmic Giant | C25: Gravity Forms Enhancement Plugin - myJDW, Corporate, Hotels, Careers, Investors, Franchising | D25: =SUM(E25,F25,G25) -> 791.69 | E25: ='Jan - 26'!F92 -> 263.69 | F25: 264 | G25: 264
B26: Elastic Search | C26: myJDW, mySchedule - Open source search and analytics engine. Charge, dependent on usage. | D26: =SUM(E26,F26,G26) -> 1914.78 | E26: ='Aug 25'!G93+'Sep 25'!G93+'Oct 25'!G93+'Nov 25'!G93+'Dec 25'!G93+'Jan - 26'!G93+'Feb - 26'!G93+'Mar - 26'!G93 -> 474.78 | F26: 720 | G26: 720 | I26: Charged monthly dependent on usage
B27: Flagsmith | C27: myJDW, mySchedule, Order & Pay - Open-source feature flag service to toggle features on and off. Annual charge - new 3 year commitment March 2025 to March 2028. Next charge March 2026. | D27: =SUM(E27,F27,G27) -> 104386.67 | E27: ='Mar - 26'!F94 -> 36951.55 | F27: 31976.33 | G27: 35458.79 | I27: Will be charged March 2026
B28: GitHub Advanced Security | C28: Github integrates deeply into our development and deployment workflow, scanning code at multiple points. £35K per year (overs 35 developers, QAs, dev ops engineers and support). Billed ~£3K per month through Filter. There will be some fluctuation due to exchange rates and use of CI/CD deployment. | D28: =SUM(E28,F28,G28) -> 2296.86 | E28: =SUM('Feb - 26'!G95,'Mar - 26'!G95) -> 2296.86 | I28: Commencing Febraury 2026
B29: Google Maps | C29: Corporate , Hotels Websites - For map API usage. Monthly charge, variable based on usage. | D29: =SUM(E29,F29,G29) -> 197998.39 | E29: ='Aug 25'!G95+'Sep 25'!G95+'Oct 25'!G95+'Nov 25'!G95+'Dec 25'!G96+'Jan - 26'!G96+'Feb - 26'!G96+'Mar - 26'!G96 -> 19438.29 | F29: =SUM(126221.29+'May 25'!G94+'June 25'!G95+'July 25'!G95) -> 138560.1 | G29: 40000 | I29: Charged monthly dependent on usage
B30: Google PPC Pilot | C30: Paid Adverts "Google Pay Per Click" Media Fee for November and December. | D30: =SUM(E30,F30,G30) -> 2595.96 | E30: ='Dec 25'!G97 -> 2595.96
B31: Ionic | C31: Order & Pay App - Cross platform application framework. Enterprise package, live updates and payments modules. Charged for two year commitment. Renewed in March. Slight annual increase due to increase in live updates by further 10 million. | D31: =SUM(E31,F31,G31) -> 147410.4 | F31: 105274.4 | G31: 42136 | I31: Will be charged March 2026
B32: Ionic | C32: Order & Pay App - Cross platform application framework. Auth Connect and Identity Vault modules to be used with Customer Accounts. Charged for 21 month commitment. | D32: =SUM(E32,F32,G32) -> 54268.4 | F32: 54268.4 | G32: 0 | I32: Will be charged June 2026
B33: MonSpark | C33: Order & Pay App, Hotels - Source code monitoring for PCI-DSS. Annual charge. | D33: =SUM(E33,F33,G33) -> 1367.84 | E33: ='Mar - 26'!F103 -> 683.84 | F33: 684 | G33: 0 | I33: Will be charged March 2026
B34: Open Weather | C34: mySchedule - Open Weather History Bulk (3 Years). One-off charge for historical capture of data. | D34: =SUM(E34,F34,G34) -> 6160 | E34: ='Dec 25'!G104 -> 6160 | F34: 0 | G34: 0
B35: Open Weather | C35: mySchedule - Open Weather Forecast Subscription & Actual History Prior Day. Fluctuates depending on usage, charged each month. | D35: =SUM(E35,F35,G35) -> 2745.6 | E35: ='Dec 25'!G105+'Jan - 26'!G105+'Feb - 26'!G105+'Mar - 26'!G105 -> 2745.6
B36: Report URL | C36: myJDW, Corporate, Hotels, Careers, Investors, Franchising, Careers - Content-Security-Policy-Report-Only, web application to restrict sources for JavaScript (and other resources, such as images or CSS). | D36: =SUM(E36,F36,G36) -> 1230 | E36: ='Oct 25'!G103+'Nov 25'!G103+'Dec 25'!G106+'Jan - 26'!G106+'Feb - 26'!G106+'Mar - 26'!G106 -> 1230
B37: WordPress Plugins | C37: myJDW, Corporate, Hotels, Careers, Investors, Franchising, Careers - To enhance Website functionality. Advanced Custom Fields PRO, Admin Columns Pro, Gravity Forms, Imagify, SearchWP, WP All Import Pro, WP Rocket, PersonalizeWP, WPMail SMTP Pro. Annual charge. | D37: =SUM(E37,F37,G37) -> 3750 | E37: ='Mar - 26'!F108 -> 1250 | F37: 1250 | G37: 1250
B38: Yoast SEO Premium | C38: Corporate, Hotels, Careers, Investors, Franchising - a paid version of the Yoast SEO plugin that provides advanced features to improve a website's search engine optimisation. | D38: =SUM(E38,F38,G38) -> 906 | E38: ='Jan - 26'!F110 -> 302 | F38: 302 | G38: 302
C39: TOTAL | D39: =SUM(D20:D38) -> 560785.83 | E39: =SUM(E20:E38) -> 102806.81 | F39: =SUM(F20:F38) -> 336749.23 | G39: =SUM(G20:G38) -> 121229.79 | H39: =SUM(E39:G39)-D39 -> 0
A41: JDW MANAGED 3rd PARTY SERVICES | D41: Feb 24 - Mar 26 | E41: Aug 25 - Mar 26 | F41: Aug 24 - Jul 25 | G41: Feb 24 - Jul 24
A42: JDW Third Party Costs (variable) | B42: AWS Cloud Services | C42: The AWS Cloud platforms used to host production and DR app environments - myJDW, mySchedule, Authentication, Order & Pay App, Customer Accounts, Suggested Rotas, ChatBot. From June 2025, a gradual shift was started to move test and UAT environments to a separate Filter AWS environment (noted above), starting with Customer App and progressing to People Apps. This is expected to run at c.£5,000 per month, and the JDW AWS account will adjust down accordingly. | D42: =SUM(E42:G42) -> 1165839.1 | E42: =(84451.51+72874.06+79704.83+85130+91071.27+84454.29+78024.34+79476.31)*0.74 -> 484838.09 | F42: 512651 | G42: 168350 | I42: We are unsure exactly how much JDW pay and how the Bytes discounts work.
B43: Sendbird | C43: The application used in myChat to enable communication between employees. Billed on a “Monthly Active User” basis, with various other thresholds. Note: Costs converted at an exchange rate of $1=£0.74 | D43: =SUM(E43:G43) -> 194766 | E43: =7491*8 -> 59928 | F43: =7491*12 -> 89892 | G43: =7491*6 -> 44946 | I43: Will be charged March 2026
B44: WP Engine | C44: WP Engine is a managed WordPress hosting platform for websites built on WordPress. Corporate, Hotels, Investors, Careers, Franchises. Billed on a quarterly basis, with set usage levels and various overage charges. 5 year contract, commenced May 2024. | D44: =SUM(E44:G44) -> 196078.8 | E44: =7513.74*8 -> 60109.92 | F44: =SUM(7513.74*12)+726 -> 90890.88 | G44: =7513*6 -> 45078 | I44: Note a credit will be issued for 1 months payment, due to service interruption.
C45: TOTAL | D45: =SUM(D42:D44) -> 1556683.9 | E45: =SUM(E42:E44) -> 604876.01 | F45: =SUM(F42:F44) -> 693433.88 | G45: =SUM(G42:G44) -> 258374 | H45: =SUM(E45+F45+G45)-D45 -> 0
A47: Supporting Notes
A48: 1 | B48: The partnership approach with Filter started in February 2024 | C48: Filter provides a comprehensive, fixed-price service model supporting all current and future products. The programme covers Research & Planning, Team Management, Customer and People operations, Business & Financial Controls, Franchising, Technology & Security, and Ongoing Support & Maintenance, delivered by a dedicated team.
A53: Potential Future costs or cost changes
A55: 1 | B55: Flagsmith | C55: The Flagsmith annual charge of £36,951.55 was billed in March 2026. This is the open-source feature flag service used across myJDW, mySchedule and Customer Order & Pay.

Sheet Summary
A1: Month: | C1: 45323 | D1: 45352 | E1: 45383 | F1: 45413 | G1: 45444 | H1: 45474 | I1: 45505 | J1: 45536 | K1: 45566 | L1: 45597 | M1: 45627 | N1: Running Total | O1: Check | Q1: 45658 | R1: 45689 | S1: 45717 | T1: 45748 | U1: 45778 | V1: 45809 | W1: 45839 | X1: 45870 | Y1: 45901 | Z1: 45931 | AA1: 45962 | AB1: 45992 | AC1: Running Total | AD1: Check | AF1: 46023 | AG1: 46054 | AH1: 46082 | AI1: Annual Running Total | AJ1: All Time Running Total | AL1: Check | AM1: Check
A3: Billing Amount (excl Third Party Services): | C3: ='Feb 24'!B3 -> 242579 | D3: ='Mar 24'!B3 -> 242579 | E3: ='Apr 24'!B3 -> 340813 | F3: ='May 24'!B3 -> 340813 | G3: ='Jun 24'!B3 -> 340813 | H3: ='Jul 24'!B3 -> 340813 | I3: ='Aug 24'!B3 -> 340813 | J3: ='Sep 24'!B3 -> 340813 | K3: ='Oct 24'!B3 -> 340813 | L3: ='Nov 24'!B3 -> 340813 | M3: ='Dec 24'!B3 -> 340813 | N3: =SUM(C3:M3) -> 3552475 | Q3: ='Jan 25'!B3 -> 340813 | R3: ='Feb 25'!B3 -> 340813 | S3: ='Mar 25'!B3 -> 340813 | T3: ='April 25'!B3 -> 340813 | U3: ='May 25'!B3 -> 340813 | V3: ='June 25'!B3 -> 340813 | W3: ='July 25'!B3 -> 340813 | X3: ='Aug 25'!B3 -> 340813 | Y3: ='Sep 25'!B3 -> 340813 | Z3: ='Oct 25'!B3 -> 353061 | AA3: ='Nov 25'!B3 -> 358179 | AB3: ='Dec 25'!B3 -> 378514 | AC3: =SUM(Q3:AB3) -> 4157071 | AF3: ='Jan - 26'!B3 -> 410756 | AG3: ='Feb - 26'!B3 -> 441376 | AH3: ='Mar - 26'!B3 -> 441376 | AI3: =+SUM(AF3,AG3,AH3) -> 1293508 | AJ3: =SUM(N3,AC3,AI3) -> 9003054 | AM3: =SUM(X3:AB3,AF3:AG3)-AM167 -> -441376
A4: Fixed Team Target Hours: | C4: ='Feb 24'!B4 -> 4016.25 | D4: ='Mar 24'!B4 -> 4016.25 | E4: ='Apr 24'!B4 -> 5984 | F4: ='May 24'!B4 -> 6256 | G4: ='Jun 24'!B4 -> 5440 | H4: ='Jul 24'!B4 -> 5984 | I4: ='Aug 24'!B4 -> 5984 | J4: ='Sep 24'!B4 -> 5712 | K4: ='Oct 24'!B4 -> 6256 | L4: ='Nov 24'!B4 -> 5712 | M4: ='Dec 24'!B4 -> 5984 | N4: =SUM(C4:M4) -> 61344.5 | Q4: ='Jan 25'!B4 -> 6256 | R4: ='Feb 25'!B4 -> 5440 | S4: ='Mar 25'!B4 -> 5712 | T4: ='April 25'!B4 -> 5984 | U4: ='May 25'!B4 -> 5984 | V4: ='June 25'!B4 -> 5712 | W4: ='July 25'!B4 -> 6256 | X4: ='Aug 25'!B4 -> 5712 | Y4: ='Sep 25'!B4 -> 5984 | Z4: ='Oct 25'!B4 -> 6549 | AA4: ='Nov 25'!B4 -> 5780 | AB4: ='Dec 25'!B4 -> 7038 | AC4: =SUM(Q4:AB4) -> 72407 | AF4: ='Jan - 26'!B4 -> 7480 | AG4: ='Feb - 26'!B4 -> 7310 | AH4: ='Mar - 26'!B4 -> 8041 | AI4: =SUM(AF4,AG4, AH4) -> 22831 | AJ4: =SUM(N4,AC4,AI4) -> 156582.5
A5: Fixed Team Recorded Hours: | C5: ='Feb 24'!B5 -> 4220.06 | D5: ='Mar 24'!B5 -> 4554.15 | E5: ='Apr 24'!B5 -> 5989.93 | F5: ='May 24'!B5 -> 6256.39 | G5: ='Jun 24'!B5 -> 5445.86 | H5: ='Jul 24'!B5 -> 6356.86 | I5: ='Aug 24'!B5 -> 6148.68 | J5: ='Sep 24'!B5 -> 5949.36 | K5: ='Oct 24'!B5 -> 6352.97 | L5: ='Nov 24'!B5 -> 5957.62 | M5: ='Dec 24'!B5 -> 6201.07 | N5: =SUM(C5:M5) -> 63432.95 | O5: =(D10+D61+C74)-N5 -> 0 | Q5: ='Jan 25'!B5 -> 6266.45 | R5: ='Feb 25'!B5 -> 5441.07 | S5: ='Mar 25'!B5 -> 5842.52 | T5: ='April 25'!B5 -> 6140.74 | U5: ='May 25'!B5 -> 6116.71 | V5: ='June 25'!B5 -> 5955.64 | W5: ='July 25'!B5 -> 6270.45 | X5: ='Aug 25'!B5 -> 5714.65 | Y5: ='Sep 25'!B5 -> 5995.92 | Z5: ='Oct 25'!B5 -> 6549.22 | AA5: ='Nov 25'!B5 -> 5784.74 | AB5: ='Dec 25'!B5 -> 7065.83 | AC5: =SUM(Q5:AB5) -> 73143.94 | AD5: =SUM(J10,J61,I74)-AC5 -> 0 | AF5: ='Jan - 26'!B5 -> 7539.75 | AG5: ='Feb - 26'!B5 -> 7346.48 | AH5: ='Mar - 26'!B5 -> 8047.028 | AI5: =SUM(AF5,AG5, AH5) -> 22933.258 | AJ5: =SUM(N5,AC5,AI5) -> 159510.15 | AK5: =SUM(P10+P61+O74)-AI5 -> 0 | AL5: =SUM(V10,V61,U74)-AJ5 -> 0
A6: Difference: | C6: ='Feb 24'!B6 -> 203.81 | D6: ='Mar 24'!B6 -> 537.9 | E6: ='Apr 24'!B6 -> 5.93 | F6: ='May 24'!B6 -> 0.39 | G6: ='Jun 24'!B6 -> 5.86 | H6: ='Jul 24'!B6 -> 372.86 | I6: ='Aug 24'!B6 -> 164.68 | J6: ='Sep 24'!B6 -> 237.36 | K6: ='Oct 24'!B6 -> 96.97 | L6: ='Nov 24'!B6 -> 245.62 | M6: ='Dec 24'!B6 -> 217.07 | N6: =SUM(C6:M6) -> 2088.45 | Q6: ='Jan 25'!B6 -> 10.45 | R6: ='Feb 25'!B6 -> 1.07 | S6: ='Mar 25'!B6 -> 130.52 | T6: ='April 25'!B6 -> 156.74 | U6: ='May 25'!B6 -> 132.71 | V6: ='June 25'!B6 -> 243.64 | W6: ='July 25'!B6 -> 14.45 | X6: ='Aug 25'!B6 -> 2.65 | Y6: ='Sep 25'!B6 -> 11.92 | Z6: ='Oct 25'!B6 -> 0.22 | AA6: ='Nov 25'!B6 -> 4.74 | AB6: ='Dec 25'!B6 -> 27.83 | AC6: =SUM(Q6:AB6) -> 736.94 | AF6: ='Jan - 26'!B6 -> 59.75 | AG6: ='Feb - 26'!B6 -> 36.48 | AH6: ='Mar - 26'!B6 -> 6.028 | AI6: =SUM(AF6,AG6, AH6) -> 102.258 | AJ6: =SUM(N6,AC6,AI6) -> 2927.648
A9: 2024 Programme Management | B9: Project Code | C9: Forecasted Hours | D9: Actual Hours | E9: Difference | G9: 2025 Programme Management | H9: Project Code | I9: Forecasted Hours | J9: Actual Hours | K9: Difference | M9: 2026 Programme Management | N9: Project Code | O9: Forecasted Hours | P9: Actual Hours | Q9: Difference | S9: Total Programme Management | T9: Project Code | U9: Forecasted Hours | V9: Actual Hours | W9: Difference
D10: =SUM('Feb 24'!S13)+('Mar 24'!T13)+('Apr 24'!T13)+('May 24'!T13)+('Jun 24'!T13)+('Jul 24'!T13)+('Aug 24'!T13)+('Sep 24'!T13)+('Oct 24'!T13)+('Nov 24'!T13)+('Dec 24'!T13) -> 20948.54 | J10: ='Jan 25'!T13+'Feb 25'!T13+'Mar 25'!T13+'April 25'!T13+'May 25'!T13+'June 25'!T13+'July 25'!T13+'Aug 25'!T13+'Sep 25'!T13+'Oct 25'!T13+'Nov 25'!T13+'Dec 25'!T13 -> 22751.6 | P10: =SUM('Jan - 26'!T13, 'Feb - 26'!T13, 'Mar - 26'!T13) -> 5595.358 | V10: =SUM(D10, J10,P10) -> 49295.498
A12: Reasearch & Planning | D12: =SUM('Feb 24'!C13:H13,'Feb 24'!J13)+SUM('Mar 24'!C13:H13,'Mar 24'!J13)+SUM('Apr 24'!C13:H13,'Apr 24'!J13)+SUM('May 24'!C13:H13,'May 24'!J13)+SUM('Jun 24'!C13:H13,'Jun 24'!J13)+SUM('Jul 24'!C13:H13,'Jul 24'!J13)+SUM('Aug 24'!C13:H13,'Aug 24'!J13)+SUM('Sep 24'!C13:H13,'Sep 24'!J13)+SUM('Oct 24'!C13:H13,'Oct 24'!J13)+SUM('Nov 24'!C13:H13,'Nov 24'!J13)+SUM('Dec 24'!C13:H13,'Dec 24'!J13) -> 6781.02 | G12: Reasearch & Planning | J12: =SUM('Jan 25'!C13,'Jan 25'!D13,'Jan 25'!E13,'Jan 25'!F13,'Jan 25'!G13,'Jan 25'!H13,'Jan 25'!J13)+ SUM('Feb 25'!C13,'Feb 25'!D13,'Feb 25'!E13,'Feb 25'!F13,'Feb 25'!G13,'Feb 25'!H13,'Feb 25'!J13)+ SUM('Mar 25'!C13,'Mar 25'!D13,'Mar 25'!E13,'Mar 25'!F13,'Mar 25'!G13,'Mar 25'!H13,'Mar 25'!J13)+ SUM('April 25'!C13,'April 25'!D13,'April 25'!E13,'April 25'!F13,'April 25'!G13,'April 25'!H13,'April 25'!J13)+SUM('May 25'!C13,'May 25'!D13,'May 25'!E13,'May 25'!F13,'May 25'!G13,'May 25'!H13,'May 25'!J13)+SUM('June 25'!C13,'June 25'!D13,'June 25'!F13,'June 25'!G13,'June 25'!H13,'June 25'!J13)+SUM('July 25'!C13,'July 25'!D13,'July 25'!E13,'July 25'!F13,'July 25'!G13,'July 25'!H13,'July 25'!J13)+SUM('Aug 25'!C13,'Aug 25'!D13,'Aug 25'!E13,'Aug 25'!F13,'Aug 25'!G13,'Aug 25'!H13,'Aug 25'!J13)+SUM('Sep 25'!C13,'Sep 25'!D13,'Sep 25'!F13,'Sep 25'!G13,'Sep 25'!H13,'Sep 25'!J13)+SUM('Oct 25'!C13,'Oct 25'!D13,'Oct 25'!E13,'Oct 25'!F13,'Oct 25'!G13,'Oct 25'!H13,'Oct 25'!J13)+SUM('Nov 25'!C13,'Nov 25'!D13,'Nov 25'!F13,'Nov 25'!G13,'Nov 25'!H13,'Nov 25'!J13)+SUM('Dec 25'!C13,'Dec 25'!D13,'Dec 25'!E13,'Dec 25'!F13,'Dec 25'!G13,'Dec 25'!H13,'Dec 25'!J13) -> 4650.41 | M12: Reasearch & Planning | P12: =SUM('Jan - 26'!C13,'Jan - 26'!D13,'Jan - 26'!E13,'Jan - 26'!F13,'Jan - 26'!G13,'Jan - 26'!H13,'Jan - 26'!J13)+SUM('Feb - 26'!C13,'Feb - 26'!D13,'Feb - 26'!E13,'Feb - 26'!F13,'Feb - 26'!G13,'Feb - 26'!H13,'Feb - 26'!J13)+SUM('Mar - 26'!C13,'Mar - 26'!D13,'Mar - 26'!F13,'Mar - 26'!G13,'Mar - 26'!J13) -> 1123.238 | S12: Reasearch & Planning | V12: =SUM(D12, J12+P12) -> 12554.668
A13: Includes industry research, feasibility and strategic design activities, programme management, financial management, strategic and senior meetings & reporting.
A15: Team Management Costs | D15: =SUM('Feb 24'!I13,'Feb 24'!K13,'Feb 24'!L13,'Feb 24'!M13,'Feb 24'!N13,'Feb 24'!O13,'Feb 24'!P13,'Feb 24'!Q13,'Feb 24'!R13)+SUM('Mar 24'!I13,'Mar 24'!K13,'Mar 24'!L13,'Mar 24'!M13,'Mar 24'!N13,'Mar 24'!O13,'Mar 24'!P13,'Mar 24'!Q13,'Mar 24'!R13,'Mar 24'!S13)+SUM('Apr 24'!I13,'Apr 24'!K13,'Apr 24'!L13,'Apr 24'!M13,'Apr 24'!N13,'Apr 24'!O13,'Apr 24'!P13,'Apr 24'!Q13,'Apr 24'!R13,'Apr 24'!S13)+SUM('May 24'!I13,'May 24'!K13,'May 24'!L13,'May 24'!M13,'May 24'!N13,'May 24'!O13,'May 24'!P13,'May 24'!Q13,'May 24'!R13,'May 24'!S13)+SUM('Jun 24'!I13,'Jun 24'!K13,'Jun 24'!L13,'Jun 24'!M13,'Jun 24'!N13,'Jun 24'!O13,'Jun 24'!P13,'Jun 24'!Q13,'Jun 24'!R13,'Jun 24'!S13)+SUM('Jul 24'!I13,'Jul 24'!K13,'Jul 24'!L13,'Jul 24'!M13,'Jul 24'!N13,'Jul 24'!O13,'Jul 24'!P13,'Jul 24'!Q13,'Jul 24'!R13,'Jul 24'!S13)+SUM('Aug 24'!I13,'Aug 24'!K13,'Aug 24'!L13,'Aug 24'!M13,'Aug 24'!N13,'Aug 24'!O13,'Aug 24'!P13,'Aug 24'!Q13,'Aug 24'!R13,'Aug 24'!S13)+SUM('Sep 24'!I13,'Sep 24'!K13,'Sep 24'!L13,'Sep 24'!M13,'Sep 24'!N13,'Sep 24'!O13,'Sep 24'!P13,'Sep 24'!Q13,'Sep 24'!R13,'Sep 24'!S13)+SUM('Oct 24'!I13,'Oct 24'!K13,'Oct 24'!L13,'Oct 24'!M13,'Oct 24'!N13,'Oct 24'!O13,'Oct 24'!P13,'Oct 24'!Q13,'Oct 24'!R13,'Oct 24'!S13)+SUM('Nov 24'!I13,'Nov 24'!K13,'Nov 24'!L13,'Nov 24'!M13,'Nov 24'!N13,'Nov 24'!O13,'Nov 24'!P13,'Nov 24'!Q13,'Nov 24'!R13,'Nov 24'!S13)+SUM('Dec 24'!I13,'Dec 24'!K13,'Dec 24'!L13,'Dec 24'!M13,'Dec 24'!N13,'Dec 24'!O13,'Dec 24'!P13,'Dec 24'!Q13,'Dec 24'!R13,'Dec 24'!S13) -> 14167.52 | G15: Team Management Costs | J15: =SUM('Jan 25'!I13,'Jan 25'!K13,'Jan 25'!L13,'Jan 25'!M13,'Jan 25'!N13,'Jan 25'!O13,'Jan 25'!P13,'Jan 25'!Q13,'Jan 25'!R13,'Jan 25'!S13)+ SUM('Feb 25'!I13,'Feb 25'!K13,'Feb 25'!L13,'Feb 25'!M13,'Feb 25'!N13,'Feb 25'!O13,'Feb 25'!P13,'Feb 25'!Q13,'Feb 25'!R13,'Feb 25'!S13)+ SUM('Mar 25'!I13,'Mar 25'!K13,'Mar 25'!L13,'Mar 25'!M13,'Mar 25'!N13,'Mar 25'!O13,'Mar 25'!P13,'Mar 25'!Q13,'Mar 25'!R13,'Mar 25'!S13)+ SUM('April 25'!I13,'April 25'!K13,'April 25'!L13,'April 25'!M13,'April 25'!N13,'April 25'!O13,'April 25'!P13,'April 25'!Q13,'April 25'!R13,'April 25'!S13)+SUM('May 25'!I13,'May 25'!K13,'May 25'!L13,'May 25'!M13,'May 25'!N13,'May 25'!O13,'May 25'!P13,'May 25'!Q13,'May 25'!S13)+SUM('June 25'!I13,'June 25'!K13,'June 25'!M13,'June 25'!N13,'June 25'!O13,'June 25'!P13,'June 25'!R13,'June 25'!S13)+SUM('July 25'!I13,'July 25'!K13,'July 25'!L13,'July 25'!M13,'July 25'!N13,'July 25'!O13,'July 25'!P13,'July 25'!Q13,'July 25'!R13,'July 25'!S13)+SUM('Aug 25'!I13,'Aug 25'!K13,'Aug 25'!L13,'Aug 25'!M13,'Aug 25'!N13,'Aug 25'!O13,'Aug 25'!P13,'Aug 25'!Q13,'Aug 25'!R13,'Aug 25'!S13)+SUM('Sep 25'!I13,'Sep 25'!K13,'Sep 25'!L13,'Sep 25'!M13,'Sep 25'!N13,'Sep 25'!O13,'Sep 25'!P13,'Sep 25'!R13,'Sep 25'!S13)+SUM('Oct 25'!I13,'Oct 25'!K13,'Oct 25'!L13,'Oct 25'!M13,'Oct 25'!N13,'Oct 25'!O13,'Oct 25'!P13,'Oct 25'!Q13,'Oct 25'!R13,'Oct 25'!S13)+SUM('Nov 25'!I13,'Nov 25'!K13,'Nov 25'!L13,'Nov 25'!M13,'Nov 25'!N13,'Nov 25'!O13,'Nov 25'!P13,'Nov 25'!R13)+SUM('Dec 25'!I13,'Dec 25'!K13,'Dec 25'!L13,'Dec 25'!M13,'Dec 25'!N13,'Dec 25'!O13,'Dec 25'!P13,'Dec 25'!Q13,'Dec 25'!R13,'Dec 25'!S13) -> 18101.19 | M15: Team Management Costs | P15: =SUM('Jan - 26'!I13,'Jan - 26'!K13,'Jan - 26'!L13,'Jan - 26'!M13,'Jan - 26'!N13,'Jan - 26'!O13,'Jan - 26'!P13,'Jan - 26'!Q13,'Jan - 26'!R13,'Jan - 26'!S13)+SUM('Feb - 26'!I13,'Feb - 26'!K13,'Feb - 26'!L13,'Feb - 26'!M13,'Feb - 26'!N13,'Feb - 26'!O13,'Feb - 26'!P13,'Feb - 26'!Q13,'Feb - 26'!R13,'Feb - 26'!S13)+SUM('Mar - 26'!I13,'Mar - 26'!K13,'Mar - 26'!L13,'Mar - 26'!M13,'Mar - 26'!N13,'Mar - 26'!O13,'Mar - 26'!P13,'Mar - 26'!R13,'Mar - 26'!S13) -> 4472.12 | S15: Team Management Costs | V15: =SUM(D15, J15,P15) -> 36740.83
A16: Includes staff recruitment, training, holidays, sick, other absences, travel and breaks for the equivalent of 32 full time Filter employees working on JDW related activities.
C17: Check | D17: =SUM(D12,D15)-D10 -> 0 | I17: Check | J17: =SUM(J15,J12)-J10 -> 0 | O17: Check | P17: =SUM(P15+P12)-P10 -> 0 | U17: Check | V17: =SUM(V15+V12)-V10 -> 0
A20: 2024 Projects | B20: Project Code | C20: Forecasted Hours | D20: Actual Hours | E20: Difference | G20: 2025 Projects | H20: Project Code | I20: Forecasted Hours | J20: Actual Hours | K20: Difference | M20: 2026 Projects | N20: Project Code | O20: Forecasted Hours | P20: Actual Hours | Q20: Difference | S20: Total Projects | T20: Project Code | U20: Forecasted Hours | V20: Actual Hours | W20: Difference
A21: Allergens Service | B21: I-000300 | D21: ='Feb 24'!J17+'Mar 24'!J17+'Apr 24'!J17+'May 24'!J17+'Jun 24'!J17+'Jul 24'!J17+'Aug 24'!J17+'Sep 24'!J17+'Oct 24'!J17+'Nov 24'!J17+'Dec 24'!J17 -> 511.58 | G21: Allergens Service | H21: I-000300 | J21: ='Jan 25'!J17+'Feb 25'!J17+'Mar 25'!J17+'April 25'!J17+'May 25'!J17+'June 25'!J17+'July 25'!J17+'Aug 25'!J17+'Sep 25'!J17+'Oct 25'!J17+'Nov 25'!J17+'Dec 25'!J17 -> 0 | M21: Allergens Service | N21: I-000300 | P21: =SUM('Jan - 26'!J17, 'Feb - 26'!J17,'Mar - 26'!J17) -> 0 | S21: Allergens Service | T21: I-000300 | V21: =SUM(D21,J21,P21) -> 511.58
A22: Authentication | B22: I-000312 | D22: ='Feb 24'!J18+'Mar 24'!J18+'Apr 24'!J18+'May 24'!J18+'Jun 24'!J18+'Jul 24'!J18+'Aug 24'!J18+'Sep 24'!J18+'Oct 24'!J18+'Nov 24'!J18+'Dec 24'!J18 -> 2038.87 | G22: Authentication | H22: I-000312 | J22: ='Jan 25'!J18+'Feb 25'!J18+'Mar 25'!J18+'April 25'!J18+'May 25'!J18+'June 25'!J18+'July 25'!J18+'Aug 25'!J18+'Sep 25'!J18+'Oct 25'!J18+'Nov 25'!J18+'Dec 25'!J18 -> 2693.56 | M22: Authentication | N22: I-000312 | P22: =SUM('Jan - 26'!J18, 'Feb - 26'!J18,'Mar - 26'!J18) -> 246.66 | S22: Authentication | T22: I-000312 | V22: =SUM(D22,J22,P22) -> 4979.09
A23: Available Ales on TV Screens | D23: ='Feb 24'!J19+'Mar 24'!J19+'Apr 24'!J19+'May 24'!J19+'Jun 24'!J19+'Jul 24'!J19+'Aug 24'!J19+'Sep 24'!J19+'Oct 24'!J19+'Nov 24'!J19+'Dec 24'!J19 -> 0 | G23: Available Ales on TV Screens | J23: ='Jan 25'!J19+'Feb 25'!J19+'Mar 25'!J19+'April 25'!J19+'May 25'!J19+'June 25'!J19+'July 25'!J19+'Aug 25'!J19+'Sep 25'!J19+'Oct 25'!J19+'Nov 25'!J19+'Dec 25'!J19 -> 65.33 | M23: Available Ales on TV Screens | P23: =SUM('Jan - 26'!J19, 'Feb - 26'!J19,'Mar - 26'!J19) -> 0 | S23: Available Ales on TV Screens | V23: =SUM(D23,J23,P23) -> 65.33
A24: Customer Information Screens | B24: I-000313 | D24: ='Feb 24'!J20+'Mar 24'!J20+'Apr 24'!J20+'May 24'!J20+'Jun 24'!J20+'Jul 24'!J20+'Aug 24'!J20+'Sep 24'!J20+'Oct 24'!J20+'Nov 24'!J20+'Dec 24'!J20 -> 418.91 | G24: Customer Information Screens | H24: I-000313 | J24: ='Jan 25'!J20+'Feb 25'!J20+'Mar 25'!J20+'April 25'!J20+'May 25'!J20+'June 25'!J20+'July 25'!J20+'Aug 25'!J20+'Sep 25'!J20+'Oct 25'!J20+'Nov 25'!J20+'Dec 25'!J20 -> 43.42 | M24: Customer Information Screens | N24: I-000313 | P24: =SUM('Jan - 26'!J20, 'Feb - 26'!J20,'Mar - 26'!J20) -> 1.25 | S24: Customer Information Screens | T24: I-000313 | V24: =SUM(D24,J24,P24) -> 463.58
A25: Corporate Website Replatform Build | B25: I-000300 | D25: ='Feb 24'!J21+'Mar 24'!J21+'Apr 24'!J21+'May 24'!J21+'Jun 24'!J21+'Jul 24'!J21+'Aug 24'!J21+'Sep 24'!J21+'Oct 24'!J21+'Nov 24'!J21+'Dec 24'!J21 -> 1786.84 | G25: Corporate Website Replatform Build | H25: I-000300 | J25: ='Jan 25'!J21+'Feb 25'!J21+'Mar 25'!J21+'April 25'!J21+'May 25'!J21+'June 25'!J21+'July 25'!J21+'Aug 25'!J21+'Sep 25'!J21+'Oct 25'!J21+'Nov 25'!J21+'Dec 25'!J21 -> 1.75 | M25: Corporate Website Replatform Build | N25: I-000300 | P25: =SUM('Jan - 26'!J21, 'Feb - 26'!J21,'Mar - 26'!J21) -> 0 | S25: Corporate Website Replatform Build | T25: I-000300 | V25: =SUM(D25,J25,P25) -> 1788.59
A26: Customer Accounts Planning | B26: I-000311 | D26: ='Feb 24'!J22+'Mar 24'!J22+'Apr 24'!J22+'May 24'!J22+'Jun 24'!J22+'Jul 24'!J22+'Aug 24'!J22+'Sep 24'!J22+'Oct 24'!J22+'Nov 24'!J22+'Dec 24'!J22 -> 1152.32 | G26: Customer Accounts Planning | H26: I-000311 | J26: ='Jan 25'!J22+'Feb 25'!J22+'Mar 25'!J22+'April 25'!J22+'May 25'!J22+'June 25'!J22+'July 25'!J22+'Aug 25'!J22+'Sep 25'!J22+'Oct 25'!J22+'Nov 25'!J22+'Dec 25'!J22 -> 1261.2 | M26: Customer Accounts Planning | N26: I-000311 | P26: =SUM('Jan - 26'!J22, 'Feb - 26'!J22,'Mar - 26'!J22) -> 34 | S26: Customer Accounts Planning | T26: I-000311 | V26: =SUM(D26,J26,P26) -> 2447.52
A27: Customer App - Ibersol Franchise Integration | D27: ='Feb 24'!J23+'Mar 24'!J23+'Apr 24'!J23+'May 24'!J23+'Jun 24'!J23+'Jul 24'!J23+'Aug 24'!J23+'Sep 24'!J23+'Oct 24'!J23+'Nov 24'!J23+'Dec 24'!J23 -> 0 | G27: Customer App - Ibersol Franchise Integration | J27: ='Jan 25'!J23+'Feb 25'!J23+'Mar 25'!J23+'April 25'!J23+'May 25'!J23+'June 25'!J23+'July 25'!J23+'Aug 25'!J23+'Sep 25'!J23+'Oct 25'!J23+'Nov 25'!J23+'Dec 25'!J23 -> 0 | M27: Customer App - Ibersol Franchise Integration | P27: =SUM('Jan - 26'!J23, 'Feb - 26'!J23,'Mar - 26'!J23) -> 137.83 | S27: Customer App - Ibersol Franchise Integration | V27: =SUM(D27,J27,P27) -> 137.83
A28: Customer App - Lagardere Franchise Integration | D28: ='Feb 24'!J24+'Mar 24'!J24+'Apr 24'!J24+'May 24'!J24+'Jun 24'!J24+'Jul 24'!J24+'Aug 24'!J24+'Sep 24'!J24+'Oct 24'!J24+'Nov 24'!J24+'Dec 24'!J24 -> 0 | G28: Customer App - Lagardere Franchise Integration | J28: ='Jan 25'!J24+'Feb 25'!J24+'Mar 25'!J24+'April 25'!J24+'May 25'!J24+'June 25'!J24+'July 25'!J24+'Aug 25'!J24+'Sep 25'!J24+'Oct 25'!J24+'Nov 25'!J24+'Dec 25'!J24 -> 0 | M28: Customer App - Lagardere Franchise Integration | P28: =SUM('Jan - 26'!J24, 'Feb - 26'!J24,'Mar - 26'!J24) -> 493.41 | S28: Customer App - Lagardere Franchise Integration | V28: =SUM(D28,J28,P28) -> 493.41
A29: Customer App / PWA / App Manager | B29: I-000287 | D29: ='Feb 24'!J25+'Mar 24'!J25+'Apr 24'!J25+'May 24'!J25+'Jun 24'!J25+'Jul 24'!J25+'Aug 24'!J25+'Sep 24'!J25+'Oct 24'!J25+'Nov 24'!J25+'Dec 24'!J25 -> 15632.11 | G29: Customer App / PWA / App Manager | H29: I-000287 | J29: ='Jan 25'!J25+'Feb 25'!J25+'Mar 25'!J25+'April 25'!J25+'May 25'!J25+'June 25'!J25+'July 25'!J25+'Aug 25'!J25+'Sep 25'!J25+'Oct 25'!J25+'Nov 25'!J25+'Dec 25'!J25 -> 11613.94 | M29: Customer App / PWA / App Manager | N29: I-000287 | P29: =SUM('Jan - 26'!J25, 'Feb - 26'!J25,'Mar - 26'!J25) -> 4297.95 | S29: Customer App / PWA / App Manager | T29: I-000287 | V29: =SUM(D29,J29,P29) -> 31544
A30: Customer App UX/UI Redesign | D30: ='Feb 24'!J26+'Mar 24'!J26+'Apr 24'!J26+'May 24'!J26+'Jun 24'!J26+'Jul 24'!J26+'Aug 24'!J26+'Sep 24'!J26+'Oct 24'!J26+'Nov 24'!J26+'Dec 24'!J26 -> 0 | G30: Customer App UX/UI Redesign | J30: ='Jan 25'!J26+'Feb 25'!J26+'Mar 25'!J26+'April 25'!J26+'May 25'!J26+'June 25'!J26+'July 25'!J26+'Aug 25'!J26+'Sep 25'!J26+'Oct 25'!J26+'Nov 25'!J26+'Dec 25'!J26 -> 938.24 | M30: Customer App UX/UI Redesign | P30: =SUM('Jan - 26'!J26, 'Feb - 26'!J26,'Mar - 26'!J26) -> 843.94 | S30: Customer App UX/UI Redesign | V30: =SUM(D30,J30,P30) -> 1782.18
A31: Customer Planning | D31: ='Feb 24'!J27+'Mar 24'!J27+'Apr 24'!J27+'May 24'!J27+'Jun 24'!J27+'Jul 24'!J27+'Aug 24'!J27+'Sep 24'!J27+'Oct 24'!J27+'Nov 24'!J27+'Dec 24'!J27 -> 0 | G31: Customer Planning | J31: ='Jan 25'!J27+'Feb 25'!J27+'Mar 25'!J27+'April 25'!J27+'May 25'!J27+'June 25'!J27+'July 25'!J27+'Aug 25'!J27+'Sep 25'!J27+'Oct 25'!J27+'Nov 25'!J27+'Dec 25'!J27 -> 0 | M31: Customer Planning | P31: =SUM('Jan - 26'!J27, 'Feb - 26'!J27,'Mar - 26'!J27) -> 0 | S31: Customer Planning | V31: =SUM(D31,J31,P31) -> 0
A32: Digital Pub Records | B32: I-000314 | D32: ='Feb 24'!J28+'Mar 24'!J28+'Apr 24'!J28+'May 24'!J28+'Jun 24'!J28+'Jul 24'!J28+'Aug 24'!J28+'Sep 24'!J28+'Oct 24'!J28+'Nov 24'!J28+'Dec 24'!J28 -> 624.27 | G32: Digital Pub Records | H32: I-000314 | J32: ='Jan 25'!J28+'Feb 25'!J28+'Mar 25'!J28+'April 25'!J28+'May 25'!J28+'June 25'!J28+'July 25'!J28+'Aug 25'!J28+'Sep 25'!J28+'Oct 25'!J28+'Nov 25'!J28+'Dec 25'!J28 -> 2846.78 | M32: Digital Pub Records | N32: I-000314 | P32: =SUM('Jan - 26'!J28, 'Feb - 26'!J28,'Mar - 26'!J28) -> 0 | S32: Digital Pub Records | T32: I-000314 | V32: =SUM(D32,J32,P32) -> 3471.05
A33: Digital Vouchers | D33: ='Feb 24'!J29+'Mar 24'!J29+'Apr 24'!J29+'May 24'!J29+'Jun 24'!J29+'Jul 24'!J29+'Aug 24'!J29+'Sep 24'!J29+'Oct 24'!J29+'Nov 24'!J29+'Dec 24'!J29 -> 0 | G33: Digital Vouchers | J33: ='Jan 25'!J29+'Feb 25'!J29+'Mar 25'!J29+'April 25'!J29+'May 25'!J29+'June 25'!J29+'July 25'!J29+'Aug 25'!J29+'Sep 25'!J29+'Oct 25'!J29+'Nov 25'!J29+'Dec 25'!J29 -> 341.17 | M33: Digital Vouchers | P33: =SUM('Jan - 26'!J29, 'Feb - 26'!J29,'Mar - 26'!J29) -> 221.43 | S33: Digital Vouchers | V33: =SUM(D33,J33,P33) -> 562.6
A34: Disaster Recovery & Business Continuity | B34: I-000315 | D34: ='Feb 24'!J30+'Mar 24'!J30+'Apr 24'!J30+'May 24'!J30+'Jun 24'!J30+'Jul 24'!J30+'Aug 24'!J30+'Sep 24'!J30+'Oct 24'!J30+'Nov 24'!J30+'Dec 24'!J30 -> 63.25 | G34: Disaster Recovery & Business Continuity | H34: I-000315 | J34: ='Jan 25'!J30+'Feb 25'!J30+'Mar 25'!J30+'April 25'!J30+'May 25'!J30+'June 25'!J30+'July 25'!J30+'Aug 25'!J30+'Sep 25'!J30+'Oct 25'!J30+'Nov 25'!J30+'Dec 25'!J30 -> 128.1 | M34: Disaster Recovery & Business Continuity | N34: I-000315 | P34: =SUM('Jan - 26'!J30, 'Feb - 26'!J30,'Mar - 26'!J30) -> 77.34 | S34: Disaster Recovery & Business Continuity | T34: I-000315 | V34: =SUM(D34,J34,P34) -> 268.69
A35: Employee Digital Record | B35: I-000316 | D35: ='Feb 24'!J31+'Mar 24'!J31+'Apr 24'!J31+'May 24'!J31+'Jun 24'!J31+'Jul 24'!J31+'Aug 24'!J31+'Sep 24'!J31+'Oct 24'!J31+'Nov 24'!J31+'Dec 24'!J31 -> 601.93 | G35: Employee Digital Record | H35: I-000316 | J35: ='Jan 25'!J31+'Feb 25'!J31+'Mar 25'!J31+'April 25'!J31+'May 25'!J31+'June 25'!J31+'July 25'!J31+'Aug 25'!J31+'Sep 25'!J31+'Oct 25'!J31+'Nov 25'!J31+'Dec 25'!J31 -> 1714.44 | M35: Employee Digital Record | N35: I-000316 | P35: =SUM('Jan - 26'!J31, 'Feb - 26'!J31,'Mar - 26'!J31) -> 433.08 | S35: Employee Digital Record | T35: I-000316 | V35: =SUM(D35,J35,P35) -> 2749.45
A36: Employee Verification (with WISDOM) | B36: I-000274 | D36: ='Feb 24'!J32+'Mar 24'!J32+'Apr 24'!J32+'May 24'!J32+'Jun 24'!J32+'Jul 24'!J32+'Aug 24'!J32+'Sep 24'!J32+'Oct 24'!J32+'Nov 24'!J32+'Dec 24'!J32 -> 243.93 | G36: Employee Verification (with WISDOM) | H36: I-000274 | J36: ='Jan 25'!J32+'Feb 25'!J32+'Mar 25'!J32+'April 25'!J32+'May 25'!J32+'June 25'!J32+'July 25'!J32+'Aug 25'!J32+'Sep 25'!J32+'Oct 25'!J32+'Nov 25'!J32+'Dec 25'!J32 -> 0 | M36: Employee Verification (with WISDOM) | N36: I-000274 | P36: =SUM('Jan - 26'!J32, 'Feb - 26'!J32,'Mar - 26'!J32) -> 0 | S36: Employee Verification (with WISDOM) | T36: I-000274 | V36: =SUM(D36,J36,P36) -> 243.93
A37: Franchises Customer App | D37: ='Feb 24'!J33+'Mar 24'!J33+'Apr 24'!J33+'May 24'!J33+'Jun 24'!J33+'Jul 24'!J33+'Aug 24'!J33+'Sep 24'!J33+'Oct 24'!J33+'Nov 24'!J33+'Dec 24'!J33 -> 1064.78 | G37: Franchises Customer App | J37: ='Jan 25'!J33+'Feb 25'!J33+'Mar 25'!J33+'April 25'!J33+'May 25'!J33+'June 25'!J33+'July 25'!J33+'Aug 25'!J33+'Sep 25'!J33+'Oct 25'!J33+'Nov 25'!J33+'Dec 25'!J33 -> 4007.58 | M37: Franchises Customer App | P37: =SUM('Jan - 26'!J33, 'Feb - 26'!J33,'Mar - 26'!J33) -> 915.72 | S37: Franchises Customer App | V37: =SUM(D37,J37,P37) -> 5988.08
A38: Franchises myJDW | D38: ='Feb 24'!J34+'Mar 24'!J34+'Apr 24'!J34+'May 24'!J34+'Jun 24'!J34+'Jul 24'!J34+'Aug 24'!J34+'Sep 24'!J34+'Oct 24'!J34+'Nov 24'!J34+'Dec 24'!J34 -> 1.5 | G38: Franchises myJDW | J38: ='Jan 25'!J34+'Feb 25'!J34+'Mar 25'!J34+'April 25'!J34+'May 25'!J34+'June 25'!J34+'July 25'!J34+'Aug 25'!J34+'Sep 25'!J34+'Oct 25'!J34+'Nov 25'!J34+'Dec 25'!J34 -> 264.61 | M38: Franchises myJDW | P38: =SUM('Jan - 26'!J34, 'Feb - 26'!J34,'Mar - 26'!J34) -> 1821.89 | S38: Franchises myJDW | V38: =SUM(D38,J38,P38) -> 2088
A39: Franchises mySchedule | D39: ='Feb 24'!J35+'Mar 24'!J35+'Apr 24'!J35+'May 24'!J35+'Jun 24'!J35+'Jul 24'!J35+'Aug 24'!J35+'Sep 24'!J35+'Oct 24'!J35+'Nov 24'!J35+'Dec 24'!J35 -> 2 | G39: Franchises mySchedule | J39: ='Jan 25'!J35+'Feb 25'!J35+'Mar 25'!J35+'April 25'!J35+'May 25'!J35+'June 25'!J35+'July 25'!J35+'Aug 25'!J35+'Sep 25'!J35+'Oct 25'!J35+'Nov 25'!J35+'Dec 25'!J35 -> 52.25 | M39: Franchises mySchedule | P39: =SUM('Jan - 26'!J35, 'Feb - 26'!J35,'Mar - 26'!J35) -> 153.73 | S39: Franchises mySchedule | V39: =SUM(D39,J39,P39) -> 207.98
A40: Franchises WordPress Websites | D40: ='Feb 24'!J36+'Mar 24'!J36+'Apr 24'!J36+'May 24'!J36+'Jun 24'!J36+'Jul 24'!J36+'Aug 24'!J36+'Sep 24'!J36+'Oct 24'!J36+'Nov 24'!J36+'Dec 24'!J36 -> 0 | G40: Franchises WordPress Websites | J40: ='Jan 25'!J36+'Feb 25'!J36+'Mar 25'!J36+'April 25'!J36+'May 25'!J36+'June 25'!J36+'July 25'!J36+'Aug 25'!J36+'Sep 25'!J36+'Oct 25'!J36+'Nov 25'!J36+'Dec 25'!J36 -> 0 | M40: Franchises WordPress Websites | P40: =SUM('Jan - 26'!J36, 'Feb - 26'!J36,'Mar - 26'!J36) -> 114.33 | S40: Franchises WordPress Websites | V40: =SUM(D40,J40,P40) -> 114.33
A41: Hotels HLS Integration | D41: ='Feb 24'!J37+'Mar 24'!J37+'Apr 24'!J37+'May 24'!J37+'Jun 24'!J37+'Jul 24'!J37+'Aug 24'!J37+'Sep 24'!J37+'Oct 24'!J37+'Nov 24'!J37+'Dec 24'!J37 -> 0 | G41: Hotels HLS Integration | J41: ='Jan 25'!J37+'Feb 25'!J37+'Mar 25'!J37+'April 25'!J37+'May 25'!J37+'June 25'!J37+'July 25'!J37+'Aug 25'!J37+'Sep 25'!J37+'Oct 25'!J37+'Nov 25'!J37+'Dec 25'!J37 -> 122.18 | M41: Hotels HLS Integration | P41: =SUM('Jan - 26'!J37, 'Feb - 26'!J37,'Mar - 26'!J37) -> 15.75 | S41: Hotels HLS Integration | V41: =SUM(D41,J41,P41) -> 137.93
A42: Hotels Price Comparison | B42: I-000317 | D42: ='Feb 24'!J38+'Mar 24'!J38+'Apr 24'!J38+'May 24'!J38+'Jun 24'!J38+'Jul 24'!J38+'Aug 24'!J38+'Sep 24'!J38+'Oct 24'!J38+'Nov 24'!J38+'Dec 24'!J38 -> 3.5 | G42: Hotels Price Comparison | H42: I-000317 | J42: ='Jan 25'!J38+'Feb 25'!J38+'Mar 25'!J38+'April 25'!J38+'May 25'!J38+'June 25'!J38+'July 25'!J38+'Aug 25'!J38+'Sep 25'!J38+'Oct 25'!J38+'Nov 25'!J38+'Dec 25'!J38 -> 0 | M42: Hotels Price Comparison | N42: I-000317 | P42: =SUM('Jan - 26'!J38, 'Feb - 26'!J38,'Mar - 26'!J38) -> 0 | S42: Hotels Price Comparison | T42: I-000317 | V42: =SUM(D42,J42,P42) -> 3.5
A43: Intelligence PoC | B43: I-000318 | D43: ='Feb 24'!J39+'Mar 24'!J39+'Apr 24'!J39+'May 24'!J39+'Jun 24'!J39+'Jul 24'!J39+'Aug 24'!J39+'Sep 24'!J39+'Oct 24'!J39+'Nov 24'!J39+'Dec 24'!J39 -> 1188.79 | G43: Intelligence PoC | H43: I-000318 | J43: ='Jan 25'!J39+'Feb 25'!J39+'Mar 25'!J39+'April 25'!J39+'May 25'!J39+'June 25'!J39+'July 25'!J39+'Aug 25'!J39+'Sep 25'!J39+'Oct 25'!J39+'Nov 25'!J39+'Dec 25'!J39 -> 2370.59 | M43: Intelligence PoC | N43: I-000318 | P43: =SUM('Jan - 26'!J39, 'Feb - 26'!J39,'Mar - 26'!J39) -> 792.65 | S43: Intelligence PoC | T43: I-000318 | V43: =SUM(D43,J43,P43) -> 4352.03
A44: Microsoft Office Replacement | D44: ='Feb 24'!J40+'Mar 24'!J40+'Apr 24'!J40+'May 24'!J40+'Jun 24'!J40+'Jul 24'!J40+'Aug 24'!J40+'Sep 24'!J40+'Oct 24'!J40+'Nov 24'!J40+'Dec 24'!J40 -> 15.5 | G44: Microsoft Office Replacement | J44: ='Jan 25'!J40+'Feb 25'!J40+'Mar 25'!J40+'April 25'!J40+'May 25'!J40+'June 25'!J40+'July 25'!J40+'Aug 25'!J40+'Sep 25'!J40+'Oct 25'!J40+'Nov 25'!J40+'Dec 25'!J40 -> 302.92 | M44: Microsoft Office Replacement | P44: =SUM('Jan - 26'!J40, 'Feb - 26'!J40,'Mar - 26'!J40) -> 29.5 | S44: Microsoft Office Replacement | V44: =SUM(D44,J44,P44) -> 347.92
A45: myETL | D45: ='Feb 24'!J41+'Mar 24'!J41+'Apr 24'!J41+'May 24'!J41+'Jun 24'!J41+'Jul 24'!J41+'Aug 24'!J41+'Sep 24'!J41+'Oct 24'!J41+'Nov 24'!J41+'Dec 24'!J41 -> 0 | G45: myETL | J45: ='Jan 25'!J41+'Feb 25'!J41+'Mar 25'!J41+'April 25'!J41+'May 25'!J41+'June 25'!J41+'July 25'!J41+'Aug 25'!J41+'Sep 25'!J41+'Oct 25'!J41+'Nov 25'!J41+'Dec 25'!J41 -> 0 | M45: myETL | P45: =SUM('Jan - 26'!J41, 'Feb - 26'!J41,'Mar - 26'!J41) -> 444.42 | S45: myETL | V45: =SUM(D45,J45,P45) -> 444.42
A46: myPub | B46: I-000319 | D46: ='Feb 24'!J42+'Mar 24'!J42+'Apr 24'!J42+'May 24'!J42+'Jun 24'!J42+'Jul 24'!J42+'Aug 24'!J42+'Sep 24'!J42+'Oct 24'!J42+'Nov 24'!J42+'Dec 24'!J42 -> 355.08 | G46: myPub | H46: I-000319 | J46: ='Jan 25'!J42+'Feb 25'!J42+'Mar 25'!J42+'April 25'!J42+'May 25'!J42+'June 25'!J42+'July 25'!J42+'Aug 25'!J42+'Sep 25'!J42+'Oct 25'!J42+'Nov 25'!J42+'Dec 25'!J42 -> 313.64 | M46: myPub | N46: I-000319 | P46: =SUM('Jan - 26'!J42, 'Feb - 26'!J42,'Mar - 26'!J42) -> 450.99 | S46: myPub | T46: I-000319 | V46: =SUM(D46,J46,P46) -> 1119.71
A47: myDiscounts App | B47: I-000320 | D47: ='Feb 24'!J43+'Mar 24'!J43+'Apr 24'!J43+'May 24'!J43+'Jun 24'!J43+'Jul 24'!J43+'Aug 24'!J43+'Sep 24'!J43+'Oct 24'!J43+'Nov 24'!J43+'Dec 24'!J43 -> 46.5 | G47: myDiscounts App | H47: I-000320 | J47: ='Jan 25'!J43+'Feb 25'!J43+'Mar 25'!J43+'April 25'!J43+'May 25'!J43+'June 25'!J43+'July 25'!J43+'Aug 25'!J43+'Sep 25'!J43+'Oct 25'!J43+'Nov 25'!J43+'Dec 25'!J43 -> 0 | M47: myDiscounts App | N47: I-000320 | P47: =SUM('Jan - 26'!J43, 'Feb - 26'!J43,'Mar - 26'!J43) -> 0 | S47: myDiscounts App | T47: I-000320 | V47: =SUM(D47,J47,P47) -> 46.5
A48: myJDW | B48: I-000239 | D48: ='Feb 24'!J44+'Mar 24'!J44+'Apr 24'!J44+'May 24'!J44+'Jun 24'!J44+'Jul 24'!J44+'Aug 24'!J44+'Sep 24'!J44+'Oct 24'!J44+'Nov 24'!J44+'Dec 24'!J44 -> 7125.79 | G48: myJDW | H48: I-000239 | J48: ='Jan 25'!J44+'Feb 25'!J44+'Mar 25'!J44+'April 25'!J44+'May 25'!J44+'June 25'!J44+'July 25'!J44+'Aug 25'!J44+'Sep 25'!J44+'Oct 25'!J44+'Nov 25'!J44+'Dec 25'!J44 -> 8645.9 | M48: myJDW | N48: I-000239 | P48: =SUM('Jan - 26'!J44, 'Feb - 26'!J44,'Mar - 26'!J44) -> 1756.9 | S48: myJDW | T48: I-000239 | V48: =SUM(D48,J48,P48) -> 17528.59
A49: mySchedule | B49: I-000271 | D49: ='Feb 24'!J45+'Mar 24'!J45+'Apr 24'!J45+'May 24'!J45+'Jun 24'!J45+'Jul 24'!J45+'Aug 24'!J45+'Sep 24'!J45+'Oct 24'!J45+'Nov 24'!J45+'Dec 24'!J45 -> 5547.01 | G49: mySchedule | H49: I-000271 | J49: ='Jan 25'!J45+'Feb 25'!J45+'Mar 25'!J45+'April 25'!J45+'May 25'!J45+'June 25'!J45+'July 25'!J45+'Aug 25'!J45+'Sep 25'!J45+'Oct 25'!J45+'Nov 25'!J45+'Dec 25'!J45 -> 4461.14 | M49: mySchedule | N49: I-000271 | P49: =SUM('Jan - 26'!J45, 'Feb - 26'!J45,'Mar - 26'!J45) -> 2014.35 | S49: mySchedule | T49: I-000271 | V49: =SUM(D49,J49,P49) -> 12022.5
A50: People Planning | D50: ='Feb 24'!J46+'Mar 24'!J46+'Apr 24'!J46+'May 24'!J46+'Jun 24'!J46+'Jul 24'!J46+'Aug 24'!J46+'Sep 24'!J46+'Oct 24'!J46+'Nov 24'!J46+'Dec 24'!J46 -> 0 | G50: People Planning | J50: ='Jan 25'!J46+'Feb 25'!J46+'Mar 25'!J46+'April 25'!J46+'May 25'!J46+'June 25'!J46+'July 25'!J46+'Aug 25'!J46+'Sep 25'!J46+'Oct 25'!J46+'Nov 25'!J46+'Dec 25'!J46 -> 0 | M50: People Planning | P50: =SUM('Jan - 26'!J46, 'Feb - 26'!J46,'Mar - 26'!J46) -> 0 | S50: People Planning | V50: =SUM(D50,J50,P50) -> 0
A51: PCI DSS Compliance | D51: ='Feb 24'!J47+'Mar 24'!J47+'Apr 24'!J47+'May 24'!J47+'Jun 24'!J47+'Jul 24'!J47+'Aug 24'!J47+'Sep 24'!J47+'Oct 24'!J47+'Nov 24'!J47+'Dec 24'!J47 -> 0 | G51: PCI DSS Compliance | J51: ='Jan 25'!J47+'Feb 25'!J47+'Mar 25'!J47+'April 25'!J47+'May 25'!J47+'June 25'!J47+'July 25'!J47+'Aug 25'!J47+'Sep 25'!J47+'Oct 25'!J47+'Nov 25'!J47+'Dec 25'!J47 -> 59.6 | M51: PCI DSS Compliance | P51: =SUM('Jan - 26'!J47, 'Feb - 26'!J47,'Mar - 26'!J47) -> 64.16 | S51: PCI DSS Compliance | V51: =SUM(D51,J51,P51) -> 123.76
A52: QR Code Admin Replatform | D52: ='Feb 24'!J48+'Mar 24'!J48+'Apr 24'!J48+'May 24'!J48+'Jun 24'!J48+'Jul 24'!J48+'Aug 24'!J48+'Sep 24'!J48+'Oct 24'!J48+'Nov 24'!J48+'Dec 24'!J48 -> 0 | G52: QR Code Admin Replatform | J52: ='Jan 25'!J48+'Feb 25'!J48+'Mar 25'!J48+'April 25'!J48+'May 25'!J48+'June 25'!J48+'July 25'!J48+'Aug 25'!J48+'Sep 25'!J48+'Oct 25'!J48+'Nov 25'!J48+'Dec 25'!J48 -> 51.75 | M52: QR Code Admin Replatform | P52: =SUM('Jan - 26'!J48, 'Feb - 26'!J48,'Mar - 26'!J48) -> 95.75 | S52: QR Code Admin Replatform | V52: =SUM(D52,J52,P52) -> 147.5
A53: Research Project: Possibilities & Benefits of AI | D53: ='Feb 24'!J49+'Mar 24'!J49+'Apr 24'!J49+'May 24'!J49+'Jun 24'!J49+'Jul 24'!J49+'Aug 24'!J49+'Sep 24'!J49+'Oct 24'!J49+'Nov 24'!J49+'Dec 24'!J49 -> 0 | G53: Research Project: Possibilities & Benefits of AI | J53: ='Jan 25'!J49+'Feb 25'!J49+'Mar 25'!J49+'April 25'!J49+'May 25'!J49+'June 25'!J49+'July 25'!J49+'Aug 25'!J49+'Sep 25'!J49+'Oct 25'!J49+'Nov 25'!J49+'Dec 25'!J49 -> 89.67 | M53: Research Project: Possibilities & Benefits of AI | P53: =SUM('Jan - 26'!J49, 'Feb - 26'!J49,'Mar - 26'!J49) -> 0 | S53: Research Project: Possibilities & Benefits of AI | V53: =SUM(D53,J53,P53) -> 89.67
A54: Out of Stock Screen Scraping | B54: I-000329 | D54: ='Feb 24'!J50+'Mar 24'!J50+'Apr 24'!J50+'May 24'!J50+'Jun 24'!J50+'Jul 24'!J50+'Aug 24'!J50+'Sep 24'!J50+'Oct 24'!J50+'Nov 24'!J50+'Dec 24'!J50 -> 35.92 | G54: Out of Stock Screen Scraping | H54: I-000329 | J54: ='Jan 25'!J50+'Feb 25'!J50+'Mar 25'!J50+'April 25'!J50+'May 25'!J50+'June 25'!J50+'July 25'!J50+'Aug 25'!J50+'Sep 25'!J50+'Oct 25'!J50+'Nov 25'!J50+'Dec 25'!J50 -> 0 | M54: Out of Stock Screen Scraping | N54: I-000329 | P54: =SUM('Jan - 26'!J50, 'Feb - 26'!J50,'Mar - 26'!J50) -> 0 | S54: Out of Stock Screen Scraping | T54: I-000329 | V54: =SUM(D54,J54,P54) -> 35.92
A55: Pub Ordering & Receipting Planning | B55: I-000330 | D55: ='Feb 24'!J51+'Mar 24'!J51+'Apr 24'!J51+'May 24'!J51+'Jun 24'!J51+'Jul 24'!J51+'Aug 24'!J51+'Sep 24'!J51+'Oct 24'!J51+'Nov 24'!J51+'Dec 24'!J51 -> 116.34 | G55: Pub Ordering & Receipting Planning | H55: I-000330 | J55: ='Jan 25'!J51+'Feb 25'!J51+'Mar 25'!J51+'April 25'!J51+'May 25'!J51+'June 25'!J51+'July 25'!J51+'Aug 25'!J51+'Sep 25'!J51+'Oct 25'!J51+'Nov 25'!J51+'Dec 25'!J51 -> 0 | M55: Pub Ordering & Receipting Planning | N55: I-000330 | P55: =SUM('Jan - 26'!J51, 'Feb - 26'!J51,'Mar - 26'!J51) -> 0 | S55: Pub Ordering & Receipting Planning | T55: I-000330 | V55: =SUM(D55,J55,P55) -> 116.34
A56: ResourceLink HCM / Absence Management | B56: I-000321 | D56: ='Feb 24'!J52+'Mar 24'!J52+'Apr 24'!J52+'May 24'!J52+'Jun 24'!J52+'Jul 24'!J52+'Aug 24'!J52+'Sep 24'!J52+'Oct 24'!J52+'Nov 24'!J52+'Dec 24'!J52 -> 114.5 | G56: ResourceLink HCM / Absence Management | H56: I-000321 | J56: ='Jan 25'!J52+'Feb 25'!J52+'Mar 25'!J52+'April 25'!J52+'May 25'!J52+'June 25'!J52+'July 25'!J52+'Aug 25'!J52+'Sep 25'!J52+'Oct 25'!J52+'Nov 25'!J52+'Dec 25'!J52 -> 47.42 | M56: ResourceLink HCM / Absence Management | N56: I-000321 | P56: =SUM('Jan - 26'!J52, 'Feb - 26'!J52,'Mar - 26'!J52) -> 0 | S56: ResourceLink HCM / Absence Management | T56: I-000321 | V56: =SUM(D56,J56,P56) -> 161.92
A57: Suggested Rotas | B57: I-000322 | D57: ='Feb 24'!J53+'Mar 24'!J53+'Apr 24'!J53+'May 24'!J53+'Jun 24'!J53+'Jul 24'!J53+'Aug 24'!J53+'Sep 24'!J53+'Oct 24'!J53+'Nov 24'!J53+'Dec 24'!J53 -> 1182.98 | G57: Suggested Rotas | H57: I-000322 | J57: ='Jan 25'!J53+'Feb 25'!J53+'Mar 25'!J53+'April 25'!J53+'May 25'!J53+'June 25'!J53+'July 25'!J53+'Aug 25'!J53+'Sep 25'!J53+'Oct 25'!J53+'Nov 25'!J53+'Dec 25'!J53 -> 2674.04 | M57: Suggested Rotas | N57: I-000322 | P57: =SUM('Jan - 26'!J53, 'Feb - 26'!J53,'Mar - 26'!J53) -> 597.17 | S57: Suggested Rotas | T57: I-000322 | V57: =SUM(D57,J57,P57) -> 4454.19
A58: Security Response Payment Service | B58: I-000323 | D58: ='Feb 24'!J54+'Mar 24'!J54+'Apr 24'!J54+'May 24'!J54+'Jun 24'!J54+'Jul 24'!J54+'Aug 24'!J54+'Sep 24'!J54+'Oct 24'!J54+'Nov 24'!J54+'Dec 24'!J54 -> 0 | G58: Security Response Payment Service | H58: I-000323 | J58: ='Jan 25'!J54+'Feb 25'!J54+'Mar 25'!J54+'April 25'!J54+'May 25'!J54+'June 25'!J54+'July 25'!J54+'Aug 25'!J54+'Sep 25'!J54+'Oct 25'!J54+'Nov 25'!J54+'Dec 25'!J54 -> 0 | M58: Security Response Payment Service | N58: I-000323 | P58: =SUM('Jan - 26'!J54, 'Feb - 26'!J54,'Mar - 26'!J54) -> 0 | S58: Security Response Payment Service | T58: I-000323 | V58: =SUM(D58,J58,P58) -> 0
A59: Technical Planning | D59: ='Feb 24'!J55+'Mar 24'!J55+'Apr 24'!J55+'May 24'!J55+'Jun 24'!J55+'Jul 24'!J55+'Aug 24'!J55+'Sep 24'!J55+'Oct 24'!J55+'Nov 24'!J55+'Dec 24'!J55 -> 0 | G59: Technical Planning | J59: ='Jan 25'!J55+'Feb 25'!J55+'Mar 25'!J55+'April 25'!J55+'May 25'!J55+'June 25'!J55+'July 25'!J55+'Aug 25'!J55+'Sep 25'!J55+'Oct 25'!J55+'Nov 25'!J55+'Dec 25'!J55 -> 0 | M59: Technical Planning | P59: =SUM('Jan - 26'!J55, 'Feb - 26'!J55,'Mar - 26'!J55) -> 8.5 | S59: Technical Planning | V59: =SUM(D59,J59,P59) -> 8.5
A60: WordPress Websites | B60: Various | D60: ='Feb 24'!J56+'Mar 24'!J56+'Apr 24'!J56+'May 24'!J56+'Jun 24'!J56+'Jul 24'!J56+'Aug 24'!J56+'Sep 24'!J56+'Oct 24'!J56+'Nov 24'!J56+'Dec 24'!J56 -> 1155.26 | G60: WordPress Websites | H60: Various | J60: ='Jan 25'!J56+'Feb 25'!J56+'Mar 25'!J56+'April 25'!J56+'May 25'!J56+'June 25'!J56+'July 25'!J56+'Aug 25'!J56+'Sep 25'!J56+'Oct 25'!J56+'Nov 25'!J56+'Dec 25'!J56 -> 1585.26 | M60: WordPress Websites | N60: Various | P60: =SUM('Jan - 26'!J56, 'Feb - 26'!J56,'Mar - 26'!J56) -> 242.62 | S60: WordPress Websites | T60: Various | V60: =SUM(D60,J60,P60) -> 2983.14
D61: =SUM(D21:D60) -> 41029.46 | J61: =SUM(J21:J60) -> 46696.48 | P61: =SUM(P21:P60) -> 16305.32 | V61: =SUM(V21:V60) -> 104031.26 | X61: =(D61+J61+P61)-V61 -> 0
A64: 2024 Support and Maintenance Hours | B64: Project Code | C64: Actual Hours | G64: 2025 Support and Maintenance Hours | H64: Project Code | I64: Actual Hours | M64: 2026 Support and Maintenance Hours | N64: Project Code | O64: Actual Hours | S64: Total Support and Maintenance Hours | T64: Project Code | U64: Actual Hours
A65: Allergens | C65: ='Feb 24'!G63+'Mar 24'!G63+'Apr 24'!G63+'May 24'!G63+'Jun 24'!G63+'Jul 24'!G63+'Aug 24'!G63+'Sep 24'!G63+'Oct 24'!G63+'Nov 24'!G63+'Dec 24'!G63 -> 0.25 | G65: Allergens | I65: ='Jan 25'!G63+'Feb 25'!G63+'Mar 25'!G63+'April 25'!G63+'May 25'!G63+'June 25'!G63+'July 25'!G63+'Aug 25'!G63+'Sep 25'!G63+'Oct 25'!G63+'Nov 25'!G63+'Dec 25'!G63 -> 4.07 | M65: Allergens | O65: =SUM('Jan - 26'!G63,'Feb - 26'!G63,'Mar - 26'!G63) -> 0 | S65: Allergens | U65: =SUM(C65,I65,O65) -> 4.32
A66: Customer Information Screens | C66: ='Feb 24'!G64+'Mar 24'!G64+'Apr 24'!G64+'May 24'!G64+'Jun 24'!G64+'Jul 24'!G64+'Aug 24'!G64+'Sep 24'!G64+'Oct 24'!G64+'Nov 24'!G64+'Dec 24'!G64 -> 47.86 | G66: Customer Information Screens | I66: ='Jan 25'!G64+'Feb 25'!G64+'Mar 25'!G64+'April 25'!G64+'May 25'!G64+'June 25'!G64+'July 25'!G64+'Aug 25'!G64+'Sep 25'!G64+'Oct 25'!G64+'Nov 25'!G64+'Dec 25'!G64 -> 27.59 | M66: Customer Information Screens | O66: =SUM('Jan - 26'!G64,'Feb - 26'!G64,'Mar - 26'!G64) -> 24.51 | S66: Customer Information Screens | U66: =SUM(C66,I66,O66) -> 99.96
A67: Customer App / PWA / App Manager | C67: ='Feb 24'!G65+'Mar 24'!G65+'Apr 24'!G65+'May 24'!G65+'Jun 24'!G65+'Jul 24'!G65+'Aug 24'!G65+'Sep 24'!G65+'Oct 24'!G65+'Nov 24'!G65+'Dec 24'!G65 -> 664.04 | G67: Customer App / PWA / App Manager | I67: ='Jan 25'!G65+'Feb 25'!G65+'Mar 25'!G65+'April 25'!G65+'May 25'!G65+'June 25'!G65+'July 25'!G65+'Aug 25'!G65+'Sep 25'!G65+'Oct 25'!G65+'Nov 25'!G65+'Dec 25'!G65 -> 2214.59 | M67: Customer App / PWA / App Manager | O67: =SUM('Jan - 26'!G65,'Feb - 26'!G65,'Mar - 26'!G65) -> 604.82 | S67: Customer App / PWA / App Manager | U67: =SUM(C67,I67,O67) -> 3483.45
A68: mAuth | C68: ='Feb 24'!G66+'Mar 24'!G66+'Apr 24'!G66+'May 24'!G66+'Jun 24'!G66+'Jul 24'!G66+'Aug 24'!G66+'Sep 24'!G66+'Oct 24'!G66+'Nov 24'!G66+'Dec 24'!G66 -> 0 | G68: mAuth | I68: ='Jan 25'!G66+'Feb 25'!G66+'Mar 25'!G66+'April 25'!G66+'May 25'!G66+'June 25'!G66+'July 25'!G66+'Aug 25'!G66+'Sep 25'!G66+'Oct 25'!G66+'Nov 25'!G66+'Dec 25'!G66 -> 97.62 | M68: mAuth | O68: =SUM('Jan - 26'!G66,'Feb - 26'!G66,'Mar - 26'!G66) -> 22.09 | S68: mAuth | U68: =SUM(C68,I68,O68) -> 119.71
A69: myJDW | C69: ='Feb 24'!G67+'Mar 24'!G67+'Apr 24'!G67+'May 24'!G67+'Jun 24'!G67+'Jul 24'!G67+'Aug 24'!G67+'Sep 24'!G67+'Oct 24'!G67+'Nov 24'!G67+'Dec 24'!G67 -> 376.47 | G69: myJDW | I69: ='Jan 25'!G67+'Feb 25'!G67+'Mar 25'!G67+'April 25'!G67+'May 25'!G67+'June 25'!G67+'July 25'!G67+'Aug 25'!G67+'Sep 25'!G67+'Oct 25'!G67+'Nov 25'!G67+'Dec 25'!G67 -> 851.22 | M69: myJDW | O69: =SUM('Jan - 26'!G67,'Feb - 26'!G67,'Mar - 26'!G67) -> 207.78 | S69: myJDW | U69: =SUM(C69,I69,O69) -> 1435.47
A70: mySchedule | C70: ='Feb 24'!G68+'Mar 24'!G68+'Apr 24'!G68+'May 24'!G68+'Jun 24'!G68+'Jul 24'!G68+'Aug 24'!G68+'Sep 24'!G68+'Oct 24'!G68+'Nov 24'!G68+'Dec 24'!G68 -> 279.17 | G70: mySchedule | I70: ='Jan 25'!G68+'Feb 25'!G68+'Mar 25'!G68+'April 25'!G68+'May 25'!G68+'June 25'!G68+'July 25'!G68+'Aug 25'!G68+'Sep 25'!G68+'Oct 25'!G68+'Nov 25'!G68+'Dec 25'!G68 -> 410.29 | M70: mySchedule | O70: =SUM('Jan - 26'!G68,'Feb - 26'!G68,'Mar - 26'!G68) -> 101.96 | S70: mySchedule | U70: =SUM(C70,I70,O70) -> 791.42
A71: Sitecore Corporate Website | C71: ='Feb 24'!G69+'Mar 24'!G69+'Apr 24'!G69+'May 24'!G69+'Jun 24'!G69+'Jul 24'!G69+'Aug 24'!G69+'Sep 24'!G69+'Oct 24'!G69+'Nov 24'!G69+'Dec 24'!G69 -> 33.55 | G71: Sitecore Corporate Website | I71: ='Jan 25'!G69+'Feb 25'!G69+'Mar 25'!G69+'April 25'!G69+'May 25'!G69+'June 25'!G69+'July 25'!G69+'Aug 25'!G69+'Sep 25'!G69+'Oct 25'!G69+'Nov 25'!G69+'Dec 25'!G69 -> 0 | M71: Sitecore Corporate Website | O71: =SUM('Jan - 26'!G69,'Feb - 26'!G69,'Mar - 26'!G69) -> 0 | S71: Sitecore Corporate Website | U71: =SUM(C71,I71,O71) -> 33.55
A72: Support for Franchises | C72: ='Feb 24'!G70+'Mar 24'!G70+'Apr 24'!G70+'May 24'!G70+'Jun 24'!G70+'Jul 24'!G70+'Aug 24'!G70+'Sep 24'!G70+'Oct 24'!G70+'Nov 24'!G70+'Dec 24'!G70 -> 0 | G72: Support for Franchises | I72: ='Jan 25'!G70+'Feb 25'!G70+'Mar 25'!G70+'April 25'!G70+'May 25'!G70+'June 25'!G70+'July 25'!G70+'Aug 25'!G70+'Sep 25'!G70+'Oct 25'!G70+'Nov 25'!G70+'Dec 25'!G70 -> 0 | M72: Support for Franchises | O72: =SUM('Jan - 26'!G70,'Feb - 26'!G70,'Mar - 26'!G70) -> 53.57 | S72: Support for Franchises | U72: =SUM(C72,I72,O72) -> 53.57
A73: WordPress Websites | C73: ='Feb 24'!G71+'Mar 24'!G71+'Apr 24'!G71+'May 24'!G71+'Jun 24'!G71+'Jul 24'!G71+'Aug 24'!G71+'Sep 24'!G71+'Oct 24'!G71+'Nov 24'!G71+'Dec 24'!G71 -> 53.61 | G73: WordPress Websites | I73: ='Jan 25'!G71+'Feb 25'!G71+'Mar 25'!G71+'April 25'!G71+'May 25'!G71+'June 25'!G71+'July 25'!G71+'Aug 25'!G71+'Sep 25'!G71+'Oct 25'!G71+'Nov 25'!G71+'Dec 25'!G71 -> 90.48 | M73: WordPress Websites | O73: =SUM('Jan - 26'!G71,'Feb - 26'!G71,'Mar - 26'!G71) -> 17.85 | S73: WordPress Websites | U73: =SUM(C73,I73,O73) -> 161.94
C74: =SUM(C65:C73) -> 1454.95 | I74: =SUM(I65:I73) -> 3695.86 | O74: =SUM(O65:O73) -> 1032.58 | U74: =SUM(U65:U73) -> 6183.39
A77: Third Party Services | C77: 45323 | D77: 45352 | E77: 45383 | F77: 45413 | G77: 45444 | H77: 45474 | I77: 45505 | J77: 45536 | K77: 45566 | L77: 45597 | M77: 45627 | N77: 45658 | O77: 45689 | P77: 45717 | Q77: 45748 | R77: 45778 | S77: 45809 | T77: 45839 | U77: 45870 | V77: 45901 | W77: 45931 | X77: 45962 | Y77: 45992 | Z77: 46023 | AA77: 46054 | AB77: 46082 | AC77: Total
C78: =SUM('Feb 24'!E100:F100) -> 41471.21 | D78: ='Mar 24'!E102+'Mar 24'!F102 -> 39166.9 | E78: ='Apr 24'!E102+'Apr 24'!F102 -> 3683.73 | F78: ='May 24'!E101+'May 24'!F101 -> 3545.18 | G78: ='Jun 24'!E101+'Jun 24'!F101 -> 3621.65 | H78: ='Jul 24'!F101 -> 31531.58 | I78: ='Aug 24'!G101 -> 19805.27 | J78: ='Sep 24'!G101 -> 14848.29 | K78: ='Oct 24'!G101 -> 18905.84 | L78: =SUM('Nov 24'!F102:G102) -> 17191.28 | M78: =SUM('Dec 24'!F102:G102) -> 17132.18 | N78: ='Jan 25'!G103 -> 15001.06 | O78: ='Feb 25'!G105 -> 14593.44 | P78: =SUM('Mar 25'!F105,'Mar 25'!G105) -> 146603.1 | Q78: =SUM('April 25'!F105+'April 25'!G105) -> 4643.78 | R78: =SUM('May 25'!F105,'May 25'!G105) -> 4392.62 | S78: =SUM('June 25'!F107+'June 25'!G107) -> 75622 | T78: ='July 25'!F107+'July 25'!G107 -> 4808.67 | U78: ='Aug 25'!G107 -> 4935.7 | V78: ='Sep 25'!G107 -> 6457.23 | W78: ='Oct 25'!G108 -> 8220.05 | X78: ='Nov 25'!G108 -> 8927.51 | Y78: ='Dec 25'!G111 -> 14798.59 | Z78: ='Jan - 26'!F111+'Jan - 26'!G111 -> 6221.81 | AA78: ='Feb - 26'!G111 -> 5879.37 | AB78: ='Mar - 26'!F111+'Mar - 26'!G111 -> 47366.55 | AC78: =SUM(C78:AA78) -> 532008.04
A81: FY23/24 Feb - Jul Programme Management | B81: Project Code | C81: Forecasted Hours | D81: Actual Hours | E81: Difference | G81: FY24/25 Aug - July Programme Management | H81: Project Code | I81: Forecasted Hours | J81: Actual Hours | K81: Difference | M81: FY25/26 Programme Management to end Mar 26 | N81: Project Code | O81: Forecasted Hours | P81: Actual Hours | Q81: Difference | S81: TOTAL Programme Management to end Mar 26 | T81: Project Code | U81: Forecasted Hours | V81: Actual Hours | W81: Difference
D82: ='Feb 24'!S13+'Mar 24'!T13+'Apr 24'!T13+'May 24'!T13+'Jun 24'!T13+'Jul 24'!T13 -> 10548.16 | J82: ='Aug 24'!T13 + 'Sep 24'!T13 + 'Oct 24'!T13 + 'Nov 24'!T13 + 'Dec 24'!T13 + 'Jan 25'!T13 + 'Feb 25'!T13 + 'Mar 25'!T13 + 'April 25'!T13+'May 25'!T13+'June 25'!T13+'July 25'!T13 -> 22994.86 | P82: ='Aug 25'!T13+'Sep 25'!T13+'Oct 25'!T13+'Nov 25'!T13+'Dec 25'!T13+'Jan - 26'!T13+'Feb - 26'!T13+'Mar - 26'!T13 -> 15752.478 | V82: =SUM(D82,J82,P82) -> 49295.498
A84: Reasearch & Planning | D84: =SUM('Feb 24'!C13:H13,'Feb 24'!J13)+SUM('Mar 24'!C13:H13,'Mar 24'!J13)+SUM('Apr 24'!C13:H13,'Apr 24'!J13)+SUM('May 24'!C13:H13,'May 24'!J13)+SUM('Jun 24'!C13:H13,'Jun 24'!J13)+SUM('Jul 24'!C13:H13,'Jul 24'!J13) -> 3897.4 | J84: =SUM('Aug 24'!C13,'Aug 24'!D13,'Aug 24'!E13,'Aug 24'!F13,'Aug 24'!G13,'Aug 24'!H13,'Aug 24'!J13)+ SUM('Sep 24'!C13,'Sep 24'!D13,'Sep 24'!E13,'Sep 24'!F13,'Sep 24'!G13,'Sep 24'!H13,'Sep 24'!J13)+ SUM('Oct 24'!C13,'Oct 24'!D13,'Oct 24'!E13,'Oct 24'!F13,'Oct 24'!G13,'Oct 24'!H13,'Oct 24'!J13)+ SUM('Nov 24'!C13,'Nov 24'!D13,'Nov 24'!E13,'Nov 24'!F13,'Nov 24'!G13,'Nov 24'!H13,'Nov 24'!J13)+ SUM('Dec 24'!C13,'Dec 24'!D13,'Dec 24'!E13,'Dec 24'!F13,'Dec 24'!G13,'Dec 24'!H13,'Dec 24'!J13)+ SUM('Jan 25'!C13,'Jan 25'!D13,'Jan 25'!E13,'Jan 25'!F13,'Jan 25'!G13,'Jan 25'!H13,'Jan 25'!J13)+ SUM('Feb 25'!C13,'Feb 25'!D13,'Feb 25'!E13,'Feb 25'!F13,'Feb 25'!G13,'Feb 25'!H13,'Feb 25'!J13)+ SUM('Mar 25'!C13,'Mar 25'!D13,'Mar 25'!E13,'Mar 25'!F13,'Mar 25'!G13,'Mar 25'!H13,'Mar 25'!J13)+ SUM('April 25'!C13,'April 25'!D13,'April 25'!E13,'April 25'!F13,'April 25'!G13,'April 25'!H13,'April 25'!J13)+SUM('May 25'!C13,'May 25'!D13,'May 25'!E13,'May 25'!F13,'May 25'!G13,'May 25'!H13,'May 25'!J13)+SUM('June 25'!C13,'June 25'!D13,'June 25'!F13,'June 25'!G13,'June 25'!H13,'June 25'!J13)+SUM('July 25'!C13,'July 25'!D13,'July 25'!E13,'July 25'!F13,'July 25'!G13,'July 25'!H13,'July 25'!J13) -> 6035.84 | P84: =SUM('Aug 25'!C13,'Aug 25'!D13,'Aug 25'!E13,'Aug 25'!F13,'Aug 25'!G13,'Aug 25'!H13,'Aug 25'!J13)+SUM('Sep 25'!C13,'Sep 25'!D13,'Sep 25'!F13,'Sep 25'!G13,'Sep 25'!H13,'Sep 25'!J13)+SUM('Oct 25'!C13,'Oct 25'!D13,'Oct 25'!E13,'Oct 25'!F13,'Oct 25'!G13,'Oct 25'!H13,'Oct 25'!J13)+SUM('Nov 25'!C13,'Nov 25'!D13,'Nov 25'!F13,'Nov 25'!G13,'Nov 25'!H13,'Nov 25'!J13)+SUM('Dec 25'!C13,'Dec 25'!D13,'Dec 25'!E13,'Dec 25'!F13,'Dec 25'!G13,'Dec 25'!H13,'Dec 25'!J13)+SUM('Jan - 26'!C13,'Jan - 26'!D13,'Jan - 26'!E13,'Jan - 26'!F13,'Jan - 26'!G13,'Jan - 26'!H13,'Jan - 26'!J13)+SUM('Feb - 26'!C13,'Feb - 26'!D13,'Feb - 26'!E13,'Feb - 26'!F13,'Feb - 26'!G13,'Feb - 26'!H13,'Feb - 26'!J13)+SUM('Mar - 26'!C13,'Mar - 26'!D13,'Mar - 26'!F13,'Mar - 26'!G13,'Mar - 26'!J13) -> 2621.428 | V84: =SUM(D84,J84,P84) -> 12554.668
A85: Includes industry research, feasibility and strategic design activities, programme management, financial management, strategic and senior meetings & reporting.
A87: Team Management Costs | D87: =SUM('Feb 24'!I13,'Feb 24'!K13,'Feb 24'!L13,'Feb 24'!M13,'Feb 24'!N13,'Feb 24'!O13,'Feb 24'!P13,'Feb 24'!Q13,'Feb 24'!R13)+SUM('Mar 24'!I13,'Mar 24'!K13,'Mar 24'!L13,'Mar 24'!M13,'Mar 24'!N13,'Mar 24'!O13,'Mar 24'!P13,'Mar 24'!Q13,'Mar 24'!R13,'Mar 24'!S13)+SUM('Apr 24'!I13,'Apr 24'!K13,'Apr 24'!L13,'Apr 24'!M13,'Apr 24'!N13,'Apr 24'!O13,'Apr 24'!P13,'Apr 24'!Q13,'Apr 24'!R13,'Apr 24'!S13)+SUM('May 24'!I13,'May 24'!K13,'May 24'!L13,'May 24'!M13,'May 24'!N13,'May 24'!O13,'May 24'!P13,'May 24'!Q13,'May 24'!R13,'May 24'!S13)+SUM('Jun 24'!I13,'Jun 24'!K13,'Jun 24'!L13,'Jun 24'!M13,'Jun 24'!N13,'Jun 24'!O13,'Jun 24'!P13,'Jun 24'!Q13,'Jun 24'!R13,'Jun 24'!S13)+SUM('Jul 24'!I13,'Jul 24'!K13,'Jul 24'!L13,'Jul 24'!M13,'Jul 24'!N13,'Jul 24'!O13,'Jul 24'!P13,'Jul 24'!Q13,'Jul 24'!R13,'Jul 24'!S13) -> 6650.76 | J87: =SUM('Aug 24'!I13,'Aug 24'!K13,'Aug 24'!L13,'Aug 24'!M13,'Aug 24'!N13,'Aug 24'!O13,'Aug 24'!P13,'Aug 24'!Q13,'Aug 24'!R13,'Aug 24'!S13)+ SUM('Sep 24'!I13,'Sep 24'!K13,'Sep 24'!L13,'Sep 24'!M13,'Sep 24'!N13,'Sep 24'!O13,'Sep 24'!P13,'Sep 24'!Q13,'Sep 24'!R13,'Sep 24'!S13)+ SUM('Oct 24'!I13,'Oct 24'!K13,'Oct 24'!L13,'Oct 24'!M13,'Oct 24'!N13,'Oct 24'!O13,'Oct 24'!P13,'Oct 24'!Q13,'Oct 24'!R13,'Oct 24'!S13)+ SUM('Nov 24'!I13,'Nov 24'!K13,'Nov 24'!L13,'Nov 24'!M13,'Nov 24'!N13,'Nov 24'!O13,'Nov 24'!P13,'Nov 24'!Q13,'Nov 24'!R13,'Nov 24'!S13)+ SUM('Dec 24'!I13,'Dec 24'!K13,'Dec 24'!L13,'Dec 24'!M13,'Dec 24'!N13,'Dec 24'!O13,'Dec 24'!P13,'Dec 24'!Q13,'Dec 24'!R13,'Dec 24'!S13)+ SUM('Jan 25'!I13,'Jan 25'!K13,'Jan 25'!L13,'Jan 25'!M13,'Jan 25'!N13,'Jan 25'!O13,'Jan 25'!P13,'Jan 25'!Q13,'Jan 25'!R13,'Jan 25'!S13)+ SUM('Feb 25'!I13,'Feb 25'!K13,'Feb 25'!L13,'Feb 25'!M13,'Feb 25'!N13,'Feb 25'!O13,'Feb 25'!P13,'Feb 25'!Q13,'Feb 25'!R13,'Feb 25'!S13)+ SUM('Mar 25'!I13,'Mar 25'!K13,'Mar 25'!L13,'Mar 25'!M13,'Mar 25'!N13,'Mar 25'!O13,'Mar 25'!P13,'Mar 25'!Q13,'Mar 25'!R13,'Mar 25'!S13)+ SUM('April 25'!I13,'April 25'!K13,'April 25'!L13,'April 25'!M13,'April 25'!N13,'April 25'!O13,'April 25'!P13,'April 25'!Q13,'April 25'!R13,'April 25'!S13)+SUM('May 25'!I13,'May 25'!K13,'May 25'!L13,'May 25'!M13,'May 25'!N13,'May 25'!O13,'May 25'!P13,'May 25'!Q13,'May 25'!R13,'May 25'!S13)+SUM('June 25'!I13,'June 25'!K13,'June 25'!M13,'June 25'!N13,'June 25'!O13,'June 25'!P13,'June 25'!R13,'June 25'!S13)+SUM('July 25'!I13,'July 25'!K13,'July 25'!L13,'July 25'!M13,'July 25'!N13,'July 25'!O13,'July 25'!P13,'July 25'!Q13,'July 25'!R13,'July 25'!S13) -> 16959.02 | P87: =SUM('Aug 25'!I13,'Aug 25'!K13,'Aug 25'!L13,'Aug 25'!M13,'Aug 25'!N13,'Aug 25'!O13,'Aug 25'!P13,'Aug 25'!Q13,'Aug 25'!R13,'Aug 25'!S13)+SUM('Sep 25'!I13,'Sep 25'!K13,'Sep 25'!L13,'Sep 25'!M13,'Sep 25'!N13,'Sep 25'!O13,'Sep 25'!P13,'Sep 25'!R13,'Sep 25'!S13)+SUM('Oct 25'!I13,'Oct 25'!K13,'Oct 25'!L13,'Oct 25'!M13,'Oct 25'!N13,'Oct 25'!O13,'Oct 25'!P13,'Oct 25'!Q13,'Oct 25'!R13,'Oct 25'!S13)+SUM('Nov 25'!I13,'Nov 25'!K13,'Nov 25'!L13,'Nov 25'!M13,'Nov 25'!N13,'Nov 25'!O13,'Nov 25'!P13,'Nov 25'!R13)+SUM('Dec 25'!I13,'Dec 25'!K13,'Dec 25'!L13,'Dec 25'!M13,'Dec 25'!N13,'Dec 25'!O13,'Dec 25'!P13,'Dec 25'!Q13,'Dec 25'!R13,'Dec 25'!S13)+SUM('Jan - 26'!I13,'Jan - 26'!K13,'Jan - 26'!L13,'Jan - 26'!M13,'Jan - 26'!N13,'Jan - 26'!O13,'Jan - 26'!P13,'Jan - 26'!Q13,'Jan - 26'!R13,'Jan - 26'!S13)+SUM('Feb - 26'!I13,'Feb - 26'!K13,'Feb - 26'!L13,'Feb - 26'!M13,'Feb - 26'!N13,'Feb - 26'!O13,'Feb - 26'!P13,'Feb - 26'!Q13,'Feb - 26'!R13,'Feb - 26'!S13)+SUM('Mar - 26'!I13,'Mar - 26'!K13,'Mar - 26'!L13,'Mar - 26'!M13,'Mar - 26'!N13,'Mar - 26'!O13,'Mar - 26'!P13,'Mar - 26'!R13,'Mar - 26'!S13) -> 13131.05 | V87: =SUM(D87,J87,P87) -> 36740.83
A88: Includes staff recruitment, training, holidays, sick, other absences, travel and breaks for the equivalent of 32 full time Filter employees working on JDW related activities.
C89: Check | D89: =SUM(D84,D87)-D82 -> 0 | I89: Check | J89: =SUM(J87,J84)-J82 -> 0 | O89: Check | P89: =SUM(P87+P84)-P82 -> 0 | U89: Check | V89: =SUM(V87+V84)-V82 -> 0
A92: FY23/24 Feb - Jul | B92: Project Code | C92: Forecasted Hours | D92: Actual Hours | E92: Difference | G92: FY24/25 Aug - July | H92: Project Code | I92: Forecasted Hours | J92: Actual Hours | K92: Difference | M92: FY25/26 Aug - Mar | N92: Project Code | O92: Forecasted Hours | P92: Actual Hours | Q92: Difference | S92: TOTAL to end Mar 26 | T92: Project Code | U92: Forecasted Hours | V92: Actual Hours | W92: Difference
A93: Allergens Service | B93: I-000300 | D93: ='Feb 24'!J17+'Mar 24'!J17+'Apr 24'!J17+'May 24'!J17+'Jun 24'!J17+'Jul 24'!J17 -> 509.5 | G93: Allergens Service | H93: I-000300 | J93: ='Aug 24'!J17 + 'Sep 24'!J17 + 'Oct 24'!J17 + 'Nov 24'!J17 + 'Dec 24'!J17 + 'Jan 25'!J17 + 'Feb 25'!J17 + 'Mar 25'!J17 + 'April 25'!J17+'May 25'!J17+'June 25'!J17+'July 25'!J17 -> 2.08 | M93: Allergens Service | N93: I-000300 | P93: ='Aug 25'!J17+'Sep 25'!J17+'Oct 25'!J17+'Nov 25'!J17+'Dec 25'!J17+'Jan - 26'!J17+'Feb - 26'!J17+'Mar - 26'!J17 -> 0 | S93: Allergens Service | T93: I-000300 | V93: =SUM(D93,J93,P93) -> 511.58
A94: Authentication | B94: I-000312 | D94: ='Feb 24'!J18+'Mar 24'!J18+'Apr 24'!J18+'May 24'!J18+'Jun 24'!J18+'Jul 24'!J18 -> 731.63 | G94: Authentication | H94: I-000312 | J94: ='Aug 24'!J18 + 'Sep 24'!J18 + 'Oct 24'!J18 + 'Nov 24'!J18 + 'Dec 24'!J18 + 'Jan 25'!J18 + 'Feb 25'!J18 + 'Mar 25'!J18 + 'April 25'!J18+'May 25'!J18+'June 25'!J18+'July 25'!J18 -> 3629.11 | M94: Authentication | N94: I-000312 | P94: ='Aug 25'!J18+'Sep 25'!J18+'Oct 25'!J18+'Nov 25'!J18+'Dec 25'!J18+'Jan - 26'!J18+'Feb - 26'!J18+'Mar - 26'!J18 -> 618.35 | S94: Authentication | T94: I-000312 | V94: =SUM(D94,J94,P94) -> 4979.09
A95: Available Ales on TV Screens | D95: ='Feb 24'!J19+'Mar 24'!J19+'Apr 24'!J19+'May 24'!J19+'Jun 24'!J19+'Jul 24'!J19 -> 0 | G95: Available Ales on TV Screens | J95: ='Aug 24'!J19 + 'Sep 24'!J19 + 'Oct 24'!J19 + 'Nov 24'!J19 + 'Dec 24'!J19 + 'Jan 25'!J19 + 'Feb 25'!J19 + 'Mar 25'!J19 + 'April 25'!J19+'May 25'!J19+'June 25'!J19+'July 25'!J19 -> 13.91 | M95: Available Ales on TV Screens | P95: ='Aug 25'!J19+'Sep 25'!J19+'Oct 25'!J19+'Nov 25'!J19+'Dec 25'!J19+'Jan - 26'!J19+'Feb - 26'!J19+'Mar - 26'!J19 -> 51.42 | S95: Available Ales on TV Screens | V95: =SUM(D95,J95,P95) -> 65.33
A96: Customer Information Screens | B96: I-000313 | D96: ='Feb 24'!J20+'Mar 24'!J20+'Apr 24'!J20+'May 24'!J20+'Jun 24'!J20+'Jul 24'!J20 -> 328 | G96: Customer Information Screens | H96: I-000313 | J96: ='Aug 24'!J20 + 'Sep 24'!J20 + 'Oct 24'!J20 + 'Nov 24'!J20 + 'Dec 24'!J20 + 'Jan 25'!J20 + 'Feb 25'!J20 + 'Mar 25'!J20 + 'April 25'!J20+'May 25'!J20+'June 25'!J20+'July 25'!J20 -> 101.16 | M96: Customer Information Screens | N96: I-000313 | P96: ='Aug 25'!J20+'Sep 25'!J20+'Oct 25'!J20+'Nov 25'!J20+'Dec 25'!J20+'Jan - 26'!J20+'Feb - 26'!J20+'Mar - 26'!J20 -> 34.42 | S96: Customer Information Screens | T96: I-000313 | V96: =SUM(D96,J96,P96) -> 463.58
A97: Corporate Website Replatform Build | B97: I-000300 | D97: ='Feb 24'!J21+'Mar 24'!J21+'Apr 24'!J21+'May 24'!J21+'Jun 24'!J21+'Jul 24'!J21 -> 1692.67 | G97: Corporate Website Replatform Build | H97: I-000300 | J97: ='Aug 24'!J21 + 'Sep 24'!J21 + 'Oct 24'!J21 + 'Nov 24'!J21 + 'Dec 24'!J21 + 'Jan 25'!J21 + 'Feb 25'!J21 + 'Mar 25'!J21 + 'April 25'!J21+'May 25'!J21+'June 25'!J21+'July 25'!J21 -> 95.92 | M97: Corporate Website Replatform Build | N97: I-000300 | P97: ='Aug 25'!J21+'Sep 25'!J21+'Oct 25'!J21+'Nov 25'!J21+'Dec 25'!J21+'Jan - 26'!J21+'Feb - 26'!J21+'Mar - 26'!J21 -> 0 | S97: Corporate Website Replatform Build | T97: I-000300 | V97: =SUM(D97,J97,P97) -> 1788.59
A98: Customer Accounts Planning | B98: I-000311 | D98: ='Feb 24'!J22+'Mar 24'!J22+'Apr 24'!J22+'May 24'!J22+'Jun 24'!J22+'Jul 24'!J22 -> 277.54 | G98: Customer Accounts Planning | H98: I-000311 | J98: ='Aug 24'!J22 + 'Sep 24'!J22 + 'Oct 24'!J22 + 'Nov 24'!J22 + 'Dec 24'!J22 + 'Jan 25'!J22 + 'Feb 25'!J22 + 'Mar 25'!J22 + 'April 25'!J22+'May 25'!J22+'June 25'!J22+'July 25'!J22 -> 1765.2 | M98: Customer Accounts Planning | N98: I-000311 | P98: ='Aug 25'!J22+'Sep 25'!J22+'Oct 25'!J22+'Nov 25'!J22+'Dec 25'!J22+'Jan - 26'!J22+'Feb - 26'!J22+'Mar - 26'!J22 -> 404.78 | S98: Customer Accounts Planning | T98: I-000311 | V98: =SUM(D98,J98,P98) -> 2447.52
A99: Customer App - Ibersol Franchise Integration | D99: ='Feb 24'!J23+'Mar 24'!J23+'Apr 24'!J23+'May 24'!J23+'Jun 24'!J23+'Jul 24'!J23 -> 0 | G99: Customer App - Ibersol Franchise Integration | J99: ='Aug 24'!J23 + 'Sep 24'!J23 + 'Oct 24'!J23 + 'Nov 24'!J23 + 'Dec 24'!J23 + 'Jan 25'!J23 + 'Feb 25'!J23 + 'Mar 25'!J23 + 'April 25'!J23+'May 25'!J23+'June 25'!J23+'July 25'!J23 -> 0 | M99: Customer App - Ibersol Franchise Integration | P99: ='Aug 25'!J23+'Sep 25'!J23+'Oct 25'!J23+'Nov 25'!J23+'Dec 25'!J23+'Jan - 26'!J23+'Feb - 26'!J23+'Mar - 26'!J23 -> 137.83 | S99: Customer App - Ibersol Franchise Integration | V99: =SUM(D99,J99,P99) -> 137.83
A100: Customer App - Lagardere Franchise Integration | D100: ='Feb 24'!J24+'Mar 24'!J24+'Apr 24'!J24+'May 24'!J24+'Jun 24'!J24+'Jul 24'!J24 -> 0 | G100: Customer App - Lagardere Franchise Integration | J100: ='Aug 24'!J24 + 'Sep 24'!J24 + 'Oct 24'!J24 + 'Nov 24'!J24 + 'Dec 24'!J24 + 'Jan 25'!J24 + 'Feb 25'!J24 + 'Mar 25'!J24 + 'April 25'!J24+'May 25'!J24+'June 25'!J24+'July 25'!J24 -> 0 | M100: Customer App - Lagardere Franchise Integration | P100: ='Aug 25'!J24+'Sep 25'!J24+'Oct 25'!J24+'Nov 25'!J24+'Dec 25'!J24+'Jan - 26'!J24+'Feb - 26'!J24+'Mar - 26'!J24 -> 493.41 | S100: Customer App - Lagardere Franchise Integration | V100: =SUM(D100,J100,P100) -> 493.41
A101: Customer App / PWA / App Manager | B101: I-000287 | D101: ='Feb 24'!J25+'Mar 24'!J25+'Apr 24'!J25+'May 24'!J25+'Jun 24'!J25+'Jul 24'!J25 -> 8786.94 | G101: Customer App / PWA / App Manager | H101: I-000287 | J101: ='Aug 24'!J25 + 'Sep 24'!J25 + 'Oct 24'!J25 + 'Nov 24'!J25 + 'Dec 24'!J25 + 'Jan 25'!J25 + 'Feb 25'!J25 + 'Mar 25'!J25 + 'April 25'!J25+'May 25'!J25+'June 25'!J25+'July 25'!J25 -> 12692.5 | M101: Customer App / PWA / App Manager | N101: I-000287 | P101: ='Aug 25'!J25+'Sep 25'!J25+'Oct 25'!J25+'Nov 25'!J25+'Dec 25'!J25+'Jan - 26'!J25+'Feb - 26'!J25+'Mar - 26'!J25 -> 10064.56 | S101: Customer App / PWA / App Manager | T101: I-000287 | V101: =SUM(D101,J101,P101) -> 31544
A102: Customer App UX/UI Redesign | D102: ='Feb 24'!J26+'Mar 24'!J26+'Apr 24'!J26+'May 24'!J26+'Jun 24'!J26+'Jul 24'!J26 -> 0 | G102: Customer App UX/UI Redesign | J102: ='Aug 24'!J26 + 'Sep 24'!J26 + 'Oct 24'!J26 + 'Nov 24'!J26 + 'Dec 24'!J26 + 'Jan 25'!J26 + 'Feb 25'!J26 + 'Mar 25'!J26 + 'April 25'!J26+'May 25'!J26+'June 25'!J26+'July 25'!J26 -> 427.59 | M102: Customer App UX/UI Redesign | P102: ='Aug 25'!J26+'Sep 25'!J26+'Oct 25'!J26+'Nov 25'!J26+'Dec 25'!J26+'Jan - 26'!J26+'Feb - 26'!J26+'Mar - 26'!J26 -> 1354.59 | S102: Customer App UX/UI Redesign | V102: =SUM(D102,J102,P102) -> 1782.18
A103: Customer Planning | D103: ='Feb 24'!J27+'Mar 24'!J27+'Apr 24'!J27+'May 24'!J27+'Jun 24'!J27+'Jul 24'!J27 -> 0 | G103: Customer Planning | J103: ='Aug 24'!J27 + 'Sep 24'!J27 + 'Oct 24'!J27 + 'Nov 24'!J27 + 'Dec 24'!J27 + 'Jan 25'!J27 + 'Feb 25'!J27 + 'Mar 25'!J27 + 'April 25'!J27+'May 25'!J27+'June 25'!J27+'July 25'!J27 -> 0 | M103: Customer Planning | P103: ='Aug 25'!J27+'Sep 25'!J27+'Oct 25'!J27+'Nov 25'!J27+'Dec 25'!J27+'Jan - 26'!J27+'Feb - 26'!J27+'Mar - 26'!J27 -> 0 | S103: Customer Planning | V103: =SUM(D103,J103,P103) -> 0
A104: Digital Pub Records | B104: I-000314 | D104: ='Feb 24'!J28+'Mar 24'!J28+'Apr 24'!J28+'May 24'!J28+'Jun 24'!J28+'Jul 24'!J28 -> 81.4 | G104: Digital Pub Records | H104: I-000314 | J104: ='Aug 24'!J28 + 'Sep 24'!J28 + 'Oct 24'!J28 + 'Nov 24'!J28 + 'Dec 24'!J28 + 'Jan 25'!J28 + 'Feb 25'!J28 + 'Mar 25'!J28 + 'April 25'!J28+'May 25'!J28+'June 25'!J28+'July 25'!J28 -> 2182.72 | M104: Digital Pub Records | N104: I-000314 | P104: ='Aug 25'!J28+'Sep 25'!J28+'Oct 25'!J28+'Nov 25'!J28+'Dec 25'!J28+'Jan - 26'!J28+'Feb - 26'!J28+'Mar - 26'!J28 -> 1206.93 | S104: Digital Pub Records | T104: I-000314 | V104: =SUM(D104,J104,P104) -> 3471.05
A105: Digital Vouchers | D105: ='Feb 24'!J29+'Mar 24'!J29+'Apr 24'!J29+'May 24'!J29+'Jun 24'!J29+'Jul 24'!J29 -> 0 | G105: Digital Vouchers | J105: ='Aug 24'!J29 + 'Sep 24'!J29 + 'Oct 24'!J29 + 'Nov 24'!J29 + 'Dec 24'!J29 + 'Jan 25'!J29 + 'Feb 25'!J29 + 'Mar 25'!J29 + 'April 25'!J29+'May 25'!J29+'June 25'!J29+'July 25'!J29 -> 146.66 | M105: Digital Vouchers | P105: ='Aug 25'!J29+'Sep 25'!J29+'Oct 25'!J29+'Nov 25'!J29+'Dec 25'!J29+'Jan - 26'!J29+'Feb - 26'!J29+'Mar - 26'!J29 -> 415.94 | S105: Digital Vouchers | V105: =SUM(D105,J105,P105) -> 562.6
A106: Disaster Recovery & Business Continuity | B106: I-000315 | D106: ='Feb 24'!J30+'Mar 24'!J30+'Apr 24'!J30+'May 24'!J30+'Jun 24'!J30+'Jul 24'!J30 -> 25.75 | G106: Disaster Recovery & Business Continuity | H106: I-000315 | J106: ='Aug 24'!J30 + 'Sep 24'!J30 + 'Oct 24'!J30 + 'Nov 24'!J30 + 'Dec 24'!J30 + 'Jan 25'!J30 + 'Feb 25'!J30 + 'Mar 25'!J30 + 'April 25'!J30+'May 25'!J30+'June 25'!J30+'July 25'!J30 -> 128.1 | M106: Disaster Recovery & Business Continuity | N106: I-000315 | P106: ='Aug 25'!J30+'Sep 25'!J30+'Oct 25'!J30+'Nov 25'!J30+'Dec 25'!J30+'Jan - 26'!J30+'Feb - 26'!J30+'Mar - 26'!J30 -> 114.84 | S106: Disaster Recovery & Business Continuity | T106: I-000315 | V106: =SUM(D106,J106,P106) -> 268.69
A107: Employee Digital Record | B107: I-000316 | D107: ='Feb 24'!J31+'Mar 24'!J31+'Apr 24'!J31+'May 24'!J31+'Jun 24'!J31+'Jul 24'!J31 -> 316.17 | G107: Employee Digital Record | H107: I-000316 | J107: ='Aug 24'!J31 + 'Sep 24'!J31 + 'Oct 24'!J31 + 'Nov 24'!J31 + 'Dec 24'!J31 + 'Jan 25'!J31 + 'Feb 25'!J31 + 'Mar 25'!J31 + 'April 25'!J31+'May 25'!J31+'June 25'!J31+'July 25'!J31 -> 1072.27 | M107: Employee Digital Record | N107: I-000316 | P107: ='Aug 25'!J31+'Sep 25'!J31+'Oct 25'!J31+'Nov 25'!J31+'Dec 25'!J31+'Jan - 26'!J31+'Feb - 26'!J31+'Mar - 26'!J31 -> 1361.01 | S107: Employee Digital Record | T107: I-000316 | V107: =SUM(D107,J107,P107) -> 2749.45
A108: Employee Verification (with WISDOM) | B108: I-000274 | D108: ='Feb 24'!J32+'Mar 24'!J32+'Apr 24'!J32+'May 24'!J32+'Jun 24'!J32+'Jul 24'!J32 -> 243.93 | G108: Employee Verification (with WISDOM) | H108: I-000274 | J108: ='Aug 24'!J32 + 'Sep 24'!J32 + 'Oct 24'!J32 + 'Nov 24'!J32 + 'Dec 24'!J32 + 'Jan 25'!J32 + 'Feb 25'!J32 + 'Mar 25'!J32 + 'April 25'!J32+'May 25'!J32+'June 25'!J32+'July 25'!J32 -> 0 | M108: Employee Verification (with WISDOM) | N108: I-000274 | P108: ='Aug 25'!J32+'Sep 25'!J32+'Oct 25'!J32+'Nov 25'!J32+'Dec 25'!J32+'Jan - 26'!J32+'Feb - 26'!J32+'Mar - 26'!J32 -> 0 | S108: Employee Verification (with WISDOM) | T108: I-000274 | V108: =SUM(D108,J108,P108) -> 243.93
A109: Franchises Customer App | D109: ='Feb 24'!J33+'Mar 24'!J33+'Apr 24'!J33+'May 24'!J33+'Jun 24'!J33+'Jul 24'!J33 -> 358.35 | G109: Franchises Customer App | J109: ='Aug 24'!J33 + 'Sep 24'!J33 + 'Oct 24'!J33 + 'Nov 24'!J33 + 'Dec 24'!J33 + 'Jan 25'!J33 + 'Feb 25'!J33 + 'Mar 25'!J33 + 'April 25'!J33+'May 25'!J33+'June 25'!J33+'July 25'!J33 -> 4384.17 | M109: Franchises Customer App | P109: ='Aug 25'!J33+'Sep 25'!J33+'Oct 25'!J33+'Nov 25'!J33+'Dec 25'!J33+'Jan - 26'!J33+'Feb - 26'!J33+'Mar - 26'!J33 -> 1245.56 | S109: Franchises Customer App | V109: =SUM(D109,J109,P109) -> 5988.08
A110: Franchises myJDW | D110: ='Feb 24'!J34+'Mar 24'!J34+'Apr 24'!J34+'May 24'!J34+'Jun 24'!J34+'Jul 24'!J34 -> 0 | G110: Franchises myJDW | J110: ='Aug 24'!J34 + 'Sep 24'!J34 + 'Oct 24'!J34 + 'Nov 24'!J34 + 'Dec 24'!J34 + 'Jan 25'!J34 + 'Feb 25'!J34 + 'Mar 25'!J34 + 'April 25'!J34+'May 25'!J34+'June 25'!J34+'July 25'!J34 -> 19.5 | M110: Franchises myJDW | P110: ='Aug 25'!J34+'Sep 25'!J34+'Oct 25'!J34+'Nov 25'!J34+'Dec 25'!J34+'Jan - 26'!J34+'Feb - 26'!J34+'Mar - 26'!J34 -> 2068.5 | S110: Franchises myJDW | V110: =SUM(D110,J110,P110) -> 2088
A111: Franchises mySchedule | D111: ='Feb 24'!J35+'Mar 24'!J35+'Apr 24'!J35+'May 24'!J35+'Jun 24'!J35+'Jul 24'!J35 -> 0 | G111: Franchises mySchedule | J111: ='Aug 24'!J35 + 'Sep 24'!J35 + 'Oct 24'!J35 + 'Nov 24'!J35 + 'Dec 24'!J35 + 'Jan 25'!J35 + 'Feb 25'!J35 + 'Mar 25'!J35 + 'April 25'!J35+'May 25'!J35+'June 25'!J35+'July 25'!J35 -> 23.75 | M111: Franchises mySchedule | P111: ='Aug 25'!J35+'Sep 25'!J35+'Oct 25'!J35+'Nov 25'!J35+'Dec 25'!J35+'Jan - 26'!J35+'Feb - 26'!J35+'Mar - 26'!J35 -> 184.23 | S111: Franchises mySchedule | V111: =SUM(D111,J111,P111) -> 207.98
A112: Franchises WordPress Websites | D112: ='Feb 24'!J36+'Mar 24'!J36+'Apr 24'!J36+'May 24'!J36+'Jun 24'!J36+'Jul 24'!J36 -> 0 | G112: Franchises WordPress Websites | J112: ='Aug 24'!J36 + 'Sep 24'!J36 + 'Oct 24'!J36 + 'Nov 24'!J36 + 'Dec 24'!J36 + 'Jan 25'!J36 + 'Feb 25'!J36 + 'Mar 25'!J36 + 'April 25'!J36+'May 25'!J36+'June 25'!J36+'July 25'!J36 -> 0 | M112: Franchises WordPress Websites | P112: ='Aug 25'!J36+'Sep 25'!J36+'Oct 25'!J36+'Nov 25'!J36+'Dec 25'!J36+'Jan - 26'!J36+'Feb - 26'!J36+'Mar - 26'!J36 -> 114.33 | S112: Franchises WordPress Websites | V112: =SUM(D112,J112,P112) -> 114.33
A113: Hotels HLS Integration | D113: ='Feb 24'!J37+'Mar 24'!J37+'Apr 24'!J37+'May 24'!J37+'Jun 24'!J37+'Jul 24'!J37 -> 0 | G113: Hotels HLS Integration | J113: ='Aug 24'!J37 + 'Sep 24'!J37 + 'Oct 24'!J37 + 'Nov 24'!J37 + 'Dec 24'!J37 + 'Jan 25'!J37 + 'Feb 25'!J37 + 'Mar 25'!J37 + 'April 25'!J37+'May 25'!J37+'June 25'!J37+'July 25'!J37 -> 119.18 | M113: Hotels HLS Integration | P113: ='Aug 25'!J37+'Sep 25'!J37+'Oct 25'!J37+'Nov 25'!J37+'Dec 25'!J37+'Jan - 26'!J37+'Feb - 26'!J37+'Mar - 26'!J37 -> 18.75 | S113: Hotels HLS Integration | V113: =SUM(D113,J113,P113) -> 137.93
A114: Hotels Price Comparison | B114: I-000317 | D114: ='Feb 24'!J38+'Mar 24'!J38+'Apr 24'!J38+'May 24'!J38+'Jun 24'!J38+'Jul 24'!J38 -> 3.5 | G114: Hotels Price Comparison | H114: I-000317 | J114: ='Aug 24'!J38 + 'Sep 24'!J38 + 'Oct 24'!J38 + 'Nov 24'!J38 + 'Dec 24'!J38 + 'Jan 25'!J38 + 'Feb 25'!J38 + 'Mar 25'!J38 + 'April 25'!J38+'May 25'!J38+'June 25'!J38+'July 25'!J38 -> 0 | M114: Hotels Price Comparison | N114: I-000317 | P114: ='Aug 25'!J38+'Sep 25'!J38+'Oct 25'!J38+'Nov 25'!J38+'Dec 25'!J38+'Jan - 26'!J38+'Feb - 26'!J38+'Mar - 26'!J38 -> 0 | S114: Hotels Price Comparison | T114: I-000317 | V114: =SUM(D114,J114,P114) -> 3.5
A115: Intelligence PoC | B115: I-000318 | D115: ='Feb 24'!J39+'Mar 24'!J39+'Apr 24'!J39+'May 24'!J39+'Jun 24'!J39+'Jul 24'!J39 -> 459.17 | G115: Intelligence PoC | H115: I-000318 | J115: ='Aug 24'!J39 + 'Sep 24'!J39 + 'Oct 24'!J39 + 'Nov 24'!J39 + 'Dec 24'!J39 + 'Jan 25'!J39 + 'Feb 25'!J39 + 'Mar 25'!J39 + 'April 25'!J39+'May 25'!J39+'June 25'!J39+'July 25'!J39 -> 2160.36 | M115: Intelligence PoC | N115: I-000318 | P115: ='Aug 25'!J39+'Sep 25'!J39+'Oct 25'!J39+'Nov 25'!J39+'Dec 25'!J39+'Jan - 26'!J39+'Feb - 26'!J39+'Mar - 26'!J39 -> 1732.5 | S115: Intelligence PoC | T115: I-000318 | V115: =SUM(D115,J115,P115) -> 4352.03
A116: Microsoft Office Replacement | D116: ='Feb 24'!J40+'Mar 24'!J40+'Apr 24'!J40+'May 24'!J40+'Jun 24'!J40+'Jul 24'!J40 -> 0 | G116: Microsoft Office Replacement | J116: ='Aug 24'!J40 + 'Sep 24'!J40 + 'Oct 24'!J40 + 'Nov 24'!J40 + 'Dec 24'!J40 + 'Jan 25'!J40 + 'Feb 25'!J40 + 'Mar 25'!J40 + 'April 25'!J40+'May 25'!J40+'June 25'!J40+'July 25'!J40 -> 279.92 | M116: Microsoft Office Replacement | P116: ='Aug 25'!J40+'Sep 25'!J40+'Oct 25'!J40+'Nov 25'!J40+'Dec 25'!J40+'Jan - 26'!J40+'Feb - 26'!J40+'Mar - 26'!J40 -> 68 | S116: Microsoft Office Replacement | V116: =SUM(D116,J116,P116) -> 347.92
A117: myETL | D117: ='Feb 24'!J41+'Mar 24'!J41+'Apr 24'!J41+'May 24'!J41+'Jun 24'!J41+'Jul 24'!J41 -> 0 | G117: myETL | J117: ='Aug 24'!J41 + 'Sep 24'!J41 + 'Oct 24'!J41 + 'Nov 24'!J41 + 'Dec 24'!J41 + 'Jan 25'!J41 + 'Feb 25'!J41 + 'Mar 25'!J41 + 'April 25'!J41+'May 25'!J41+'June 25'!J41+'July 25'!J41 -> 0 | M117: myETL | P117: ='Aug 25'!J41+'Sep 25'!J41+'Oct 25'!J41+'Nov 25'!J41+'Dec 25'!J41+'Jan - 26'!J41+'Feb - 26'!J41+'Mar - 26'!J41 -> 444.42 | S117: myETL | V117: =SUM(D117,J117,P117) -> 444.42
...

Sheet Feb 24
A1: Month: | B1: 45323
A3: Dedicated Team Billing: | B3: =B9+B60 -> 242579
A4: Fixed Team Target Hours: | B4: =SUM(22.5*8.5)*21 -> 4016.25 | C4: 25 people (20 dedicated, 5 part-time)
A5: Fixed Team Recorded Hours: | B5: =S13+J57+G72 -> 4220.06
A6: Difference: | B6: =B5-B4 -> 203.81
A9: Planning, Development & Delivery | B9: 222986
C10: R&P | D10: R&P | E10: R&P | F10: R&P | G10: R&P | H10: R&P | I10: TMC | J10: R&P | K10: TMC | L10: TMC | M10: TMC | N10: TMC | O10: TMC | P10: TMC | Q10: TMC | R10: TMC
A11: Programme Management Hours | B11: Project Code | C11: Planning | D11: Project Management, Meetings & Reporting | E11: Design | F11: Admin | G11: Systems Admin | H11: Research | I11: Training | J11: Finance | K11: HR | L11: Recruitment | M11: Travel | N11: Break | O11: Lunch | P11: Holiday | Q11: Sick | R11: Other Absence | S11: Total
C13: 41 | D13: 235.99 | E13: =SUM(E12) -> 0 | F13: 78.08 | G13: 129.95 | H13: 11.51 | I13: 93.77 | J13: 19 | K13: 18.33 | L13: 59.92 | M13: 6.25 | N13: 47.6 | O13: 248.38 | P13: 89.75 | Q13: 35.25 | R13: 17 | S13: =SUM(C13:R13) -> 1131.78
A16: Projects Hours | B16: Project Code | C16: Development | D16: Project Management, Meetings & Reporting | E16: Testing | F16: Planning | G16: Systems Admin | H16: Design | I16: Release | J16: Total
A17: Allergens Service | B17: I-000300 | C17: 74.82 | D17: 30.94 | E17: 0.25 | J17: =SUM(C17:I17) -> 106.01
A18: Authentication | B18: I-000312 | F18: 12.5 | J18: =SUM(C18:I18) -> 12.5
A19: Available Ales on TV Screens | J19: =SUM(C19:I19) -> 0
A20: Customer Information Screens | B20: I-000313 | C20: 11.75 | D20: 2.75 | E20: 2 | F20: 1 | J20: =SUM(C20:I20) -> 17.5
A21: Corporate Website Replatform Build | B21: I-000300 | C21: 176.5 | D21: 45.83 | F21: 0.75 | G21: 1.25 | H21: 2.75 | J21: =SUM(C21:I21) -> 227.08
A22: Customer Accounts Planning | B22: I-000311 | C22: 4.92 | D22: 3.25 | F22: 6 | J22: =SUM(C22:I22) -> 14.17
A23: Customer App - Ibersol Franchise Integration
A24: Customer App - Lagardere Franchise Integration
A25: Customer App / PWA / App Manager | B25: I-000287 | C25: 401.89 | D25: =148.18+0.5 -> 148.68 | E25: =311.75+1.5 -> 313.25 | F25: =22+18 -> 40 | G25: 33.43 | H25: 18.5 | I25: 0.75 | J25: =SUM(C25:I25) -> 956.5
A26: Customer App UX/UI Redesign | J26: =SUM(C26:I26) -> 0
A27: Customer Planning
A28: Digital Pub Records | B28: I-000314 | J28: =SUM(C28:I28) -> 0
A29: Digital Vouchers
A30: Disaster Recovery & Business Continuity | B30: I-000315 | J30: =SUM(C30:I30) -> 0
A31: Employee Digital Records | B31: I-000316 | J31: =SUM(C31:I31) -> 0
A32: Employee Verification (with WISDOM) | B32: I-000274 | D32: 12.25 | J32: =SUM(C32:I32) -> 12.25
A33: Franchises Customer App | F33: 9 | J33: =SUM(C33:I33) -> 9
A34: Franchises myJDW | J34: =SUM(C34:I34) -> 0
A35: Franchises mySchedule | J35: =SUM(C35:I35) -> 0
A36: Franchises WordPress Websites
A37: Hotels HLS Integration | J37: =SUM(C37:I37) -> 0
A38: Hotels Price Comparison | B38: I-000317 | J38: =SUM(C38:I38) -> 0
A39: Intelligence PoC | B39: I-000318 | J39: =SUM(C39:I39) -> 0
A40: Microsoft Office Replacement | J40: =SUM(C40:I40) -> 0
A41: myETL
A42: myPub | B42: I-000319 | J42: =SUM(C42:I42) -> 0
A43: myDiscounts App | B43: I-000320 | D43: 8.75 | F43: 4 | H43: 10.25 | J43: =SUM(C43:I43) -> 23
A44: myJDW | B44: I-000239 | C44: 406.15 | D44: 166.51 | E44: 1 | F44: 86.81 | G44: 0.38 | H44: 3.25 | J44: =SUM(C44:I44) -> 664.1
A45: mySchedule | B45: I-000271 | C45: 266.89 | D45: 101.16 | E45: 166.74 | F45: 83.4 | G45: 1.58 | H45: 7 | I45: 7.33 | J45: =SUM(C45:I45) -> 634.1
A46: People Planning
A47: PCI DSS Compliance | J47: =SUM(C47:I47) -> 0
A48: QR Code Admin Replatform | J48: =SUM(C48:I48) -> 0
A49: Research Project: Possibilities & Benefits of AI | J49: =SUM(C49:I49) -> 0
A50: Out of Stock Screen Scraping | B50: I-000329 | J50: =SUM(C50:I50) -> 0
A51: Pub Ordering & Receipting Planning | B51: I-000330 | J51: =SUM(C51:I51) -> 0
A52: ResourceLink HCM / Absence Management | B52: I-000321 | J52: =SUM(C52:I52) -> 0
A53: Suggested Rotas | B53: I-000322 | F53: 11 | H53: 1 | J53: =SUM(C53:I53) -> 12
A54: Security Response Payment Service | B54: I-000323 | J54: =SUM(C54:I54) -> 0
A55: Technical Planning
A56: WordPress Websites | B56: Various | C56: 79.33 | D56: 23.87 | F56: 1 | H56: 0.5 | J56: =SUM(C56:I56) -> 104.7
C57: =SUM(C17:C56) -> 1422.25 | D57: =SUM(D17:D56) -> 543.99 | E57: =SUM(E17:E56) -> 483.24 | F57: =SUM(F17:F56) -> 255.46 | G57: =SUM(G17:G56) -> 36.64 | H57: =SUM(H17:H56) -> 43.25 | I57: =SUM(I17:I56) -> 8.08 | J57: =SUM(C57:I57) -> 2792.91
A60: Support and Maintenance | B60: 19593
A62: Support and Maintenance Hours | B62: Project Code | C62: Customer Support | D62: Project Management, Meetings & Reporting | E62: Maintenance | F62: Systems Admin | G62: Total
A63: Allergens | C63: 0.25 | G63: =SUM(C63:F63) -> 0.25
A64: Customer Information Screens | C64: 2.35 | D64: 2.66 | E64: 2.5 | G64: =SUM(C64:F64) -> 7.51
A65: Customer App / PWA / App Manager | C65: 16.9 | D65: 14.17 | E65: 3.92 | F65: 2.41 | G65: =SUM(C65:F65) -> 37.4
A66: myAuth | G66: =SUM(C66:F66) -> 0
A67: myJDW | C67: 98.77 | D67: 22.63 | E67: 31.35 | F67: 10.05 | G67: =SUM(C67:F67) -> 162.8
A68: mySchedule | C68: 45.71 | D68: 10.05 | E68: 8.92 | F68: 4.25 | G68: =SUM(C68:F68) -> 68.93
A69: Sitecore Corporate Website | C69: 0.1 | E69: 6.8 | G69: =SUM(C69:F69) -> 6.9
A70: Support for Franchises | G70: =SUM(C70:F70) -> 0
A71: WordPress Websites | C71: 10.58 | D71: 0.5 | E71: 0.5 | G71: =SUM(C71:F71) -> 11.58
C72: =SUM(C63:C71) -> 174.66 | D72: =SUM(D63:D71) -> 50.01 | E72: =SUM(E63:E71) -> 53.99 | F72: =SUM(F63:F71) -> 16.71 | G72: =SUM(C72:F72) -> 295.37
A75: Third Party Services | B75: Variable
A77: Company | B77: Website / Application | D77: Contracted To | E77: Per Annum Charge | F77: Per Month Charge | G77: Service Notes
A79: AWS | B79: myJDW, mySchedule, Authentication | D79: JDW | G79: Charged directly to JDW. Figures are converted from dollars at 0.82 pound sterling.
A80: AWS | B80: Customer App | D80: JDW | G80: Charged directly to JDW. Figures are converted from dollars at 0.82 pound sterling.
A81: AWS | B81: Auth0 Wisdom & Customer Accounts PoC | D81: JDW | G81: Charged directly to JDW. Figures are converted from dollars at 0.82 pound sterling.
A82: AWS | B82: Corporate Website Sitecore | D82: JDW | G82: Charged directly to JDW. Figures are converted from dollars at 0.82 pound sterling.
A83: Sendbird | B83: myJDW | D83: JDW | G83: Charged directly to JDW. Filter don't have sight of this fee.
A85: Elastic Search | B85: myJDW & mySchedule | D85: Filter | F85: 54.96 | G85: Fluctuates depending on usage, charged each month. No real increase for mySchedule as there is limited content to search. Not possible to split by service.
A86: Open Weather | B86: mySchedule | D86: Filter | G86: Fluctuates depending on usage, charged each month., currently not hitting limits to be charged.
A87: Ionic Enterprise Package | B87: Customer App | D87: Filter | E87: 27658.4 | G87: Enterprise package with live updates.
A88: Ionic Payments | B88: Customer App | D88: Filter | E88: 10371.9 | G88: Annual requirement from Feb 24.
A89: Apple Developer Enterprise Program - One year | B89: myJDW | D89: JDW | G89: Recharegd by Filter. Traditionally we haven't marked this cost up.
A90: Google Maps API | B90: Corporate & Hotels Websites | D90: Filter | F90: 1647.25 | G90: Fluctuates depending on usage.
A91: WordPress Plugins Annual Budget | D91: Filter | G91: In use across WordPress websites. Included Corporate website once live. Plugins include: Gravity Forms Elite, Search Pro, PersonalizeWP Pro, WPRocket, Imagify, Media Library Organiser Pro, Advanced Custom Fields, Advanced Post Type Order, Yoast Duplicate Post, Admin Columns Pro, WP Migrate Premier, Wordfence, WP Activity Log. Potentially need to look at this as more of a package moving forwards across all sites.
A92: Website Hosting | B92: Careers | D92: Filter | F92: 750 | G92: This fees will become obsolete if moving to a WP Engine Premier Hosting Solution, see Corporate Website.
A93: Website Hosting | B93: Investors | D93: Filter | F93: 750 | G93: This fees will become obsolete if moving to a WP Engine Premier Hosting Solution, see Corporate Website.
A94: Website Hosting | B94: Hotel | D94: Filter | G94: This fees will become obsolete if moving to a WP Engine Premier Hosting Solution, see Corporate Website.
A95: Website Hosting | B95: Corporate | D95: TBC | G95: The re-platforming will involve the set-up of a multi-site solution to pull together all the microsites into a single platform. WP Engine have proposed two options for this, please see WP Engine / JDW - proposal for the details. We can discuss this further, alongside the decision as to whether Filter will contract on behalf of JDW (at 15% admin fee) or you choose to contract directly with WP Engine. Included is single node fee.
A96: Website Cookie Yes | B96: Corporate | D96: Filter | G96: Outside of standard plugin package.
A97: Website Cookie Yes | B97: Hotel | D97: Filter | G97: Outside of standard plugin package.
A98: Website Yoast SEO Premium | B98: Hotel | D98: Filter | G98: Outside of standard plugin package.
A99: Statamic | D99: Filter | F99: 238.7 | G99: Reduces after one year to c.£60 per year.
E100: =SUM(E78:E99) -> 38030.3 | F100: =SUM(F79:F99) -> 3440.91

Sheet Mar 24
A1: Month: | B1: 45352
A3: Dedicated Team Billing: | B3: =B9+B60 -> 242579
A4: Fixed Team Target Hours: | B4: =SUM(22.5*8.5)*21 -> 4016.25 | C4: 25 people (20 dedicated, 5 part-time)
A5: Fixed Team Recorded Hours: | B5: =T13+J57+G72 -> 4554.15
A6: Difference: | B6: =B5-B4 -> 537.9
A9: Planning, Development & Delivery | B9: 222986
C10: R&P | D10: R&P | E10: R&P | F10: R&P | G10: R&P | H10: R&P | I10: TMC | J10: R&P | K10: TMC | L10: TMC | M10: TMC | N10: TMC | O10: TMC | P10: TMC | Q10: TMC | R10: TMC | S10: TMC
A11: Programme Management Hours | B11: Project Code | C11: Planning | D11: Project Management, Meetings & Reporting | E11: Design | F11: Admin | G11: Systems Admin | H11: Research | I11: Training | J11: Finance | K11: HR | L11: Recruitment | M11: Travel | N11: Break | O11: Lunch | P11: Holiday | Q11: Bank Holiday | R11: Sick | S11: Other Absence | T11: Total
C13: 121.75 | D13: 301.76 | E13: =SUM(E12) -> 0 | F13: 31.32 | G13: 156.41 | H13: 6 | I13: 69.52 | J13: 7.25 | K13: 22.27 | L13: 50.02 | M13: 11.75 | N13: 33.84 | O13: 266.25 | P13: 170 | Q13: 193.5 | R13: 35.75 | S13: 82 | T13: =SUM(C13:S13) -> 1559.39
A16: Projects Hours | B16: Project Code | C16: Development | D16: Project Management, Meetings & Reporting | E16: Testing | F16: Planning | G16: Systems Admin | H16: Design | I16: Release | J16: Total
A17: Allergens Service | B17: I-000300 | C17: 37.78 | D17: 43.81 | E17: 10.46 | F17: 3 | G17: 2.33 | H17: 0.5 | I17: 3.42 | J17: =SUM(C17:I17) -> 101.3
A18: Authentication | B18: I-000312 | D18: 16.89 | F18: 84.33 | H18: 10.75 | J18: =SUM(C18:I18) -> 111.97
A19: Available Ales on TV Screens | J19: =SUM(C19:I19) -> 0
A20: Customer Information Screens | B20: I-000313 | C20: 5.5 | D20: 0.25 | E20: 1 | F20: 4.25 | J20: =SUM(C20:I20) -> 11
A21: Corporate Website Replatform Build | B21: I-000300 | C21: 108 | D21: 26.5 | F21: 4.25 | G21: 0.25 | H21: 0.75 | J21: =SUM(C21:I21) -> 139.75
A22: Customer Accounts Planning | B22: I-000311 | C22: 94.75 | D22: 14.03 | E22: 1.75 | F22: 1 | J22: =SUM(C22:I22) -> 111.53
A23: Customer App - Ibersol Franchise Integration
A24: Customer App - Lagardere Franchise Integration
A25: Customer App / PWA / App Manager | B25: I-000287 | C25: =521.62+1.17 -> 522.79 | D25: =209.73+6.5 -> 216.23 | E25: =223.35+1.25 -> 224.6 | F25: 40.62 | G25: 114.2 | H25: =17.25+0.75 -> 18 | I25: 8.5 | J25: =SUM(C25:I25) -> 1144.94
A26: Customer App UX/UI Redesign | J26: =SUM(C26:I26) -> 0
A27: Customer Planning
A28: Digital Pub Records | B28: I-000314 | J28: =SUM(C28:I28) -> 0
A29: Digital Vouchers | J29: =SUM(C29:I29) -> 0
A30: Disaster Recovery & Business Continuity | B30: I-000315 | J30: =SUM(C30:I30) -> 0
A31: Employee Digital Records | B31: I-000316 | F31: 11 | J31: =SUM(C31:I31) -> 11
A32: Employee Verification (with WISDOM) | B32: I-000274 | C32: 6.45 | D32: 8.96 | F32: 3 | H32: 2.35 | J32: =SUM(C32:I32) -> 20.76
A33: Franchises Customer App | D33: 3.5 | F33: 15.59 | J33: =SUM(C33:I33) -> 19.09
A34: Franchises myJDW | J34: =SUM(C34:I34) -> 0
A35: Franchises mySchedule | J35: =SUM(C35:I35) -> 0
A36: Franchises WordPress Websites
A37: Hotels HLS Integration | J37: =SUM(C37:I37) -> 0
A38: Hotels Price Comparison | B38: I-000317 | J38: =SUM(C38:I38) -> 0
A39: Intelligence PoC | B39: I-000318 | D39: 1 | F39: 6 | J39: =SUM(C39:I39) -> 7
A40: Microsoft Office Replacement | J40: =SUM(C40:I40) -> 0
A41: myETL
A42: myPub | B42: I-000319 | J42: =SUM(C42:I42) -> 0
A43: myDiscounts App | B43: I-000320 | D43: 13 | F43: 5.25 | H43: 3.25 | J43: =SUM(C43:I43) -> 21.5
A44: myJDW | B44: I-000239 | C44: 245.57 | D44: 171.29 | E44: 138.75 | F44: 70.66 | H44: 1 | J44: =SUM(C44:I44) -> 627.27
A45: mySchedule | B45: I-000271 | C45: 277.32 | D45: 80.89 | E45: 1.25 | F45: 117.85 | G45: 3.25 | I45: 6.02 | J45: =SUM(C45:I45) -> 486.58
A46: People Planning
A47: PCI DSS Compliance | J47: =SUM(C47:I47) -> 0
A48: QR Code Admin Replatform | J48: =SUM(C48:I48) -> 0
A49: Research Project: Possibilities & Benefits of AI | J49: =SUM(C49:I49) -> 0
A50: Out of Stock Screen Scraping | B50: I-000329 | J50: =SUM(C50:I50) -> 0
A51: Pub Ordering & Receipting Planning | B51: I-000330 | J51: =SUM(C51:I51) -> 0
A52: ResourceLink HCM / Absence Management | B52: I-000321 | J52: =SUM(C52:I52) -> 0
A53: Suggested Rotas | B53: I-000322 | D53: 2.5 | F53: 9.39 | J53: =SUM(C53:I53) -> 11.89
A54: Security Response Payment Service | B54: I-000323 | J54: =SUM(C54:I54) -> 0
A55: Technical Planning
A56: WordPress Websites | B56: Various | C56: 77 | D56: 18.79 | I56: 1 | J56: =SUM(C56:I56) -> 96.79
C57: =SUM(C17:C56) -> 1375.16 | D57: =SUM(D17:D56) -> 617.64 | E57: =SUM(E17:E56) -> 377.81 | F57: =SUM(F17:F56) -> 376.19 | G57: =SUM(G17:G56) -> 120.03 | H57: =SUM(H17:H56) -> 36.6 | I57: =SUM(I17:I56) -> 18.94 | J57: =SUM(C57:I57) -> 2922.37
A60: Support and Maintenance | B60: 19593
A62: Support and Maintenance Hours | B62: Project Code | C62: Customer Support | D62: Project Management, Meetings & Reporting | E62: Maintenance | F62: Systems Admin | G62: Total
A63: Allergens | G63: =SUM(C63:F63) -> 0
A64: Customer Information Screens | C64: 5 | E64: 3.5 | G64: =SUM(C64:F64) -> 8.5
A65: Customer App / PWA / App Manager | C65: 4.6 | E65: 2.5 | G65: =SUM(C65:F65) -> 7.1
A66: myAuth | G66: =SUM(C66:F66) -> 0
A67: myJDW | C67: 17.01 | E67: 1.5 | G67: =SUM(C67:F67) -> 18.51
A68: mySchedule | C68: 15.28 | E68: 15.5 | G68: =SUM(C68:F68) -> 30.78
A69: Sitecore Corporate Website | C69: 1.9 | E69: 3.1 | G69: =SUM(C69:F69) -> 5
A70: Support for Franchises | G70: =SUM(C70:F70) -> 0
A71: WordPress Websites | C71: 2.5 | G71: =SUM(C71:F71) -> 2.5
C72: =SUM(C64:C71) -> 46.29 | D72: =SUM(D64:D71) -> 0 | E72: =SUM(E64:E71) -> 26.1 | F72: =SUM(F63:F71) -> 0 | G72: =SUM(C72:F72) -> 72.39
A75: Third Party Services | B75: Variable
A77: Company | B77: Website / Application | D77: Contracted To | E77: Per Annum Charge | F77: Per Month Charge | G77: Service Notes
A79: AWS | B79: myJDW, mySchedule, Authentication | D79: JDW | G79: Charged directly to JDW. Figures are converted from dollars at 0.82 pound sterling.
A80: AWS | B80: Customer App | D80: JDW | G80: Charged directly to JDW. Figures are converted from dollars at 0.82 pound sterling.
A81: AWS | B81: Auth0 Wisdom & Customer Accounts PoC | D81: JDW | G81: Charged directly to JDW. Figures are converted from dollars at 0.82 pound sterling.
A82: AWS | B82: Corporate Website Sitecore | D82: JDW | G82: Charged directly to JDW. Figures are converted from dollars at 0.82 pound sterling.
A83: Sendbird | B83: myJDW | D83: JDW | G83: Charged directly to JDW. Filter don't have sight of this fee.
A85: Elastic Search | B85: myJDW & mySchedule | D85: Filter | F85: 58.64 | G85: Fluctuates depending on usage, charged each month. No real increase for mySchedule as there is limited content to search. Not possible to split by service.
A86: Open Weather | B86: mySchedule | D86: Filter | G86: Fluctuates depending on usage, charged each month., currently not hitting limits to be charged.
A87: Ionic Enterprise Package | B87: Customer App | D87: Filter | G87: Enterprise package with live updates.
A88: Ionic Payments | B88: Customer App | D88: Filter | G88: Annual requirement from Feb 24.
A89: Apple Developer Enterprise Program - One year | B89: myJDW | D89: JDW | E89: 259 | G89: Recharegd by Filter. Traditionally we haven't marked this cost up.
A90: Google Maps API | B90: Corporate & Hotels Websites | D90: Filter | F90: 1804.86 | G90: Fluctuates depending on usage.
A91: WordPress Plugins Annual Budget | D91: Filter | F91: 750 | G91: In use across WordPress websites. Included Corporate website once live. Plugins include: Gravity Forms Elite, Search Pro, PersonalizeWP Pro, WPRocket, Imagify, Media Library Organiser Pro, Advanced Custom Fields, Advanced Post Type Order, Yoast Duplicate Post, Admin Columns Pro, WP Migrate Premier, Wordfence, WP Activity Log. Potentially need to look at this as more of a package moving forwards across all sites.
A92: Website Hosting | B92: Careers | D92: Filter | F92: 750 | G92: This fees will become obsolete if moving to a WP Engine Premier Hosting Solution, see Corporate Website.
A93: Website Hosting | B93: Investors | D93: Filter | G93: This fees will become obsolete if moving to a WP Engine Premier Hosting Solution, see Corporate Website.
A94: Website Hosting | B94: Hotel | D94: Filter | G94: This fees will become obsolete if moving to a WP Engine Premier Hosting Solution, see Corporate Website.
A95: Website Hosting | B95: Corporate | D95: TBC | G95: The re-platforming will involve the set-up of a multi-site solution to pull together all the microsites into a single platform. WP Engine have proposed two options for this, please see WP Engine / JDW - proposal for the details. We can discuss this further, alongside the decision as to whether Filter will contract on behalf of JDW (at 15% admin fee) or you choose to contract directly with WP Engine. Included is single node fee.
A96: Website Cookie Yes | B96: Corporate | D96: Filter | G96: Outside of standard plugin package.
A97: Website Cookie Yes | B97: Hotel | D97: Filter | G97: Outside of standard plugin package.
A98: Website Yoast SEO Premium | B98: Hotel | D98: Filter | G98: Outside of standard plugin package.
A99: Statamic | D99: Filter | G99: Reduces after one year to c.£60 per year.
A100: WP SMTP | B100: myJDW | D100: Filter | E100: 85.61 | G100: myJDW forms email service
A101: Flagsmith | B101: myJDW & mySchedule | D101: Filter | E101: 35458.79 | G101: To allow for the toggling of features on and off.
E102: =SUM(E78:E101) -> 35803.4 | F102: =SUM(F78:F101) -> 3363.5

Sheet Apr 24
A1: Month: | B1: 45383
A3: Dedicated Team Billing: | B3: =B9+B60 -> 340813
A4: Fixed Team Target Hours: | B4: =SUM(32*8.5)*22 -> 5984 | C4: 32 FTE
A5: Fixed Team Recorded Hours: | B5: =T13+J57+G72 -> 5989.93
A6: Difference: | B6: =B5-B4 -> 5.93
A9: Planning, Development & Delivery | B9: 315839
C10: R&P | D10: R&P | E10: R&P | F10: R&P | G10: R&P | H10: R&P | I10: TMC | J10: R&P | K10: TMC | L10: TMC | M10: TMC | N10: TMC | O10: TMC | P10: TMC | Q10: TMC | R10: TMC | S10: TMC
A11: Programme Management Hours | B11: Project Code | C11: Planning | D11: Project Management, Meetings & Reporting | E11: Design | F11: Admin | G11: Systems Admin | H11: Research | I11: Training | J11: Finance | K11: HR | L11: Recruitment | M11: Travel | N11: Break | O11: Lunch | P11: Holiday | Q11: Bank Holiday | R11: Sick | S11: Other Absence | T11: Total
C13: 116.27 | D13: 298.73 | E13: =SUM(E12) -> 0 | F13: 42.67 | G13: 122.34 | H13: 35.25 | I13: 71.83 | J13: 4 | K13: 21.8 | L13: 24.15 | M13: 10.75 | N13: 48.72 | O13: 436.17 | P13: 294.75 | Q13: 194.5 | R13: =SUM(R12) -> 0 | S13: 9.5 | T13: =SUM(C13:S13) -> 1731.43
A16: Projects Hours | B16: Project Code | C16: Development | D16: Project Management, Meetings & Reporting | E16: Testing | F16: Planning | G16: Systems Admin | H16: Design | I16: Release | J16: Total
A17: Allergens Service | B17: I-000300 | C17: 6.79 | D17: 25.89 | E17: 21 | G17: 0.75 | H17: 0.08 | J17: =SUM(C17:I17) -> 54.51
A18: Authentication | B18: I-000312 | D18: 7.37 | F18: 18 | J18: =SUM(C18:I18) -> 25.37
A19: Available Ales on TV Screens | J19: =SUM(C19:I19) -> 0
A20: Customer Information Screens | B20: I-000313 | C20: 1.25 | J20: =SUM(C20:I20) -> 1.25
A21: Corporate Website Replatform Build | B21: I-000300 | C21: 213.5 | D21: 24.5 | J21: =SUM(C21:I21) -> 238
A22: Customer Accounts Planning | B22: I-000311 | J22: =SUM(C22:I22) -> 0
A23: Customer App - Ibersol Franchise Integration
A24: Customer App - Lagardere Franchise Integration
A25: Customer App / PWA / App Manager | B25: I-000287 | C25: 825.01 | D25: 267.36 | E25: 562.92 | F25: 151.42 | G25: 138.79 | H25: 57.5 | I25: 5.75 | J25: =SUM(C25:I25) -> 2008.75
A26: Customer App UX/UI Redesign | J26: =SUM(C26:I26) -> 0
A27: Customer Planning
A28: Digital Pub Records | B28: I-000314 | J28: =SUM(C28:I28) -> 0
A29: Digital Vouchers | J29: =SUM(C29:I29) -> 0
A30: Disaster Recovery & Business Continuity | B30: I-000315 | J30: =SUM(C30:I30) -> 0
A31: Employee Digital Records | B31: I-000316 | D31: 31.75 | F31: 11.5 | H31: 9 | J31: =SUM(C31:I31) -> 52.25
A32: Employee Verification (with WISDOM) | B32: I-000274 | C32: 108.74 | D32: 22.31 | H32: 4 | J32: =SUM(C32:I32) -> 135.05
A33: Franchises Customer App | D33: 5 | F33: 11 | H33: 0.75 | J33: =SUM(C33:I33) -> 16.75
A34: Franchises myJDW | J34: =SUM(C34:I34) -> 0
A35: Franchises mySchedule | J35: =SUM(C35:I35) -> 0
A36: Franchises WordPress Websites
A37: Hotels HLS Integration | J37: =SUM(C37:I37) -> 0
A38: Hotels Price Comparison | B38: I-000317 | J38: =SUM(C38:I38) -> 0
A39: Intelligence PoC | B39: I-000318 | D39: 35.5 | F39: 68.67 | H39: 31.17 | J39: =SUM(C39:I39) -> 135.34
A40: Microsoft Office Replacement | J40: =SUM(C40:I40) -> 0
A41: myETL
A42: myPub | B42: I-000319 | J42: =SUM(C42:I42) -> 0
A43: myDiscounts App | B43: I-000320 | J43: =SUM(C43:I43) -> 0
A44: myJDW | B44: I-000239 | C44: 243.93 | D44: 147.94 | E44: 137.5 | F44: 83.25 | I44: 7.03 | J44: =SUM(C44:I44) -> 619.65
A45: mySchedule | B45: I-000271 | C45: 272.09 | D45: 110.15 | E45: 152.92 | F45: 108.18 | H45: 6 | I45: 3.84 | J45: =SUM(C45:I45) -> 653.18
A46: People Planning
A47: PCI DSS Compliance | J47: =SUM(C47:I47) -> 0
A48: QR Code Admin Replatform | J48: =SUM(C48:I48) -> 0
A49: Research Project: Possibilities & Benefits of AI | J49: =SUM(C49:I49) -> 0
A50: Out of Stock Screen Scraping | B50: I-000329 | J50: =SUM(C50:I50) -> 0
A51: Pub Ordering & Receipting Planning | B51: I-000330 | J51: =SUM(C51:I51) -> 0
A52: ResourceLink HCM / Absence Management | B52: I-000321 | D52: 8 | F52: 1 | J52: =SUM(C52:I52) -> 9
A53: Suggested Rotas | B53: I-000322 | D53: 6.5 | F53: 82.09 | H53: 9 | J53: =SUM(C53:I53) -> 97.59
A54: Security Response Payment Service | B54: I-000323 | J54: =SUM(C54:I54) -> 0
A55: Technical Planning
A56: WordPress Websites | B56: Various | C56: 89.75 | D56: 39.25 | E56: 16 | F56: 2.5 | J56: =SUM(C56:I56) -> 147.5
C57: =SUM(C17:C56) -> 1761.06 | D57: =SUM(D17:D56) -> 731.52 | E57: =SUM(E17:E56) -> 890.34 | F57: =SUM(F17:F56) -> 537.61 | G57: =SUM(G17:G56) -> 139.54 | H57: =SUM(H17:H56) -> 117.5 | I57: =SUM(I17:I56) -> 16.62 | J57: =SUM(C57:I57) -> 4194.19
A60: Support and Maintenance | B60: 24974
A62: Support and Maintenance Hours | B62: Project Code | C62: Customer Support | D62: Project Management, Meetings & Reporting | E62: Maintenance | F62: Systems Admin | G62: Total
A63: Allergens | G63: =SUM(C63:F63) -> 0
A64: Customer Information Screens | E64: 7.85 | G64: =SUM(C64:F64) -> 7.85
A65: Customer App / PWA / App Manager | C65: 2 | G65: =SUM(C65:F65) -> 2
A66: myAuth | G66: =SUM(C66:F66) -> 0
A67: myJDW | C67: 15.18 | E67: 3 | G67: =SUM(C67:F67) -> 18.18
A68: mySchedule | C68: 17.78 | E68: 16.25 | G68: =SUM(C68:F68) -> 34.03
A69: Sitecore Corporate Website | E69: 1.75 | G69: =SUM(C69:F69) -> 1.75
A70: Support for Franchises | G70: =SUM(C70:F70) -> 0
A71: WordPress Websites | C71: 0.5 | G71: =SUM(C71:F71) -> 0.5
C72: =SUM(C63:C71) -> 35.46 | D72: =SUM(D63:D71) -> 0 | E72: =SUM(E63:E71) -> 28.85 | F72: =SUM(F63:F71) -> 0 | G72: =SUM(C72:F72) -> 64.31
A75: Third Party Services | B75: Variable
A77: Company | B77: Website / Application | D77: Contracted To | E77: Per Annum Charge | F77: Per Month Charge | G77: Service Notes
A79: AWS | B79: myJDW, mySchedule, Authentication | D79: JDW | G79: Charged directly to JDW. Figures are converted from dollars at 0.82 pound sterling.
A80: AWS | B80: Customer App | D80: JDW | G80: Charged directly to JDW. Figures are converted from dollars at 0.82 pound sterling.
A81: AWS | B81: Auth0 Wisdom & Customer Accounts PoC | D81: JDW | G81: Charged directly to JDW. Figures are converted from dollars at 0.82 pound sterling.
A82: AWS | B82: Corporate Website Sitecore | D82: JDW | G82: Charged directly to JDW. Figures are converted from dollars at 0.82 pound sterling.
A83: Sendbird | B83: myJDW | D83: JDW | G83: Charged directly to JDW. Filter don't have sight of this fee.
A85: Elastic Search | B85: myJDW & mySchedule | D85: Filter | F85: 56.82 | G85: Fluctuates depending on usage, charged each month. No real increase for mySchedule as there is limited content to search. Not possible to split by service.
A86: Open Weather | B86: mySchedule | D86: Filter | G86: Fluctuates depending on usage, charged each month., currently not hitting limits to be charged.
A87: Ionic Enterprise Package | B87: Customer App | D87: Filter | G87: Enterprise package with live updates.
A88: Ionic Payments | B88: Customer App | D88: Filter | G88: Annual requirement from Feb 24.
A89: Apple Developer Enterprise Program - One year | B89: myJDW | D89: JDW | G89: Recharegd by Filter. Traditionally we haven't marked this cost up.
A90: Google Maps API | B90: Corporate & Hotels Websites | D90: Filter | F90: 1767.46 | G90: Fluctuates depending on usage.
A91: WordPress Plugins Annual Budget | D91: Filter | G91: In use across WordPress websites. Included Corporate website once live. Plugins include: Gravity Forms Elite, Search Pro, PersonalizeWP Pro, WPRocket, Imagify, Media Library Organiser Pro, Advanced Custom Fields, Advanced Post Type Order, Yoast Duplicate Post, Admin Columns Pro, WP Migrate Premier, Wordfence, WP Activity Log. Potentially need to look at this as more of a package moving forwards across all sites.
A92: Website Hosting | B92: Careers | D92: Filter | F92: 750 | G92: This fees will become obsolete if moving to a WP Engine Premier Hosting Solution, see Corporate Website.
A93: Website Hosting | B93: Investors | D93: Filter | F93: 750 | G93: This fees will become obsolete if moving to a WP Engine Premier Hosting Solution, see Corporate Website.
A94: Website Hosting | B94: Hotel | D94: Filter | G94: This fees will become obsolete if moving to a WP Engine Premier Hosting Solution, see Corporate Website.
A95: Website Hosting | B95: Corporate | D95: TBC | G95: The re-platforming will involve the set-up of a multi-site solution to pull together all the microsites into a single platform. WP Engine have proposed two options for this, please see WP Engine / JDW - proposal for the details. We can discuss this further, alongside the decision as to whether Filter will contract on behalf of JDW (at 15% admin fee) or you choose to contract directly with WP Engine. Included is single node fee.
A96: Website Cookie Yes | B96: Corporate | D96: Filter | G96: Outside of standard plugin package.
A97: Website Cookie Yes | B97: Hotel | D97: Filter | G97: Outside of standard plugin package.
A98: Website Yoast SEO Premium | B98: Hotel | D98: Filter | G98: Outside of standard plugin package.
A99: Website Gravity Wiz | B99: myJDW Forms | D99: Filter | E99: 262.53
A100: Website Gravity Flow | B100: myJDW Forms | D100: Filter | E100: 96.92
A101: Statamic | D101: Filter | G101: Reduces after one year to c.£60 per year.
E102: =SUM(E78:E101) -> 359.45 | F102: =SUM(F79:F101) -> 3324.28

Sheet May 24
A1: Month: | B1: 45413
A3: Dedicated Team Billing: | B3: =B9+B60 -> 340813
A4: Fixed Team Target Hours: | B4: =SUM(32*8.5)*23 -> 6256 | C4: 32 FTE
A5: Fixed Team Recorded Hours: | B5: =T13+J57+G72 -> 6256.39
A6: Difference: | B6: =B5-B4 -> 0.39
A9: Planning, Development & Delivery | B9: 315839
C10: R&P | D10: R&P | E10: R&P | F10: R&P | G10: R&P | H10: R&P | I10: TMC | J10: R&P | K10: TMC | L10: TMC | M10: TMC | N10: TMC | O10: TMC | P10: TMC | Q10: TMC | R10: TMC | S10: TMC
A11: Programme Management Hours | B11: Project Code | C11: Planning | D11: Project Management, Meetings & Reporting | E11: Design | F11: Admin | G11: Systems Admin | H11: Research | I11: Training | J11: Finance | K11: HR | L11: Recruitment | M11: Travel | N11: Break | O11: Lunch | P11: Holiday | Q11: Bank Holiday | R11: Sick | S11: Other Absence | T11: Total
C13: 131.92 | D13: 316.68 | E13: =SUM(E12) -> 0 | F13: 59.93 | G13: 172.92 | H13: 57.18 | I13: 141 | J13: 4.75 | K13: 35.55 | L13: 23.34 | M13: 19.5 | N13: 32.71 | O13: 439.98 | P13: 356.75 | Q13: 459 | R13: 22.68 | S13: 15 | T13: =SUM(C13:S13) -> 2288.89
A16: Projects Hours | B16: Project Code | C16: Development | D16: Project Management, Meetings & Reporting | E16: Testing | F16: Planning | G16: Systems Admin | H16: Design | I16: Release | J16: Total
A17: Allergens Service | B17: I-000300 | C17: 22.09 | D17: 10.64 | E17: 104 | F17: 0.75 | I17: 0.25 | J17: =SUM(C17:I17) -> 137.73
A18: Authentication | B18: I-000312 | D18: 32.84 | F18: 14.52 | H18: 20.5 | J18: =SUM(C18:I18) -> 67.86
A19: Available Ales on TV Screens | J19: =SUM(C19:I19) -> 0
A20: Customer Information Screens | B20: I-000313 | D20: 10.83 | F20: 35.5 | H20: 11 | J20: =SUM(C20:I20) -> 57.33
A21: Corporate Website Replatform Build | B21: I-000300 | C21: 230.25 | D21: 44 | E21: 81.25 | F21: 3.5 | H21: 10.25 | J21: =SUM(C21:I21) -> 369.25
A22: Customer Accounts Planning | B22: I-000311 | J22: =SUM(C22:I22) -> 0
A23: Customer App - Ibersol Franchise Integration
A24: Customer App - Lagardere Franchise Integration
A25: Customer App / PWA / App Manager | B25: I-000287 | C25: 777 | D25: 199.34 | E25: 184.67 | F25: 148.3 | G25: 59.92 | H25: 10.25 | I25: 11.5 | J25: =SUM(C25:I25) -> 1390.98
A26: Customer App UX/UI Redesign | J26: =SUM(C26:I26) -> 0
A27: Customer Planning
A28: Digital Pub Records | B28: I-000314 | D28: 3.07 | J28: =SUM(C28:I28) -> 3.07
A29: Digital Vouchers | J29: =SUM(C29:I29) -> 0
A30: Disaster Recovery & Business Continuity | B30: I-000315 | D30: 1 | F30: 1 | J30: =SUM(C30:I30) -> 2
A31: Employee Digital Records | B31: I-000316 | D31: 11.25 | F31: 5.75 | H31: 13.5 | J31: =SUM(C31:I31) -> 30.5
A32: Employee Verification (with WISDOM) | B32: I-000274 | C32: 15.07 | D32: 22.97 | E32: 1.42 | F32: 0.75 | I32: 1.95 | J32: =SUM(C32:I32) -> 42.16
A33: Franchises Customer App | D33: 28.17 | E33: 29.25 | F33: 76.5 | J33: =SUM(C33:I33) -> 133.92
A34: Franchises myJDW | J34: =SUM(C34:I34) -> 0
A35: Franchises mySchedule | J35: =SUM(C35:I35) -> 0
A36: Franchises WordPress Websites
A37: Hotels HLS Integration | J37: =SUM(C37:I37) -> 0
A38: Hotels Price Comparison | B38: I-000317 | D38: 3.5 | J38: =SUM(C38:I38) -> 3.5
A39: Intelligence PoC | B39: I-000318 | C39: 68.75 | D39: 48.33 | E39: 6.5 | F39: 3.75 | H39: 16.83 | I39: 5.5 | J39: =SUM(C39:I39) -> 149.66
A40: Microsoft Office Replacement | J40: =SUM(C40:I40) -> 0
A41: myETL
A42: myPub | B42: I-000319 | J42: =SUM(C42:I42) -> 0
A43: myDiscounts App | B43: I-000320 | D43: 0.5 | J43: =SUM(C43:I43) -> 0.5
A44: myJDW | B44: I-000239 | C44: 257.69 | D44: 155.8 | E44: 214 | F44: 35.55 | H44: 18.25 | I44: 0.48 | J44: =SUM(C44:I44) -> 681.77
A45: mySchedule | B45: I-000271 | C45: 281.73 | D45: 161.69 | E45: 63.25 | F45: 90.84 | G45: 9.25 | H45: 50.75 | I45: 11.67 | J45: =SUM(C45:I45) -> 669.18
A46: People Planning
A47: PCI DSS Compliance | J47: =SUM(C47:I47) -> 0
A48: QR Code Admin Replatform | J48: =SUM(C48:I48) -> 0
A49: Research Project: Possibilities & Benefits of AI | J49: =SUM(C49:I49) -> 0
A50: Out of Stock Screen Scraping | B50: I-000329 | J50: =SUM(C50:I50) -> 0
A51: Pub Ordering & Receipting Planning | B51: I-000330 | J51: =SUM(C51:I51) -> 0
A52: ResourceLink HCM / Absence Management | B52: I-000321 | D52: 4.75 | F52: 0.25 | H52: 1.5 | J52: =SUM(C52:I52) -> 6.5
A53: Suggested Rotas | B53: I-000322 | D53: 5.25 | E53: 1 | F53: 34.09 | J53: =SUM(C53:I53) -> 40.34
A54: Security Response Payment Service | B54: I-000323 | J54: =SUM(C54:I54) -> 0
A55: Technical Planning
A56: WordPress Websites | B56: Various | C56: 10.25 | D56: 18 | E56: 40 | F56: 4 | J56: =SUM(C56:I56) -> 72.25
C57: =SUM(C17:C56) -> 1662.83 | D57: =SUM(D17:D56) -> 761.93 | E57: =SUM(E17:E56) -> 725.34 | F57: =SUM(F17:F56) -> 455.05 | G57: =SUM(G17:G56) -> 69.17 | H57: =SUM(H17:H56) -> 152.83 | I57: =SUM(I17:I56) -> 31.35 | J57: =SUM(C57:I57) -> 3858.5
A60: Support and Maintenance | B60: 24974
A62: Support and Maintenance Hours | B62: Project Code | C62: Customer Support | D62: Project Management, Meetings & Reporting | E62: Maintenance | F62: Systems Admin | G62: Total
A63: Allergens | G63: =SUM(C63:F63) -> 0
A64: Customer Information Screens | C64: 1.5 | E64: 7.75 | G64: =SUM(C64:F64) -> 9.25
A65: Customer App / PWA / App Manager | C65: 5.25 | E65: 5.5 | G65: =SUM(C65:F65) -> 10.75
A66: myAuth | G66: =SUM(C66:F66) -> 0
A67: myJDW | C67: 10.85 | E67: 3 | G67: =SUM(C67:F67) -> 13.85
A68: mySchedule | C68: 47.15 | E68: 15.75 | G68: =SUM(C68:F68) -> 62.9
A69: Sitecore Corporate Website | C69: 7.15 | E69: 4.35 | G69: =SUM(C69:F69) -> 11.5
A70: Support for Franchises | G70: =SUM(C70:F70) -> 0
A71: WordPress Websites | C71: 0.5 | E71: 0.25 | G71: =SUM(C71:F71) -> 0.75
C72: =SUM(C63:C71) -> 72.4 | D72: =SUM(D63:D71) -> 0 | E72: =SUM(E63:E71) -> 36.6 | F72: =SUM(F63:F71) -> 0 | G72: =SUM(C72:F72) -> 109
A75: Third Party Services | B75: Variable
A77: Company | B77: Website / Application | D77: Contracted To | E77: Per Annum Charge | F77: Per Month Charge | G77: Service Notes
A79: AWS | B79: myJDW, mySchedule, Authentication | D79: JDW | G79: Charged directly to JDW. Figures are converted from dollars at 0.82 pound sterling.
A80: AWS | B80: Customer App | D80: JDW | G80: Charged directly to JDW. Figures are converted from dollars at 0.82 pound sterling.
A81: AWS | B81: Auth0 Wisdom & Customer Accounts PoC | D81: JDW | G81: Charged directly to JDW. Figures are converted from dollars at 0.82 pound sterling.
A82: AWS | B82: Corporate Website Sitecore | D82: JDW | G82: Charged directly to JDW. Figures are converted from dollars at 0.82 pound sterling.
A83: AWS | B83: ChatBot AWS Costs | D83: Filter | F83: 167.76 | G83: AWS costs accrued in the Filter account. We have now deleted the main service (Opensearch, which will from now on bring the cost significantly down.
A84: Sendbird | B84: myJDW | D84: JDW | G84: Charged directly to JDW. Filter don't have sight of this fee.
A86: Elastic Search | B86: myJDW & mySchedule | D86: Filter | F86: 56.3 | G86: Fluctuates depending on usage, charged each month. No real increase for mySchedule as there is limited content to search. Not possible to split by service.
A87: Open Weather | B87: mySchedule | D87: Filter | G87: Fluctuates depending on usage, charged each month., currently not hitting limits to be charged.
A88: Ionic Enterprise Package | B88: Customer App | D88: Filter | G88: Enterprise package with live updates.
A89: Ionic Payments | B89: Customer App | D89: Filter | G89: Annual requirement from Feb 24.
A90: Apple Developer Enterprise Program - One year | B90: myJDW | D90: JDW | G90: Recharegd by Filter. Traditionally we haven't marked this cost up.
A91: Google Maps API | B91: Corporate & Hotels Websites | D91: Filter | F91: 1821.12 | G91: Fluctuates depending on usage.
A92: WordPress Plugins Annual Budget | D92: Filter | G92: In use across WordPress websites. Included Corporate website once live. Plugins include: Gravity Forms Elite, Search Pro, PersonalizeWP Pro, WPRocket, Imagify, Media Library Organiser Pro, Advanced Custom Fields, Advanced Post Type Order, Yoast Duplicate Post, Admin Columns Pro, WP Migrate Premier, Wordfence, WP Activity Log. Potentially need to look at this as more of a package moving forwards across all sites.
A93: Website Hosting | B93: Careers | D93: Filter | F93: 750 | G93: This fees will become obsolete if moving to a WP Engine Premier Hosting Solution, see Corporate Website.
A94: Website Hosting | B94: Investors | D94: Filter | F94: 750 | G94: This fees will become obsolete if moving to a WP Engine Premier Hosting Solution, see Corporate Website.
A95: Website Hosting | B95: Hotel | D95: Filter | G95: This fees will become obsolete if moving to a WP Engine Premier Hosting Solution, see Corporate Website.
A96: Website Hosting | B96: Corporate | D96: TBC | G96: The re-platforming will involve the set-up of a multi-site solution to pull together all the microsites into a single platform. WP Engine have proposed two options for this, please see WP Engine / JDW - proposal for the details. We can discuss this further, alongside the decision as to whether Filter will contract on behalf of JDW (at 15% admin fee) or you choose to contract directly with WP Engine. Included is single node fee.
A97: Website Cookie Yes | B97: Corporate | D97: Filter | G97: Outside of standard plugin package.
A98: Website Cookie Yes | B98: Hotel | D98: Filter | G98: Outside of standard plugin package.
A99: Website Yoast SEO Premium | B99: Hotel | D99: Filter | G99: Outside of standard plugin package.
A100: Statamic | D100: Filter | G100: Reduces after one year to c.£60 per year.
E101: =SUM(E78:E100) -> 0 | F101: =SUM(F79:F100) -> 3545.18

Sheet Jun 24
A1: Month: | B1: 45444
A3: Dedicated Team Billing: | B3: =B9+B60 -> 340813
A4: Fixed Team Target Hours: | B4: =SUM(32*8.5)*20 -> 5440 | C4: 32 FTE
A5: Fixed Team Recorded Hours: | B5: =T13+J57+G72 -> 5445.86
A6: Difference: | B6: =B5-B4 -> 5.86
A9: Planning, Development & Delivery | B9: 315839
C10: R&P | D10: R&P | E10: R&P | F10: R&P | G10: R&P | H10: R&P | I10: TMC | J10: R&P | K10: TMC | L10: TMC | M10: TMC | N10: TMC | O10: TMC | P10: TMC | Q10: TMC | R10: TMC | S10: TMC
A11: Programme Management Hours | B11: Project Code | C11: Planning | D11: Project Management, Meetings & Reporting | E11: Design | F11: Admin | G11: Systems Admin | H11: Research | I11: Training | J11: Finance | K11: HR | L11: Recruitment | M11: Travel | N11: Break | O11: Lunch | P11: Holiday | Q11: Bank Holiday | R11: Sick | S11: Other Absence | T11: Total
C13: 67.25 | D13: 301.57 | E13: =SUM(E12) -> 0 | F13: 63.02 | G13: 169.78 | H13: 4.75 | I13: 86.33 | J13: 2.25 | K13: 35.75 | L13: 21.08 | M13: 12.91 | N13: 31.2 | O13: 434.48 | P13: 448 | Q13: 0 | R13: 25.5 | S13: 66.25 | T13: =SUM(C13:S13) -> 1770.12
A16: Projects Hours | B16: Project Code | C16: Development | D16: Project Management, Meetings & Reporting | E16: Testing | F16: Planning | G16: Systems Admin | H16: Design | I16: Release | J16: Total
A17: Allergens Service | B17: I-000300 | C17: 30.64 | D17: 26.61 | E17: 0.75 | G17: 1.5 | I17: 4.75 | J17: =SUM(C17:I17) -> 64.25
A18: Authentication | B18: I-000312 | C18: 91.85 | D18: 76.55 | E18: 4 | F18: 98.82 | G18: 1 | H18: 27.65 | J18: =SUM(C18:I18) -> 299.87
A19: Available Ales on TV Screens | J19: =SUM(C19:I19) -> 0
A20: Customer Information Screens | B20: I-000313 | C20: 74 | D20: 23.25 | F20: 11 | H20: 8.67 | J20: =SUM(C20:I20) -> 116.92
A21: Corporate Website Replatform Build | B21: I-000300 | C21: 323.5 | D21: 27.25 | E21: 7.5 | F21: 4 | H21: 4.5 | J21: =SUM(C21:I21) -> 366.75
A22: Customer Accounts Planning | B22: I-000311 | F22: 2 | J22: =SUM(C22:I22) -> 2
A23: Customer App - Ibersol Franchise Integration
A24: Customer App - Lagardere Franchise Integration
A25: Customer App / PWA / App Manager | B25: I-000287 | C25: 606.16 | D25: =259.88+11.5 -> 271.38 | E25: 293.2 | F25: 166.23 | G25: 120.01 | H25: 10.5 | J25: =SUM(C25:I25) -> 1467.48
A26: Customer App UX/UI Redesign | J26: =SUM(C26:I26) -> 0
A27: Customer Planning
A28: Digital Pub Records | B28: I-000314 | C28: 2.8 | D28: 9.28 | F28: 17.25 | J28: =SUM(C28:I28) -> 29.33
A29: Digital Vouchers | J29: =SUM(C29:I29) -> 0
A30: Disaster Recovery & Business Continuity | B30: I-000315 | D30: 1 | F30: 9 | J30: =SUM(C30:I30) -> 10
A31: Employee Digital Records | B31: I-000316 | D31: 34.42 | F31: 21.25 | H31: 63.75 | J31: =SUM(C31:I31) -> 119.42
A32: Employee Verification (with WISDOM) | B32: I-000274 | C32: 1.45 | D32: 11.45 | J32: =SUM(C32:I32) -> 12.9
A33: Franchises Customer App | D33: 40.09 | F33: 70.75 | G33: 9.75 | H33: 1.5 | J33: =SUM(C33:I33) -> 122.09
A34: Franchises myJDW | J34: =SUM(C34:I34) -> 0
A35: Franchises mySchedule | J35: =SUM(C35:I35) -> 0
A36: Franchises WordPress Websites
A37: Hotels HLS Integration | J37: =SUM(C37:I37) -> 0
A38: Hotels Price Comparison | B38: I-000317 | J38: =SUM(C38:I38) -> 0
A39: Intelligence PoC | B39: I-000318 | C39: 2 | D39: 9.25 | F39: 13.25 | H39: 23.25 | J39: =SUM(C39:I39) -> 47.75
A40: Microsoft Office Replacement | J40: =SUM(C40:I40) -> 0
A41: myETL
A42: myPub | B42: I-000319 | D42: 0.25 | F42: 1 | J42: =SUM(C42:I42) -> 1.25
A43: myDiscounts App | B43: I-000320 | J43: =SUM(C43:I43) -> 0
A44: myJDW | B44: I-000239 | C44: 162.13 | D44: 110.09 | E44: 1 | F44: 11 | H44: 16.25 | I44: 1.87 | J44: =SUM(C44:I44) -> 302.34
A45: mySchedule | B45: I-000271 | C45: 176.07 | D45: 112.73 | F45: 71.43 | H45: 2.5 | I45: 2 | J45: =SUM(C45:I45) -> 364.73
A46: People Planning
A47: PCI DSS Compliance | J47: =SUM(C47:I47) -> 0
A48: QR Code Admin Replatform | J48: =SUM(C48:I48) -> 0
A49: Research Project: Possibilities & Benefits of AI | J49: =SUM(C49:I49) -> 0
A50: Out of Stock Screen Scraping | B50: I-000329 | J50: =SUM(C50:I50) -> 0
A51: Pub Ordering & Receipting Planning | B51: I-000330 | J51: =SUM(C51:I51) -> 0
A52: ResourceLink HCM / Absence Management | B52: I-000321 | D52: 5 | J52: =SUM(C52:I52) -> 5
A53: Suggested Rotas | B53: I-000322 | C53: 109.75 | D53: 75.95 | F53: 63.42 | H53: 47.25 | J53: =SUM(C53:I53) -> 296.37
A54: Security Response Payment Service | B54: I-000323 | J54: =SUM(C54:I54) -> 0
A55: Technical Planning
A56: WordPress Websites | B56: Various | J56: =SUM(C56:I56) -> 0
C57: =SUM(C17:C56) -> 1580.35 | D57: =SUM(D17:D56) -> 834.55 | E57: =SUM(E17:E56) -> 306.45 | F57: =SUM(F17:F56) -> 560.4 | G57: =SUM(G17:G56) -> 132.26 | H57: =SUM(H17:H56) -> 205.82 | I57: =SUM(I17:I56) -> 8.62 | J57: =SUM(C57:I57) -> 3628.45
A60: Support and Maintenance | B60: 24974
A62: Support and Maintenance Hours | B62: Project Code | C62: Customer Support | D62: Project Management, Meetings & Reporting | E62: Maintenance | F62: Systems Admin | G62: Total
A63: Allergens | G63: =SUM(C63:F63) -> 0
A64: Customer Information Screens | E64: 2.75 | G64: =SUM(C64:F64) -> 2.75
A65: Customer App / PWA / App Manager | C65: 1.95 | G65: =SUM(C65:F65) -> 1.95
A66: myAuth | G66: =SUM(C66:F66) -> 0
A67: myJDW | C67: 14.56 | E67: 2.75 | G67: =SUM(C67:F67) -> 17.31
A68: mySchedule | C68: 17.73 | E68: 4 | G68: =SUM(C68:F68) -> 21.73
A69: Sitecore Corporate Website | E69: 2.75 | G69: =SUM(C69:F69) -> 2.75
A70: Support for Franchises | G70: =SUM(C70:F70) -> 0
A71: WordPress Websites | C71: 0.8 | G71: =SUM(C71:F71) -> 0.8
C72: =SUM(C63:C71) -> 35.04 | D72: =SUM(D63:D71) -> 0 | E72: =SUM(E63:E71) -> 12.25 | F72: =SUM(F63:F71) -> 0 | G72: =SUM(C72:F72) -> 47.29
A75: Third Party Services | B75: Variable
A77: Company | B77: Website / Application | D77: Contracted To | E77: Per Annum Charge | F77: Per Month Charge | G77: Service Notes
A79: AWS | B79: myJDW, mySchedule, Authentication | D79: JDW | G79: Charged directly to JDW. Figures are converted from dollars at 0.82 pound sterling.
A80: AWS | B80: Customer App | D80: JDW | G80: Charged directly to JDW. Figures are converted from dollars at 0.82 pound sterling.
A81: AWS | B81: Auth0 Wisdom & Customer Accounts PoC | D81: JDW | G81: Charged directly to JDW. Figures are converted from dollars at 0.82 pound sterling.
A82: AWS | B82: Corporate Website Sitecore | D82: JDW | G82: Charged directly to JDW. Figures are converted from dollars at 0.82 pound sterling.
A83: AWS | B83: ChatBot AWS Costs | D83: Filter | F83: 210.13
A84: Sendbird | B84: myJDW | D84: JDW | G84: Charged directly to JDW. Filter don't have sight of this fee.
A86: Elastic Search | B86: myJDW & mySchedule | D86: Filter | F86: 55.39 | G86: Fluctuates depending on usage, charged each month. No real increase for mySchedule as there is limited content to search. Not possible to split by service.
A87: Open Weather | B87: mySchedule | D87: Filter | G87: Fluctuates depending on usage, charged each month., currently not hitting limits to be charged.
A88: Ionic Enterprise Package | B88: Customer App | D88: Filter | G88: Enterprise package with live updates.
A89: Ionic Payments | B89: Customer App | D89: Filter | G89: Annual requirement from Feb 24.
A90: Apple Developer Enterprise Program - One year | B90: myJDW | D90: JDW | G90: Recharegd by Filter. Traditionally we haven't marked this cost up.
A91: Google Maps API | B91: Corporate & Hotels Websites | D91: Filter | F91: 1856.13 | G91: Fluctuates depending on usage.
A92: WordPress Plugins Annual Budget | D92: Filter | G92: In use across WordPress websites. Included Corporate website once live. Plugins include: Gravity Forms Elite, Search Pro, PersonalizeWP Pro, WPRocket, Imagify, Media Library Organiser Pro, Advanced Custom Fields, Advanced Post Type Order, Yoast Duplicate Post, Admin Columns Pro, WP Migrate Premier, Wordfence, WP Activity Log. Potentially need to look at this as more of a package moving forwards across all sites.
A93: Website Hosting | B93: Careers | D93: Filter | F93: 750 | G93: This fees will become obsolete if moving to a WP Engine Premier Hosting Solution, see Corporate Website.
A94: Website Hosting | B94: Investors | D94: Filter | F94: 750 | G94: This fees will become obsolete if moving to a WP Engine Premier Hosting Solution, see Corporate Website.
A95: Website Hosting | B95: Hotel | D95: Filter | G95: This fees will become obsolete if moving to a WP Engine Premier Hosting Solution, see Corporate Website.
A96: Website Hosting | B96: Corporate | D96: TBC | G96: The re-platforming will involve the set-up of a multi-site solution to pull together all the microsites into a single platform. WP Engine have proposed two options for this, please see WP Engine / JDW - proposal for the details. We can discuss this further, alongside the decision as to whether Filter will contract on behalf of JDW (at 15% admin fee) or you choose to contract directly with WP Engine. Included is single node fee.
A97: Website Cookie Yes | B97: Corporate | D97: Filter | G97: Outside of standard plugin package.
A98: Website Cookie Yes | B98: Hotel | D98: Filter | G98: Outside of standard plugin package.
A99: Website Yoast SEO Premium | B99: Hotel | D99: Filter | G99: Outside of standard plugin package.
A100: Statamic | D100: Filter | G100: Reduces after one year to c.£60 per year.
E101: =SUM(E78:E100) -> 0 | F101: =SUM(F79:F100) -> 3621.65

Sheet Jul 24
A1: Month: | B1: 45474
A3: Dedicated Team Billing: | B3: =B9+B60 -> 340813
A4: Fixed Team Target Hours: | B4: =SUM(32*8.5)*22 -> 5984 | C4: 32 FTE
A5: Fixed Team Recorded Hours: | B5: =T13+J57+G72 -> 6356.86
A6: Difference: | B6: =B5-B4 -> 372.86
A9: Planning, Development & Delivery | B9: 315839
C10: R&P | D10: R&P | E10: R&P | F10: R&P | G10: R&P | H10: R&P | I10: TMC | J10: R&P | K10: TMC | L10: TMC | M10: TMC | N10: TMC | O10: TMC | P10: TMC | Q10: TMC | R10: TMC | S10: TMC
A11: Programme Management Hours | B11: Project Code | C11: Planning | D11: Project Management, Meetings & Reporting | E11: Design | F11: Admin | G11: Systems Admin | H11: Research | I11: Training | J11: Finance | K11: HR | L11: Recruitment | M11: Travel | N11: Break | O11: Lunch | P11: Holiday | Q11: Bank Holiday | R11: Sick | S11: Other Absence | T11: Total
C13: 56 | D13: 414.9 | F13: 57.25 | G13: 225.97 | H13: 27 | I13: 13.62 | J13: 5 | K13: 29.5 | L13: 14.33 | M13: 17.5 | N13: 29.14 | O13: 455.34 | P13: 516 | R13: 16 | S13: 189 | T13: =SUM(C13:S13) -> 2066.55
A16: Projects Hours | B16: Project Code | C16: Development | D16: Project Management, Meetings & Reporting | E16: Testing | F16: Planning | G16: Systems Admin | H16: Design | I16: Release | J16: Total
A17: Allergens Service | B17: I-000300 | C17: 2.25 | D17: 27.42 | E17: 6.5 | G17: 2.75 | H17: 2.5 | I17: 4.28 | J17: =SUM(C17:I17) -> 45.7
A18: Authentication | B18: I-000312 | C18: 76.57 | D18: 36.67 | F18: 67.85 | H18: 32.97 | J18: =SUM(C18:I18) -> 214.06
A19: Available Ales on TV Screens | J19: =SUM(C19:I19) -> 0
A20: Customer Information Screens | B20: I-000313 | C20: 92 | D20: 23.75 | E20: 6.5 | F20: 1.25 | H20: 0.5 | J20: =SUM(C20:I20) -> 124
A21: Corporate Website Replatform Build | B21: I-000300 | C21: 107.84 | D21: 64 | E21: 160.75 | F21: 3 | H21: 2.5 | I21: 13.75 | J21: =SUM(C21:I21) -> 351.84
A22: Customer Accounts Planning | B22: I-000311 | C22: 26.67 | D22: 34.75 | E22: 3.75 | F22: 56.42 | G22: 10 | H22: 15.25 | I22: 3 | J22: =SUM(C22:I22) -> 149.84
A23: Customer App - Ibersol Franchise Integration
A24: Customer App - Lagardere Franchise Integration
A25: Customer App / PWA / App Manager | B25: I-000287 | C25: 690.11 | D25: 360.12 | E25: 340.92 | F25: 60.41 | G25: 188.23 | H25: 79.5 | I25: 99 | J25: =SUM(C25:I25) -> 1818.29
A26: Customer App UX/UI Redesign | J26: =SUM(C26:I26) -> 0
A27: Customer Planning
A28: Digital Pub Records | B28: I-000314 | D28: 22.75 | F28: 10.75 | H28: 15.5 | J28: =SUM(C28:I28) -> 49
A29: Digital Vouchers | J29: =SUM(C29:I29) -> 0
A30: Disaster Recovery & Business Continuity | B30: I-000315 | D30: 8.25 | F30: 5 | G30: 0.5 | J30: =SUM(C30:I30) -> 13.75
A31: Employee Digital Records | B31: I-000316 | D31: 47.5 | F31: 30.5 | H31: 25 | J31: =SUM(C31:I31) -> 103
A32: Employee Verification (with WISDOM) | B32: I-000274 | C32: 10.53 | D32: 6.7 | I32: 3.58 | J32: =SUM(C32:I32) -> 20.81
A33: Franchises Customer App | D33: 26.5 | F33: 31 | J33: =SUM(C33:I33) -> 57.5
A34: Franchises myJDW | J34: =SUM(C34:I34) -> 0
A35: Franchises mySchedule | J35: =SUM(C35:I35) -> 0
A36: Franchises WordPress Websites
A37: Hotels HLS Integration | J37: =SUM(C37:I37) -> 0
A38: Hotels Price Comparison | B38: I-000317 | J38: =SUM(C38:I38) -> 0
A39: Intelligence PoC | B39: I-000318 | D39: 43.17 | F39: 31.25 | H39: 45 | J39: =SUM(C39:I39) -> 119.42
A40: Microsoft Office Replacement | J40: =SUM(C40:I40) -> 0
A41: myETL
A42: myPub | B42: I-000319 | D42: 28.66 | F42: 22.92 | J42: =SUM(C42:I42) -> 51.58
A43: myDiscounts App | B43: I-000320 | J43: =SUM(C43:I43) -> 0
A44: myJDW | B44: I-000239 | C44: 246.99 | D44: 122.64 | E44: 14 | F44: 13 | H44: 13.25 | I44: 2.58 | J44: =SUM(C44:I44) -> 412.46
A45: mySchedule | B45: I-000271 | C45: 197.79 | D45: 88.47 | F45: 84.85 | I45: 8.3 | J45: =SUM(C45:I45) -> 379.41
A46: People Planning
A47: PCI DSS Compliance | J47: =SUM(C47:I47) -> 0
A48: QR Code Admin Replatform | J48: =SUM(C48:I48) -> 0
A49: Research Project: Possibilities & Benefits of AI | J49: =SUM(C49:I49) -> 0
A50: Out of Stock Screen Scraping | B50: I-000329 | J50: =SUM(C50:I50) -> 0
A51: Pub Ordering & Receipting Planning | B51: I-000330 | J51: =SUM(C51:I51) -> 0
A52: ResourceLink HCM / Absence Management | B52: I-000321 | D52: 6.75 | J52: =SUM(C52:I52) -> 6.75
A53: Suggested Rotas | B53: I-000322 | C53: 129.09 | D53: 22.5 | F53: 46.75 | H53: 25.59 | J53: =SUM(C53:I53) -> 223.93
A54: Security Response Payment Service | B54: I-000323 | J54: =SUM(C54:I54) -> 0
A55: Technical Planning
A56: WordPress Websites | B56: Various | D56: 35.75 | F56: 16.5 | J56: =SUM(C56:I56) -> 52.25
C57: =SUM(C17:C56) -> 1579.84 | D57: =SUM(D17:D56) -> 1006.35 | E57: =SUM(E17:E56) -> 532.42 | F57: =SUM(F17:F56) -> 481.45 | G57: =SUM(G17:G56) -> 201.48 | H57: =SUM(H17:H56) -> 257.56 | I57: =SUM(I17:I56) -> 134.49 | J57: =SUM(C57:I57) -> 4193.59
A60: Support and Maintenance | B60: 24974
A62: Support and Maintenance Hours | B62: Project Code | C62: Customer Support | D62: Project Management, Meetings & Reporting | E62: Maintenance | F62: Systems Admin | G62: Total
A63: Allergens | G63: =SUM(C63:F63) -> 0
A64: Customer Information Screens | C64: 1.75 | E64: 2.5 | G64: =SUM(C64:F64) -> 4.25
A65: Customer App / PWA / App Manager | C65: 44.5 | E65: 19.5 | G65: =SUM(C65:F65) -> 64
A66: myAuth | G66: =SUM(C66:F66) -> 0
A67: myJDW | C67: 14.92 | E67: 0.5 | G67: =SUM(C67:F67) -> 15.42
A68: mySchedule | C68: 3.25 | E68: 4.5 | G68: =SUM(C68:F68) -> 7.75
A69: Sitecore Corporate Website | C69: 1.25 | E69: 0.3 | G69: =SUM(C69:F69) -> 1.55
A70: Support for Franchises | G70: =SUM(C70:F70) -> 0
A71: WordPress Websites | C71: 2.75 | E71: 1 | G71: =SUM(C71:F71) -> 3.75
C72: =SUM(C63:C71) -> 68.42 | D72: =SUM(D63:D71) -> 0 | E72: =SUM(E63:E71) -> 28.3 | F72: =SUM(F63:F71) -> 0 | G72: =SUM(C72:F72) -> 96.72
A75: Third Party Services | B75: Variable
A77: Company | B77: Website / Application | D77: Contracted To | E77: Per Annum Charge | F77: Per Month Charge | G77: Service Notes
A79: AWS | B79: myJDW, mySchedule, Authentication | D79: JDW | G79: Charged directly to JDW. Figures are converted from dollars at 0.82 pound sterling.
A80: AWS | B80: Customer App | D80: JDW | G80: Charged directly to JDW. Figures are converted from dollars at 0.82 pound sterling.
A81: AWS | B81: Auth0 Wisdom & Customer Accounts PoC | D81: JDW | G81: Charged directly to JDW. Figures are converted from dollars at 0.82 pound sterling.
A82: AWS | B82: Corporate Website Sitecore | D82: JDW | G82: Charged directly to JDW. Figures are converted from dollars at 0.82 pound sterling.
A83: AWS | B83: ChatBot AWS Costs | D83: Filter
A84: Sendbird | B84: myJDW | D84: JDW | G84: Charged directly to JDW. Filter don't have sight of this fee.
A86: Elastic Search | B86: myJDW & mySchedule | D86: Filter | F86: 57.29 | G86: Fluctuates depending on usage, charged each month. No real increase for mySchedule as there is limited content to search. Not possible to split by service.
A87: Open Weather | B87: mySchedule | D87: Filter | G87: Fluctuates depending on usage, charged each month., currently not hitting limits to be charged.
A88: Ionic Enterprise Package | B88: Customer App | D88: Filter | G88: Enterprise package with live updates.
A89: Ionic Payments | B89: Customer App | D89: Filter | G89: Annual requirement from Feb 24.
A90: Apple Developer Enterprise Program - One year | B90: myJDW | D90: JDW | G90: Recharegd by Filter. Traditionally we haven't marked this cost up.
A91: Google Maps API | B91: Customer App, Corporate & Hotels Websites | D91: Filter | F91: 30474.29 | G91: Fluctuates depending on usage.
A92: WordPress Plugins Annual Budget | D92: Filter | G92: In use across WordPress websites. Included Corporate website once live. Plugins include: Gravity Forms Elite, Search Pro, PersonalizeWP Pro, WPRocket, Imagify, Media Library Organiser Pro, Advanced Custom Fields, Advanced Post Type Order, Yoast Duplicate Post, Admin Columns Pro, WP Migrate Premier, Wordfence, WP Activity Log. Potentially need to look at this as more of a package moving forwards across all sites.
A93: Website Hosting | B93: Careers | D93: Filter | F93: 500 | G93: This fee will become obsolete from August, with move to dedicated WPEngine hosting charged directly to JDW.
A94: Website Hosting | B94: Investors | D94: Filter | F94: 500 | G94: This fee will become obsolete from August, with move to dedicated WPEngine hosting charged directly to JDW.
A95: Website Hosting | B95: Hotel | D95: Filter | G95: This fees will become obsolete if moving to a WP Engine Premier Hosting Solution, see Corporate Website.
A96: Website Hosting | B96: Corporate | D96: TBC | G96: The re-platforming will involve the set-up of a multi-site solution to pull together all the microsites into a single platform. WP Engine have proposed two options for this, please see WP Engine / JDW - proposal for the details. We can discuss this further, alongside the decision as to whether Filter will contract on behalf of JDW (at 15% admin fee) or you choose to contract directly with WP Engine. Included is single node fee.
A97: Website Cookie Yes | B97: Corporate | D97: Filter | G97: Outside of standard plugin package.
A98: Website Cookie Yes | B98: Hotel | D98: Filter | G98: Outside of standard plugin package.
A99: Website Yoast SEO Premium | B99: Hotel | D99: Filter | G99: Outside of standard plugin package.
A100: Statamic | D100: Filter | G100: Reduces after one year to c.£60 per year.
E101: =SUM(E78:E100) -> 0 | F101: =SUM(F79:F100) -> 31531.58

Sheet Aug 24
A1: Month: | B1: 45505
A3: Dedicated Team Billing: | B3: =B9+B60 -> 340813
A4: Fixed Team Target Hours: | B4: =SUM(32*8.5)*22 -> 5984 | C4: 32 FTE
A5: Fixed Team Recorded Hours: | B5: 6148.68
A6: Difference: | B6: =B5-B4 -> 164.68
A9: Planning, Development & Delivery | B9: 315839
C10: R&P | D10: R&P | E10: R&P | F10: R&P | G10: R&P | H10: R&P | I10: TMC | J10: R&P | K10: TMC | L10: TMC | M10: TMC | N10: TMC | O10: TMC | P10: TMC | Q10: TMC | R10: TMC | S10: TMC
A11: Programme Management Hours | B11: Project Code | C11: Planning | D11: Project Management, Meetings & Reporting | E11: Design | F11: Admin | G11: Systems Admin | H11: Research | I11: Training | J11: Finance | K11: HR | L11: Recruitment | M11: Travel | N11: Break | O11: Lunch | P11: Holiday | Q11: Bank Holiday | R11: Sick | S11: Other Absence | T11: Total
C13: 16.76 | D13: 351.47 | F13: 16.23 | G13: 124.84 | H13: 3 | I13: 7.75 | J13: 4.75 | K13: 36.75 | M13: 11.58 | N13: 41.74 | O13: 405.26 | P13: 812.75 | Q13: 256.5 | R13: 31.5 | S13: 187 | T13: =SUM(C13:S13) -> 2307.88
A16: Projects Hours | B16: Project Code | C16: Development | D16: Project Management, Meetings & Reporting | E16: Testing | F16: Planning | G16: Systems Admin | H16: Design | I16: Release | J16: Total
A17: Allergens Service | B17: I-000300 | C17: 0.58 | D17: 1 | G17: 0.5 | J17: =SUM(C17:I17) -> 2.08
A18: Authentication | B18: I-000312 | C18: 69.72 | D18: 44.19 | F18: 18.75 | H18: 3.17 | J18: =SUM(C18:I18) -> 135.83
A19: Available Ales on TV Screens | J19: =SUM(C19:I19) -> 0
A20: Customer Information Screens | B20: I-000313 | C20: 21.66 | D20: 4.75 | E20: 3.5 | I20: 0.75 | J20: =SUM(C20:I20) -> 30.66
A21: Corporate Website Replatform Build | B21: I-000300 | C21: 33.42 | D21: 6 | E21: 1 | F21: 0.5 | H21: 3.75 | I21: 1 | J21: =SUM(C21:I21) -> 45.67
A22: Customer Accounts Planning | B22: I-000311 | C22: 121.25 | D22: 17 | E22: 6.25 | F22: 24 | G22: 14.75 | H22: 12.75 | J22: =SUM(C22:I22) -> 196
A23: Customer App - Ibersol Franchise Integration
A24: Customer App - Lagardere Franchise Integration
A25: Customer App / PWA / App Manager | B25: I-000287 | C25: 614.52 | D25: 350.75 | E25: 211.25 | F25: 217.65 | G25: 129.34 | H25: 19.6 | I25: 9 | J25: =SUM(C25:I25) -> 1552.11
A26: Customer App UX/UI Redesign | J26: =SUM(C26:I26) -> 0
A27: Customer Planning
A28: Digital Pub Records | B28: I-000314 | C28: 0.42 | D28: 35.8 | F28: 25 | H28: 6.75 | J28: =SUM(C28:I28) -> 67.97
A29: Digital Vouchers | J29: =SUM(C29:I29) -> 0
A30: Disaster Recovery & Business Continuity | B30: I-000315 | D30: 2.5 | J30: =SUM(C30:I30) -> 2.5
A31: Employee Digital Records | B31: I-000316 | D31: 24.5 | F31: 12.5 | H31: 22.75 | J31: =SUM(C31:I31) -> 59.75
A32: Employee Verification (with WISDOM) | B32: I-000274 | J32: =SUM(C32:I32) -> 0
A33: Franchises Customer App | C33: 25.5 | D33: 16.75 | F33: 2.25 | H33: 0.5 | J33: =SUM(C33:I33) -> 45
A34: Franchises myJDW | J34: =SUM(C34:I34) -> 0
A35: Franchises mySchedule | J35: =SUM(C35:I35) -> 0
A36: Franchises WordPress Websites
A37: Hotels HLS Integration | J37: =SUM(C37:I37) -> 0
A38: Hotels Price Comparison | B38: I-000317 | J38: =SUM(C38:I38) -> 0
A39: Intelligence PoC | B39: I-000318 | D39: 11.25 | F39: 5.75 | H39: 1 | J39: =SUM(C39:I39) -> 18
A40: Microsoft Office Replacement | J40: =SUM(C40:I40) -> 0
A41: myETL
A42: myPub | B42: I-000319 | D42: 43.26 | F42: 112.66 | J42: =SUM(C42:I42) -> 155.92
A43: myDiscounts App | B43: I-000320 | F43: 1 | J43: =SUM(C43:I43) -> 1
A44: myJDW | B44: I-000239 | C44: 311.83 | D44: 128.96 | E44: 25 | F44: 44 | H44: 22.5 | J44: =SUM(C44:I44) -> 532.29
A45: mySchedule | B45: I-000271 | C45: 231.86 | D45: 146.95 | F45: 83.09 | G45: 3.75 | H45: 4.75 | I45: 12.94 | J45: =SUM(C45:I45) -> 483.34
A46: People Planning
A47: PCI DSS Compliance | J47: =SUM(C47:I47) -> 0
A48: QR Code Admin Replatform | J48: =SUM(C48:I48) -> 0
A49: Research Project: Possibilities & Benefits of AI | J49: =SUM(C49:I49) -> 0
A50: Out of Stock Screen Scraping | B50: I-000329 | J50: =SUM(C50:I50) -> 0
A51: Pub Ordering & Receipting Planning | B51: I-000330 | J51: =SUM(C51:I51) -> 0
A52: ResourceLink HCM / Absence Management | B52: I-000321 | D52: 15.5 | F52: 6 | J52: =SUM(C52:I52) -> 21.5
A53: Suggested Rotas | B53: I-000322 | C53: 140.01 | D53: 37.25 | F53: 7 | H53: 2 | J53: =SUM(C53:I53) -> 186.26
A54: Security Response Payment Service | B54: I-000323 | J54: =SUM(C54:I54) -> 0
A55: Technical Planning
A56: WordPress Websites | B56: Various | C56: 128.17 | D56: 37.5 | F56: 34.75 | J56: =SUM(C56:I56) -> 200.42
C57: =SUM(C17:C56) -> 1698.94 | D57: =SUM(D17:D56) -> 923.91 | E57: =SUM(E17:E56) -> 247 | F57: =SUM(F17:F56) -> 594.9 | G57: =SUM(G17:G56) -> 148.34 | H57: =SUM(H17:H56) -> 99.52 | I57: =SUM(I17:I56) -> 23.69 | J57: =SUM(C57:I57) -> 3736.3
A60: Support and Maintenance | B60: 24974
A62: Support and Maintenance Hours | B62: Project Code | C62: Customer Support | D62: Project Management, Meetings & Reporting | E62: Maintenance | F62: Systems Admin | G62: Total
A63: Allergens | G63: =SUM(C63:F63) -> 0
A64: Customer Information Screens | C64: 1.75 | E64: 0.75 | G64: =SUM(C64:F64) -> 2.5
A65: Customer App / PWA / App Manager | C65: 22.85 | E65: 21 | G65: =SUM(C65:F65) -> 43.85
A66: myAuth | G66: =SUM(C66:F66) -> 0
A67: myJDW | C67: 43.9 | E67: 0.25 | G67: =SUM(C67:F67) -> 44.15
A68: mySchedule | C68: 5.75 | E68: 2.75 | G68: =SUM(C68:F68) -> 8.5
A69: Sitecore Corporate Website | E69: 0.25 | G69: =SUM(C69:F69) -> 0.25
A70: Support for Franchises | G70: =SUM(C70:F70) -> 0
A71: WordPress Websites | C71: 5.25 | G71: =SUM(C71:F71) -> 5.25
C72: =SUM(C63:C71) -> 79.5 | D72: =SUM(D63:D71) -> 0 | E72: =SUM(E63:E71) -> 25 | F72: =SUM(F63:F71) -> 0 | G72: =SUM(C72:F72) -> 104.5
A75: Third Party Services | B75: Variable
A77: Company | B77: Website / Application | D77: Contracted To | E77: Frequency | F77: Per Annum Charge | G77: Per Month Charge | H77: Service Notes
A79: AWS | B79: myJDW, mySchedule, Authentication | D79: JDW | E79: Monthly | H79: Charged directly to JDW. Figures are converted from dollars at 0.82 pound sterling.
A80: AWS | B80: Customer App | D80: JDW | E80: Monthly | H80: Charged directly to JDW. Figures are converted from dollars at 0.82 pound sterling.
A81: AWS | B81: Auth0 Wisdom & Customer Accounts PoC | D81: JDW | E81: Monthly | H81: Charged directly to JDW. Figures are converted from dollars at 0.82 pound sterling.
A82: AWS | B82: Corporate Website Sitecore | D82: JDW | E82: NA | H82: Charged directly to JDW. Figures are converted from dollars at 0.82 pound sterling.
A83: AWS | B83: Rota Automation & ChatBot AWS Costs | D83: JDW | E83: Monthly
A84: Sendbird | B84: myJDW | D84: JDW | E84: Monthly | H84: Charged directly to JDW. Filter don't have sight of this fee.
A86: Elastic Search | B86: myJDW & mySchedule | D86: Filter | E86: Monthly | G86: 57.52 | H86: Fluctuates depending on usage, charged each month. No real increase for mySchedule as there is limited content to search. Not possible to split by service.
A87: Open Weather | B87: mySchedule | D87: Filter | E87: Monthly | H87: Fluctuates depending on usage, charged each month., currently not hitting limits to be charged.
A88: Ionic Enterprise Package | B88: Customer App | D88: Filter | E88: Annual | H88: Enterprise package with live updates.
A89: Ionic Payments | B89: Customer App | D89: Filter | E89: Annual | H89: Annual requirement from Feb 24.
A90: Apple Developer Enterprise Program - One year | B90: myJDW | D90: JDW | E90: Annual | H90: Recharegd by Filter. Traditionally we haven't marked this cost up.
A91: Google Maps API | B91: Customer App, Corporate & Hotels Websites | D91: Filter | E91: Monthly | G91: 19747.75 | H91: Fluctuates depending on usage.
A92: WordPress Plugins Annual Budget | D92: Filter | E92: Annual | H92: In use across WordPress websites. Included Corporate website once live. Plugins include: Gravity Forms Elite, Search Pro, PersonalizeWP Pro, WPRocket, Imagify, Media Library Organiser Pro, Advanced Custom Fields, Advanced Post Type Order, Yoast Duplicate Post, Admin Columns Pro, WP Migrate Premier, Wordfence, WP Activity Log. Potentially need to look at this as more of a package moving forwards across all sites.
A93: WPEngine Website Hosting | B93: Careers | D93: JDW | E93: Monthly | H93: This fee will become obsolete from August, with move to dedicated WPEngine hosting charged directly to JDW.
A94: WPEngine Website Hosting | B94: Investors | D94: JDW | E94: Monthly | H94: This fee will become obsolete from August, with move to dedicated WPEngine hosting charged directly to JDW.
A95: WPEngine Website Hosting | B95: Hotel | D95: JDW | E95: Monthly | H95: This fees will become obsolete if moving to a WP Engine Premier Hosting Solution, see Corporate Website.
A96: WPEngine Website Hosting | B96: Corporate | D96: JDW | E96: Monthly | H96: The re-platforming will involve the set-up of a multi-site solution to pull together all the microsites into a single platform. WP Engine have proposed two options for this, please see WP Engine / JDW - proposal for the details. We can discuss this further, alongside the decision as to whether Filter will contract on behalf of JDW (at 15% admin fee) or you choose to contract directly with WP Engine. Included is single node fee.
A97: Website Cookie Yes | B97: Corporate | D97: Filter | E97: Annual | H97: Outside of standard plugin package.
A98: Website Cookie Yes | B98: Hotel | D98: Filter | E98: Annual | H98: Outside of standard plugin package.
A99: Website Yoast SEO Premium | B99: Hotel | D99: Filter | E99: Annual | H99: Outside of standard plugin package.
A100: Statamic | D100: Filter | E100: Annual | H100: Reduces after one year to c.£60 per year.
F101: =SUM(F78:F100) -> 0 | G101: =SUM(G79:G100) -> 19805.27

Sheet Sep 24
A1: Month: | B1: 45536
A3: Dedicated Team Billing: | B3: =B9+B60 -> 340813
A4: Fixed Team Target Hours: | B4: =SUM(32*8.5)*21 -> 5712 | C4: 32 FTE
A5: Fixed Team Recorded Hours: | B5: 5949.36
A6: Difference: | B6: =B5-B4 -> 237.36
A9: Planning, Development & Delivery | B9: 315839
C10: R&P | D10: R&P | E10: R&P | F10: R&P | G10: R&P | H10: R&P | I10: TMC | J10: R&P | K10: TMC | L10: TMC | M10: TMC | N10: TMC | O10: TMC | P10: TMC | Q10: TMC | R10: TMC | S10: TMC
A11: Programme Management Hours | B11: Project Code | C11: Planning | D11: Project Management, Meetings & Reporting | E11: Design | F11: Admin | G11: Systems Admin | H11: Research | I11: Training | J11: Finance | K11: HR | L11: Recruitment | M11: Travel | N11: Break | O11: Lunch | P11: Holiday | Q11: Bank Holiday | R11: Sick | S11: Other Absence | T11: Total
C13: 45.5 | D13: 360.73 | F13: 22 | G13: 129.42 | H13: 5.25 | J13: 2 | K13: 35.18 | L13: 3 | M13: 12.25 | N13: 55.5 | O13: 418 | P13: 461.25 | S13: 9.5 | T13: =SUM(C13:S13) -> 1559.58
A16: Projects Hours | B16: Project Code | C16: Development | D16: Project Management, Meetings & Reporting | E16: Testing | F16: Planning | G16: Systems Admin | H16: Design | I16: Release | J16: Total
A17: Allergens Service | B17: I-000300 | J17: =SUM(C17:I17) -> 0
A18: Authentication | B18: I-000312 | C18: 102.82 | D18: 39.49 | F18: 28.5 | J18: =SUM(C18:I18) -> 170.81
A19: Available Ales on TV Screens | J19: =SUM(C19:I19) -> 0
A20: Customer Information Screens | B20: I-000313 | C20: 40.25 | D20: 11 | E20: 6.5 | J20: =SUM(C20:I20) -> 57.75
A21: Corporate Website Replatform Build | B21: I-000300 | C21: 34.5 | D21: 5.75 | E21: 0.25 | F21: 3 | H21: 0.75 | I21: 1.25 | J21: =SUM(C21:I21) -> 45.5
A22: Customer Accounts Planning | B22: I-000311 | C22: 158.84 | D22: 19.67 | E22: 1 | F22: 57.25 | G22: 1 | H22: 3.25 | J22: =SUM(C22:I22) -> 241.01
A23: Customer App - Ibersol Franchise Integration
A24: Customer App - Lagardere Franchise Integration
A25: Customer App / PWA / App Manager | B25: I-000287 | C25: 728.06 | D25: 339.39 | E25: 223.51 | F25: 115.75 | G25: 106.84 | H25: 24.5 | J25: =SUM(C25:I25) -> 1538.05
A26: Customer App UX/UI Redesign | J26: =SUM(C26:I26) -> 0
A27: Customer Planning
A28: Digital Pub Records | B28: I-000314 | D28: 25.09 | F28: 11.5 | H28: 4 | J28: =SUM(C28:I28) -> 40.59
A29: Digital Vouchers | J29: =SUM(C29:I29) -> 0
A30: Disaster Recovery & Business Continuity | B30: I-000315 | D30: 3 | J30: =SUM(C30:I30) -> 3
A31: Employee Digital Records | B31: I-000316 | D31: 42.83 | H31: 18.75 | J31: =SUM(C31:I31) -> 61.58
A32: Employee Verification (with WISDOM) | B32: I-000274 | J32: =SUM(C32:I32) -> 0
A33: Franchises Customer App | C33: 3.5 | D33: 15.5 | F33: 2.25 | H33: 0.5 | J33: =SUM(C33:I33) -> 21.75
A34: Franchises myJDW | J34: =SUM(C34:I34) -> 0
A35: Franchises mySchedule | J35: =SUM(C35:I35) -> 0
A36: Franchises WordPress Websites
A37: Hotels HLS Integration | J37: =SUM(C37:I37) -> 0
A38: Hotels Price Comparison | B38: I-000317 | J38: =SUM(C38:I38) -> 0
A39: Intelligence PoC | B39: I-000318 | D39: 34 | F39: 13.25 | H39: 43 | J39: =SUM(C39:I39) -> 90.25
A40: Microsoft Office Replacement | J40: =SUM(C40:I40) -> 0
A41: myETL
A42: myPub | B42: I-000319 | D42: 32.75 | F42: 60.49 | J42: =SUM(C42:I42) -> 93.24
A43: myDiscounts App | B43: I-000320 | F43: 0.5 | J43: =SUM(C43:I43) -> 0.5
A44: myJDW | B44: I-000239 | C44: 602.95 | D44: 184.68 | E44: 128.5 | F44: 59 | H44: 17.5 | J44: =SUM(C44:I44) -> 992.63
A45: mySchedule | B45: I-000271 | C45: 208.95 | D45: 118.06 | F45: 100.18 | G45: 8.5 | H45: 6.5 | I45: 6.57 | J45: =SUM(C45:I45) -> 448.76
A46: People Planning
A47: PCI DSS Compliance | J47: =SUM(C47:I47) -> 0
A48: QR Code Admin Replatform | J48: =SUM(C48:I48) -> 0
A49: Research Project: Possibilities & Benefits of AI | J49: =SUM(C49:I49) -> 0
A50: Out of Stock Screen Scraping | B50: I-000329 | D50: 5.75 | F50: 22.92 | J50: =SUM(C50:I50) -> 28.67
A51: Pub Ordering & Receipting Planning | B51: I-000330 | D51: 3.5 | J51: =SUM(C51:I51) -> 3.5
A52: ResourceLink HCM / Absence Management | B52: I-000321 | D52: 26.25 | F52: 2.25 | J52: =SUM(C52:I52) -> 28.5
A53: Suggested Rotas | B53: I-000322 | C53: 118.18 | D53: 28.5 | F53: 2.92 | H53: 40 | I53: 0.5 | J53: =SUM(C53:I53) -> 190.1
A54: Security Response Payment Service | B54: I-000323 | J54: =SUM(C54:I54) -> 0
A55: Technical Planning
A56: WordPress Websites | B56: Various | C56: 54.91 | D56: 60.74 | F56: 18.75 | J56: =SUM(C56:I56) -> 134.4
C57: =SUM(C17:C56) -> 2052.96 | D57: =SUM(D17:D56) -> 995.95 | E57: =SUM(E17:E56) -> 359.76 | F57: =SUM(F17:F56) -> 498.51 | G57: =SUM(G17:G56) -> 116.34 | H57: =SUM(H17:H56) -> 158.75 | I57: =SUM(I17:I56) -> 8.32 | J57: =SUM(C57:I57) -> 4190.59
A60: Support and Maintenance | B60: 24974
A62: Support and Maintenance Hours | B62: Project Code | C62: Customer Support | D62: Project Management, Meetings & Reporting | E62: Maintenance | F62: Systems Admin | G62: Total
A63: Allergens | G63: =SUM(C63:F63) -> 0
A64: Customer Information Screens | C64: 0.5 | E64: 1.75 | G64: =SUM(C64:F64) -> 2.25
A65: Customer App / PWA / App Manager | C65: 127.57 | E65: 41.75 | G65: =SUM(C65:F65) -> 169.32
A66: myAuth | G66: =SUM(C66:F66) -> 0
A67: myJDW | C67: 15.2 | E67: 0.5 | G67: =SUM(C67:F67) -> 15.7
A68: mySchedule | C68: 3.17 | E68: 3 | G68: =SUM(C68:F68) -> 6.17
A69: Sitecore Corporate Website | G69: =SUM(C69:F69) -> 0
A70: Support for Franchises | G70: =SUM(C70:F70) -> 0
A71: WordPress Websites | C71: 4 | E71: 1.75 | G71: =SUM(C71:F71) -> 5.75
C72: =SUM(C64:C71) -> 150.44 | D72: =SUM(D64:D71) -> 0 | E72: =SUM(E64:E71) -> 48.75 | F72: =SUM(F63:F71) -> 0 | G72: =SUM(C72:F72) -> 199.19
A75: Third Party Services | B75: Variable
A77: Company | B77: Website / Application | D77: Contracted To | E77: Frequency | F77: Per Annum Charge | G77: Per Month Charge | H77: Service Notes
A79: AWS | B79: myJDW, mySchedule, Authentication | D79: JDW | E79: Monthly | H79: Charged directly to JDW. Figures are converted from dollars at 0.82 pound sterling.
A80: AWS | B80: Customer App | D80: JDW | E80: Monthly | H80: Charged directly to JDW. Figures are converted from dollars at 0.82 pound sterling.
A81: AWS | B81: Auth0 Wisdom & Customer Accounts PoC | D81: JDW | E81: Monthly | H81: Charged directly to JDW. Figures are converted from dollars at 0.82 pound sterling.
A82: AWS | B82: Corporate Website Sitecore | D82: JDW | E82: NA | H82: Charged directly to JDW. Figures are converted from dollars at 0.82 pound sterling.
A83: AWS | B83: Rota Automation & ChatBot AWS Costs | D83: JDW | E83: Monthly
A84: Sendbird | B84: myJDW | D84: JDW | E84: Monthly | H84: Charged directly to JDW. Filter don't have sight of this fee.
A86: Elastic Search | B86: myJDW & mySchedule | D86: Filter | E86: Monthly | G86: 53.81 | H86: Fluctuates depending on usage, charged each month. No real increase for mySchedule as there is limited content to search. Not possible to split by service.
A87: Open Weather | B87: mySchedule | D87: Filter | E87: Monthly | H87: Fluctuates depending on usage, charged each month., currently not hitting limits to be charged.
A88: Ionic Enterprise Package | B88: Customer App | D88: Filter | E88: Annual | H88: Enterprise package with live updates.
A89: Ionic Payments | B89: Customer App | D89: Filter | E89: Annual | H89: Annual requirement from Feb 24.
A90: Apple Developer Enterprise Program - One year | B90: myJDW | D90: JDW | E90: Annual | H90: Recharegd by Filter. Traditionally we haven't marked this cost up.
A91: Google Maps API | B91: Customer App, Corporate & Hotels Websites | D91: Filter | E91: Monthly | G91: 14794.48 | H91: Fluctuates depending on usage.
A92: WordPress Plugins Annual Budget | D92: Filter | E92: Annual | H92: In use across WordPress websites. Included Corporate website once live. Plugins include: Gravity Forms Elite, Search Pro, PersonalizeWP Pro, WPRocket, Imagify, Media Library Organiser Pro, Advanced Custom Fields, Advanced Post Type Order, Yoast Duplicate Post, Admin Columns Pro, WP Migrate Premier, Wordfence, WP Activity Log. Potentially need to look at this as more of a package moving forwards across all sites.
A93: WPEngine Website Hosting | B93: Careers | D93: JDW | E93: Monthly | H93: This fee will become obsolete from August, with move to dedicated WPEngine hosting charged directly to JDW.
A94: WPEngine Website Hosting | B94: Investors | D94: JDW | E94: Monthly | H94: This fee will become obsolete from August, with move to dedicated WPEngine hosting charged directly to JDW.
A95: WPEngine Website Hosting | B95: Hotel | D95: JDW | E95: Monthly | H95: This fees will become obsolete if moving to a WP Engine Premier Hosting Solution, see Corporate Website.
A96: WPEngine Website Hosting | B96: Corporate | D96: JDW | E96: Monthly | H96: The re-platforming will involve the set-up of a multi-site solution to pull together all the microsites into a single platform. WP Engine have proposed two options for this, please see WP Engine / JDW - proposal for the details. We can discuss this further, alongside the decision as to whether Filter will contract on behalf of JDW (at 15% admin fee) or you choose to contract directly with WP Engine. Included is single node fee.
A97: Website Cookie Yes | B97: Corporate | D97: Filter | E97: Annual | H97: Outside of standard plugin package.
A98: Website Cookie Yes | B98: Hotel | D98: Filter | E98: Annual | H98: Outside of standard plugin package.
A99: Website Yoast SEO Premium | B99: Hotel | D99: Filter | E99: Annual | H99: Outside of standard plugin package.
A100: Statamic | D100: Filter | E100: Annual | H100: Reduces after one year to c.£60 per year.
F101: =SUM(F78:F100) -> 0 | G101: =SUM(G79:G100) -> 14848.29

Sheet Oct 24
A1: Month: | B1: 45566
A3: Dedicated Team Billing: | B3: =B9+B60 -> 340813
A4: Fixed Team Target Hours: | B4: =SUM(32*8.5)*23 -> 6256 | C4: 32 FTE
A5: Fixed Team Recorded Hours: | B5: 6352.97
A6: Difference: | B6: =B5-B4 -> 96.97
A9: Planning, Development & Delivery | B9: 315839
C10: R&P | D10: R&P | E10: R&P | F10: R&P | G10: R&P | H10: R&P | I10: TMC | J10: R&P | K10: TMC | L10: TMC | M10: TMC | N10: TMC | O10: TMC | P10: TMC | Q10: TMC | R10: TMC | S10: TMC
A11: Programme Management Hours | B11: Project Code | C11: Planning | D11: Project Management, Meetings & Reporting | E11: Design | F11: Admin | G11: Systems Admin | H11: Research | I11: Training | J11: Finance | K11: HR | L11: Recruitment | M11: Travel | N11: Break | O11: Lunch | P11: Holiday | Q11: Bank Holiday | R11: Sick | S11: Other Absence | T11: Total
C13: 66.25 | D13: 386.99 | F13: 26.25 | G13: 112.92 | H13: 21.25 | I13: 4.5 | J13: 0.5 | K13: 27.42 | L13: 13.33 | M13: 18.5 | N13: 36 | O13: 455.5 | P13: 458.75 | R13: 46.25 | S13: 5.5 | T13: =SUM(C13:S13) -> 1679.91
A16: Projects Hours | B16: Project Code | C16: Development | D16: Project Management, Meetings & Reporting | E16: Testing | F16: Planning | G16: Systems Admin | H16: Design | I16: Release | J16: Total
A17: Allergens Service | B17: I-000300 | J17: =SUM(C17:I17) -> 0
A18: Authentication | B18: I-000312 | C18: 197.81 | D18: 31.6 | F18: 62.99 | G18: 19.5 | H18: 2.75 | J18: =SUM(C18:I18) -> 314.65
A19: Available Ales on TV Screens | J19: =SUM(C19:I19) -> 0
A20: Customer Information Screens | B20: I-000313 | D20: 2.5 | J20: =SUM(C20:I20) -> 2.5
A21: Corporate Website Replatform Build | B21: I-000300 | C21: 1.75 | F21: 0.25 | G21: 0.25 | J21: =SUM(C21:I21) -> 2.25
A22: Customer Accounts Planning | B22: I-000311 | C22: 28 | D22: 13 | F22: 55.25 | H22: 4.5 | J22: =SUM(C22:I22) -> 100.75
A23: Customer App - Ibersol Franchise Integration
A24: Customer App - Lagardere Franchise Integration
A25: Customer App / PWA / App Manager | B25: I-000287 | C25: 879.41 | D25: 365.26 | E25: 219.51 | F25: 101.34 | G25: 103.86 | H25: 62 | I25: 8.58 | J25: =SUM(C25:I25) -> 1739.96
A26: Customer App UX/UI Redesign | J26: =SUM(C26:I26) -> 0
A27: Customer Planning
A28: Digital Pub Records | B28: I-000314 | D28: 21.22 | F28: 28.5 | J28: =SUM(C28:I28) -> 49.72
A29: Digital Vouchers | J29: =SUM(C29:I29) -> 0
A30: Disaster Recovery & Business Continuity | B30: I-000315 | D30: 14.5 | F30: 0.5 | G30: 6 | J30: =SUM(C30:I30) -> 21
A31: Employee Digital Records | B31: I-000316 | D31: 29.28 | F31: 10.75 | H31: 34.25 | J31: =SUM(C31:I31) -> 74.28
A32: Employee Verification (with WISDOM) | B32: I-000274 | J32: =SUM(C32:I32) -> 0
A33: Franchises Customer App | C33: 8.5 | D33: 11.5 | G33: 3.25 | H33: 1.92 | J33: =SUM(C33:I33) -> 25.17
A34: Franchises myJDW | D34: 0.5 | F34: 1 | J34: =SUM(C34:I34) -> 1.5
A35: Franchises mySchedule | F35: 1 | J35: =SUM(C35:I35) -> 1
A36: Franchises WordPress Websites
A37: Hotels HLS Integration | J37: =SUM(C37:I37) -> 0
A38: Hotels Price Comparison | B38: I-000317 | J38: =SUM(C38:I38) -> 0
A39: Intelligence PoC | B39: I-000318 | C39: 84.84 | D39: 81.86 | F39: 5.75 | H39: 42.25 | J39: =SUM(C39:I39) -> 214.7
A40: Microsoft Office Replacement | J40: =SUM(C40:I40) -> 0
A41: myETL
A42: myPub | B42: I-000319 | D42: 21.84 | F42: 19.17 | J42: =SUM(C42:I42) -> 41.01
A43: myDiscounts App | B43: I-000320 | J43: =SUM(C43:I43) -> 0
A44: myJDW | B44: I-000239 | C44: 644.27 | D44: 145.84 | E44: 124.75 | F44: 29.08 | H44: 6.25 | J44: =SUM(C44:I44) -> 950.19
A45: mySchedule | B45: I-000271 | C45: 237.58 | D45: 156.13 | F45: 87.85 | G45: 4.25 | H45: 118.75 | I45: 8.51 | J45: =SUM(C45:I45) -> 613.07
A46: People Planning
A47: PCI DSS Compliance | J47: =SUM(C47:I47) -> 0
A48: QR Code Admin Replatform | J48: =SUM(C48:I48) -> 0
A49: Research Project: Possibilities & Benefits of AI | J49: =SUM(C49:I49) -> 0
A50: Out of Stock Screen Scraping | B50: I-000329 | D50: 1.75 | F50: 5.5 | J50: =SUM(C50:I50) -> 7.25
A51: Pub Ordering & Receipting Planning | B51: I-000330 | D51: 25.33 | F51: 71.09 | J51: =SUM(C51:I51) -> 96.42
A52: ResourceLink HCM / Absence Management | B52: I-000321 | D52: 2.75 | J52: =SUM(C52:I52) -> 2.75
A53: Suggested Rotas | B53: I-000322 | C53: 22.75 | D53: 52 | F53: 13.75 | H53: 11 | J53: =SUM(C53:I53) -> 99.5
A54: Security Response Payment Service | B54: I-000323 | J54: =SUM(C54:I54) -> 0
A55: Technical Planning
A56: WordPress Websites | B56: Various | C56: 183.71 | D56: 34.51 | E56: 6 | F56: 31.75 | I56: 0.75 | J56: =SUM(C56:I56) -> 256.72
C57: =SUM(C17:C56) -> 2288.62 | D57: =SUM(D17:D56) -> 1011.37 | E57: =SUM(E17:E56) -> 350.26 | F57: =SUM(F17:F56) -> 525.52 | G57: =SUM(G17:G56) -> 137.11 | H57: =SUM(H17:H56) -> 283.67 | I57: =SUM(I17:I56) -> 17.84 | J57: =SUM(C57:I57) -> 4614.39
A60: Support and Maintenance | B60: 24974
A62: Support and Maintenance Hours | B62: Project Code | C62: Customer Support | D62: Project Management, Meetings & Reporting | E62: Maintenance | F62: Systems Admin | G62: Total
A63: Allergens | G63: =SUM(C63:F63) -> 0
A64: Customer Information Screens | C64: 1.75 | E64: 1 | G64: =SUM(C64:F64) -> 2.75
A65: Customer App / PWA / App Manager | C65: 17.87 | E65: 6.08 | G65: =SUM(C65:F65) -> 23.95
A66: myAuth | G66: =SUM(C66:F66) -> 0
A67: myJDW | C67: 6.25 | E67: 0.5 | G67: =SUM(C67:F67) -> 6.75
A68: mySchedule | C68: 6.63 | E68: 10.26 | G68: =SUM(C68:F68) -> 16.89
A69: Sitecore Corporate Website | E69: 0.5 | G69: =SUM(C69:F69) -> 0.5
A70: Support for Franchises | G70: =SUM(C70:F70) -> 0
A71: WordPress Websites | C71: 4.33 | E71: 3.5 | G71: =SUM(C71:F71) -> 7.83
C72: =SUM(C64:C71) -> 36.83 | D72: =SUM(D64:D71) -> 0 | E72: =SUM(E64:E71) -> 21.84 | F72: =SUM(F63:F71) -> 0 | G72: =SUM(C72:F72) -> 58.67
A75: Third Party Services | B75: Variable
A77: Company | B77: Website / Application | D77: Contracted To | E77: Frequency | F77: Per Annum Charge | G77: Per Month Charge | H77: Service Notes
A79: AWS | B79: myJDW, mySchedule, Authentication | D79: JDW | E79: Monthly | H79: Charged directly to JDW. Figures are converted from dollars at 0.82 pound sterling.
A80: AWS | B80: Customer App | D80: JDW | E80: Monthly | H80: Charged directly to JDW. Figures are converted from dollars at 0.82 pound sterling.
A81: AWS | B81: Auth0 Wisdom & Customer Accounts PoC | D81: JDW | E81: Monthly | H81: Charged directly to JDW. Figures are converted from dollars at 0.82 pound sterling.
A82: AWS | B82: Corporate Website Sitecore | D82: JDW | E82: NA | H82: Charged directly to JDW. Figures are converted from dollars at 0.82 pound sterling.
A83: AWS | B83: Rota Automation & ChatBot AWS Costs | D83: JDW | E83: Monthly
A84: Sendbird | B84: myJDW | D84: JDW | E84: Monthly | H84: Charged directly to JDW. Filter don't have sight of this fee.
A86: Elastic Search | B86: myJDW & mySchedule | D86: Filter | E86: Monthly | G86: 56.68 | H86: Fluctuates depending on usage, charged each month. No real increase for mySchedule as there is limited content to search. Not possible to split by service.
A87: Open Weather | B87: mySchedule | D87: Filter | E87: Monthly | H87: Fluctuates depending on usage, charged each month., currently not hitting limits to be charged.
A88: Ionic Enterprise Package | B88: Customer App | D88: Filter | E88: Annual | H88: Enterprise package with live updates.
A89: Ionic Payments | B89: Customer App | D89: Filter | E89: Annual | H89: Annual requirement from Feb 24.
A90: Apple Developer Enterprise Program - One year | B90: myJDW | D90: JDW | E90: Annual | H90: Recharegd by Filter. Traditionally we haven't marked this cost up.
A91: Google Maps API | B91: Customer App, Corporate & Hotels Websites | D91: Filter | E91: Monthly | G91: 18054.06 | H91: Fluctuates depending on usage.
A92: WordPress Plugins Annual Budget | D92: Filter | E92: Annual | H92: In use across WordPress websites. Included Corporate website once live. Plugins include: Gravity Forms Elite, Search Pro, PersonalizeWP Pro, WPRocket, Imagify, Media Library Organiser Pro, Advanced Custom Fields, Advanced Post Type Order, Yoast Duplicate Post, Admin Columns Pro, WP Migrate Premier, Wordfence, WP Activity Log. Potentially need to look at this as more of a package moving forwards across all sites.
A93: WPEngine Website Hosting | B93: Careers | D93: JDW | E93: Monthly | H93: This fee will become obsolete from August, with move to dedicated WPEngine hosting charged directly to JDW.
A94: WPEngine Website Hosting | B94: Investors | D94: JDW | E94: Monthly | H94: This fee will become obsolete from August, with move to dedicated WPEngine hosting charged directly to JDW.
A95: WPEngine Website Hosting | B95: Hotel | D95: JDW | E95: Monthly | H95: This fees will become obsolete if moving to a WP Engine Premier Hosting Solution, see Corporate Website.
A96: WPEngine Website Hosting | B96: Corporate | D96: JDW | E96: Monthly | H96: The re-platforming will involve the set-up of a multi-site solution to pull together all the microsites into a single platform. WP Engine have proposed two options for this, please see WP Engine / JDW - proposal for the details. We can discuss this further, alongside the decision as to whether Filter will contract on behalf of JDW (at 15% admin fee) or you choose to contract directly with WP Engine. Included is single node fee.
A97: Website Cookie Yes | B97: Corporate | D97: Filter | E97: Annual | G97: 398.97 | H97: Outside of standard plugin package.
A98: Website Cookie Yes | B98: Hotel | D98: Filter | E98: Annual | G98: 396.13 | H98: Outside of standard plugin package.
A99: Website Yoast SEO Premium | B99: Hotel | D99: Filter | E99: Annual | H99: Outside of standard plugin package.
A100: Statamic | D100: Filter | E100: Annual | H100: Reduces after one year to c.£60 per year.
F101: =SUM(F78:F100) -> 0 | G101: =SUM(G79:G100) -> 18905.84

Sheet Nov 24
A1: Month: | B1: 45597
A3: Dedicated Team Billing: | B3: =B9+B60 -> 340813
A4: Fixed Team Target Hours: | B4: =SUM(32*8.5)*21 -> 5712 | C4: 32 FTE
A5: Fixed Team Recorded Hours: | B5: 5957.62
A6: Difference: | B6: =B5-B4 -> 245.62
A9: Planning, Development & Delivery | B9: 315839
C10: R&P | D10: R&P | E10: R&P | F10: R&P | G10: R&P | H10: R&P | I10: TMC | J10: R&P | K10: TMC | L10: TMC | M10: TMC | N10: TMC | O10: TMC | P10: TMC | Q10: TMC | R10: TMC | S10: TMC
A11: Programme Management Hours | B11: Project Code | C11: Planning | D11: Project Management, Meetings & Reporting | E11: Design | F11: Admin | G11: Systems Admin | H11: Research | I11: Training | J11: Finance | K11: HR | L11: Recruitment | M11: Travel | N11: Break | O11: Lunch | P11: Holiday | Q11: Bank Holiday | R11: Sick | S11: Other Absence | T11: Total
C13: 122.17 | D13: 363.35 | F13: 24.25 | G13: 132.43 | H13: 12 | I13: 19.25 | J13: 4.75 | K13: 27.75 | L13: 10.5 | M13: 11 | N13: 31.33 | O13: 416.62 | P13: 432.75 | R13: 72.57 | S13: 17 | T13: =SUM(C13:S13) -> 1697.72
A16: Projects Hours | B16: Project Code | C16: Development | D16: Project Management, Meetings & Reporting | E16: Testing | F16: Planning | G16: Systems Admin | H16: Design | I16: Release | J16: Total
A17: Allergens Service | B17: I-000300 | J17: =SUM(C17:I17) -> 0
A18: Authentication | B18: I-000312 | C18: 192.69 | D18: 41.51 | E18: 115.3 | F18: 98.59 | G18: 21.53 | H18: 8 | I18: 0.58 | J18: =SUM(C18:I18) -> 478.2
A19: Available Ales on TV Screens | J19: =SUM(C19:I19) -> 0
A20: Customer Information Screens | B20: I-000313 | J20: =SUM(C20:I20) -> 0
A21: Corporate Website Replatform Build | B21: I-000300 | H21: 0.75 | J21: =SUM(C21:I21) -> 0.75
A22: Customer Accounts Planning | B22: I-000311 | C22: 124.17 | D22: 6.42 | F22: 24.75 | G22: 4.25 | H22: 0.5 | J22: =SUM(C22:I22) -> 160.09
A23: Customer App - Ibersol Franchise Integration
A24: Customer App - Lagardere Franchise Integration
A25: Customer App / PWA / App Manager | B25: I-000287 | C25: 455.45 | D25: 320.45 | E25: 364.13 | F25: 89.25 | G25: 55.67 | H25: 39.75 | I25: 7.92 | J25: =SUM(C25:I25) -> 1332.62
A26: Customer App UX/UI Redesign | J26: =SUM(C26:I26) -> 0
A27: Customer Planning
A28: Digital Pub Records | B28: I-000314 | D28: 46.42 | F28: 47.5 | H28: 9.75 | J28: =SUM(C28:I28) -> 103.67
A29: Digital Vouchers | J29: =SUM(C29:I29) -> 0
A30: Disaster Recovery & Business Continuity | B30: I-000315 | D30: 4.25 | F30: 5 | J30: =SUM(C30:I30) -> 9.25
A31: Employee Digital Records | B31: I-000316 | D31: 20.4 | F31: 8 | H31: 46.25 | J31: =SUM(C31:I31) -> 74.65
A32: Employee Verification (with WISDOM) | B32: I-000274 | J32: =SUM(C32:I32) -> 0
A33: Franchises Customer App | C33: 279.25 | D33: 41.75 | F33: 7 | G33: 13.75 | H33: 14.67 | J33: =SUM(C33:I33) -> 356.42
A34: Franchises myJDW | J34: =SUM(C34:I34) -> 0
A35: Franchises mySchedule | J35: =SUM(C35:I35) -> 0
A36: Franchises WordPress Websites
A37: Hotels HLS Integration | J37: =SUM(C37:I37) -> 0
A38: Hotels Price Comparison | B38: I-000317 | J38: =SUM(C38:I38) -> 0
A39: Intelligence PoC | B39: I-000318 | C39: 119.67 | D39: 55.92 | F39: 2 | H39: 15.75 | J39: =SUM(C39:I39) -> 193.34
A40: Microsoft Office Replacement | J40: =SUM(C40:I40) -> 0
A41: myETL
A42: myPub | B42: I-000319 | D42: 7.58 | F42: 4.5 | J42: =SUM(C42:I42) -> 12.08
A43: myDiscounts App | B43: I-000320 | J43: =SUM(C43:I43) -> 0
A44: myJDW | B44: I-000239 | C44: 394.19 | D44: 166.33 | E44: 48.25 | F44: 26.75 | H44: 33 | I44: 57.42 | J44: =SUM(C44:I44) -> 725.94
A45: mySchedule | B45: I-000271 | C45: 346.47 | D45: 108.77 | F45: 82.68 | G45: 0.25 | J45: =SUM(C45:I45) -> 538.17
A46: People Planning
A47: PCI DSS Compliance | J47: =SUM(C47:I47) -> 0
A48: QR Code Admin Replatform | J48: =SUM(C48:I48) -> 0
A49: Research Project: Possibilities & Benefits of AI | J49: =SUM(C49:I49) -> 0
A50: Out of Stock Screen Scraping | B50: I-000329 | J50: =SUM(C50:I50) -> 0
A51: Pub Ordering & Receipting Planning | B51: I-000330 | D51: 5.5 | F51: 10.92 | J51: =SUM(C51:I51) -> 16.42
A52: ResourceLink HCM / Absence Management | B52: I-000321 | D52: 3.5 | J52: =SUM(C52:I52) -> 3.5
A53: Suggested Rotas | B53: I-000322 | D53: 15.25 | F53: 2 | H53: 0.5 | J53: =SUM(C53:I53) -> 17.75
A54: Security Response Payment Service | B54: I-000323 | J54: =SUM(C54:I54) -> 0
A55: Technical Planning
A56: WordPress Websites | B56: Various | C56: 3.74 | D56: 17.33 | F56: 14.75 | J56: =SUM(C56:I56) -> 35.82
C57: =SUM(C17:C56) -> 1915.63 | D57: =SUM(D17:D56) -> 861.38 | E57: =SUM(E17:E56) -> 527.68 | F57: =SUM(F17:F56) -> 423.69 | G57: =SUM(G17:G56) -> 95.45 | H57: =SUM(H17:H56) -> 168.92 | I57: =SUM(I17:I56) -> 65.92 | J57: =SUM(C57:I57) -> 4058.67
A60: Support and Maintenance | B60: 24974
A62: Support and Maintenance Hours | B62: Project Code | C62: Customer Support | D62: Project Management, Meetings & Reporting | E62: Maintenance | F62: Systems Admin | G62: Total
A63: Allergens | G63: =SUM(C63:F63) -> 0
A64: Customer Information Screens | E64: 0.25 | G64: =SUM(C64:F64) -> 0.25
A65: Customer App / PWA / App Manager | C65: 134.08 | E65: 23.35 | G65: =SUM(C65:F65) -> 157.43
A66: myAuth | G66: =SUM(C66:F66) -> 0
A67: myJDW | C67: 9.75 | E67: 13.9 | G67: =SUM(C67:F67) -> 23.65
A68: mySchedule | C68: 4.75 | E68: 10.4 | G68: =SUM(C68:F68) -> 15.15
A69: Sitecore Corporate Website | C69: 0.25 | E69: 1 | G69: =SUM(C69:F69) -> 1.25
A70: Support for Franchises | G70: =SUM(C70:F70) -> 0
A71: WordPress Websites | C71: 1.75 | E71: 1.75 | G71: =SUM(C71:F71) -> 3.5
C72: =SUM(C64:C71) -> 150.58 | D72: =SUM(D64:D71) -> 0 | E72: =SUM(E64:E71) -> 50.65 | F72: =SUM(F63:F71) -> 0 | G72: =SUM(C72:F72) -> 201.23
A75: Third Party Services | B75: Variable
A77: Company | B77: Website / Application | D77: Contracted To | E77: Frequency | F77: Per Annum Charge | G77: Per Month Charge | H77: Service Notes
A79: AWS | B79: myJDW, mySchedule, Authentication | D79: JDW | E79: Monthly | H79: Charged directly to JDW. Figures are converted from dollars at 0.82 pound sterling.
A80: AWS | B80: Customer App | D80: JDW | E80: Monthly | H80: Charged directly to JDW. Figures are converted from dollars at 0.82 pound sterling.
A81: AWS | B81: Auth0 Wisdom & Customer Accounts PoC | D81: JDW | E81: Monthly | H81: Charged directly to JDW. Figures are converted from dollars at 0.82 pound sterling.
A82: AWS | B82: Corporate Website Sitecore | D82: JDW | E82: NA | H82: Charged directly to JDW. Figures are converted from dollars at 0.82 pound sterling.
A83: AWS | B83: Rota Automation & ChatBot AWS Costs | D83: JDW | E83: Monthly
A84: Sendbird | B84: myJDW | D84: JDW | E84: Monthly | H84: Charged directly to JDW. Filter don't have sight of this fee.
A86: Elastic Search | B86: myJDW & mySchedule | D86: Filter | E86: Monthly | G86: 50.88 | H86: Fluctuates depending on usage, charged each month. No real increase for mySchedule as there is limited content to search. Not possible to split by service.
A87: Open Weather | B87: mySchedule | D87: Filter | E87: Monthly | H87: Fluctuates depending on usage, charged each month., currently not hitting limits to be charged.
A88: Ionic Enterprise Package | B88: Customer App | D88: Filter | E88: Annual | H88: Enterprise package with live updates.
A89: Ionic Payments | B89: Customer App | D89: Filter | E89: Annual | H89: Annual requirement from Feb 24.
A90: Apple Developer Enterprise Program - One year | B90: myJDW | D90: JDW | E90: Annual | H90: Recharegd by Filter. Traditionally we haven't marked this cost up.
A91: Google Maps API | B91: Customer App, Corporate & Hotels Websites | D91: Filter | E91: Monthly | G91: 16154.4 | H91: Fluctuates depending on usage.
A92: WordPress Plugins Annual Budget | D92: Filter | E92: Annual | H92: In use across WordPress websites. Included Corporate website once live. Plugins include: Gravity Forms Elite, Search Pro, PersonalizeWP Pro, WPRocket, Imagify, Media Library Organiser Pro, Advanced Custom Fields, Advanced Post Type Order, Yoast Duplicate Post, Admin Columns Pro, WP Migrate Premier, Wordfence, WP Activity Log. Potentially need to look at this as more of a package moving forwards across all sites.
A93: WPEngine Website Hosting | B93: Careers | D93: JDW | E93: Monthly | H93: This fee will become obsolete from August, with move to dedicated WPEngine hosting charged directly to JDW.
A94: WPEngine Website Hosting | B94: Investors | D94: JDW | E94: Monthly | H94: This fee will become obsolete from August, with move to dedicated WPEngine hosting charged directly to JDW.
A95: WPEngine Website Hosting | B95: Hotel | D95: JDW | E95: Monthly | H95: This fees will become obsolete if moving to a WP Engine Premier Hosting Solution, see Corporate Website.
A96: WPEngine Website Hosting | B96: Corporate | D96: JDW | E96: Monthly | H96: The re-platforming will involve the set-up of a multi-site solution to pull together all the microsites into a single platform. WP Engine have proposed two options for this, please see WP Engine / JDW - proposal for the details. We can discuss this further, alongside the decision as to whether Filter will contract on behalf of JDW (at 15% admin fee) or you choose to contract directly with WP Engine. Included is single node fee.
A97: Website Cookie Yes | B97: Corporate | D97: Filter | E97: Annual | H97: Outside of standard plugin package.
A98: Website Cookie Yes | B98: Hotel | D98: Filter | E98: Annual | H98: Outside of standard plugin package.
A99: Website Yoast SEO Premium | B99: Hotel | D99: Filter | E99: Annual | H99: Outside of standard plugin package.
A100: Statamic | D100: Filter | E100: Annual | H100: Reduces after one year to c.£60 per year.
A101: AWS Partnership Select Tier Recharge | F101: 986 | H101: 50% invoiced to JDW at cost
F102: =SUM(F78:F101) -> 986 | G102: =SUM(G79:G101) -> 16205.28

Sheet Dec 24
A1: Month: | B1: 45627
A3: Dedicated Team Billing: | B3: =B9+B60 -> 340813
A4: Fixed Team Target Hours: | B4: =SUM(32*8.5)*22 -> 5984 | C4: 32 FTE
A5: Fixed Team Recorded Hours: | B5: 6201.07
A6: Difference: | B6: =B5-B4 -> 217.07
A9: Planning, Development & Delivery | B9: 315839
C10: R&P | D10: R&P | E10: R&P | F10: R&P | G10: R&P | H10: R&P | I10: TMC | J10: R&P | K10: TMC | L10: TMC | M10: TMC | N10: TMC | O10: TMC | P10: TMC | Q10: TMC | R10: TMC | S10: TMC
A11: Programme Management Hours | B11: Project Code | C11: Planning | D11: Project Management, Meetings & Reporting | E11: Design | F11: Admin | G11: Systems Admin | H11: Research | I11: Training | J11: Finance | K11: HR | L11: Recruitment | M11: Travel | N11: Break | O11: Lunch | P11: Holiday | Q11: Bank Holiday | R11: Sick | S11: Other Absence | T11: Total
C13: 50.53 | D13: 341.53 | F13: 36.25 | G13: 95.83 | H13: 3.67 | I13: 55.08 | J13: 0.75 | K13: 15.5 | L13: 0.25 | M13: 8.25 | N13: 18.83 | O13: 356.17 | P13: 1634.74 | Q13: 534.16 | R13: 3.75 | T13: =SUM(C13:S13) -> 3155.29
A16: Projects Hours | B16: Project Code | C16: Development | D16: Project Management, Meetings & Reporting | E16: Testing | F16: Planning | G16: Systems Admin | H16: Design | I16: Release | J16: Total
A17: Allergens Service | B17: I-000300 | J17: =SUM(C17:I17) -> 0
A18: Authentication | B18: I-000312 | C18: 49.95 | D18: 24.2 | E18: 25.75 | F18: 95.43 | G18: 9.24 | H18: 1.25 | I18: 1.93 | J18: =SUM(C18:I18) -> 207.75
A19: Available Ales on TV Screens | J19: =SUM(C19:I19) -> 0
A20: Customer Information Screens | B20: I-000313 | J20: =SUM(C20:I20) -> 0
A21: Corporate Website Replatform Build | B21: I-000300 | J21: =SUM(C21:I21) -> 0
A22: Customer Accounts Planning | B22: I-000311 | C22: 125.43 | D22: 18.5 | F22: 31.75 | H22: 1.25 | J22: =SUM(C22:I22) -> 176.93
A23: Customer App - Ibersol Franchise Integration
A24: Customer App - Lagardere Franchise Integration
A25: Customer App / PWA / App Manager | B25: I-000287 | C25: 175.93 | D25: 256.08 | E25: 99.5 | F25: 117.25 | G25: 25.67 | H25: 5 | I25: 3 | J25: =SUM(C25:I25) -> 682.43
A26: Customer App UX/UI Redesign | J26: =SUM(C26:I26) -> 0
A27: Customer Planning
A28: Digital Pub Records | B28: I-000314 | C28: 129.5 | D28: 80.92 | F28: 42.75 | H28: 27.75 | J28: =SUM(C28:I28) -> 280.92
A29: Digital Vouchers | J29: =SUM(C29:I29) -> 0
A30: Disaster Recovery & Business Continuity | B30: I-000315 | D30: 1.75 | J30: =SUM(C30:I30) -> 1.75
A31: Employee Digital Records | B31: I-000316 | D31: 7.25 | H31: 8.25 | J31: =SUM(C31:I31) -> 15.5
A32: Employee Verification (with WISDOM) | B32: I-000274 | J32: =SUM(C32:I32) -> 0
A33: Franchises Customer App | C33: 185.5 | D33: 37.75 | F33: 1 | G33: 27.67 | H33: 6.17 | J33: =SUM(C33:I33) -> 258.09
A34: Franchises myJDW | J34: =SUM(C34:I34) -> 0
A35: Franchises mySchedule | D35: 1 | J35: =SUM(C35:I35) -> 1
A36: Franchises WordPress Websites
A37: Hotels HLS Integration | J37: =SUM(C37:I37) -> 0
A38: Hotels Price Comparison | B38: I-000317 | J38: =SUM(C38:I38) -> 0
A39: Intelligence PoC | B39: I-000318 | C39: 100.5 | D39: 50 | F39: 20.75 | H39: 42.08 | J39: =SUM(C39:I39) -> 213.33
A40: Microsoft Office Replacement | F40: 15.5 | J40: =SUM(C40:I40) -> 15.5
A41: myETL
A42: myPub | B42: I-000319 | J42: =SUM(C42:I42) -> 0
A43: myDiscounts App | B43: I-000320 | J43: =SUM(C43:I43) -> 0
A44: myJDW | B44: I-000239 | C44: 272.19 | D44: 118.71 | E44: 183.5 | F44: 34 | H44: 8.75 | J44: =SUM(C44:I44) -> 617.15
A45: mySchedule | B45: I-000271 | C45: 138.86 | D45: 57.87 | F45: 79.18 | H45: 0.58 | J45: =SUM(C45:I45) -> 276.49
A46: People Planning
A47: PCI DSS Compliance | J47: =SUM(C47:I47) -> 0
A48: QR Code Admin Replatform | J48: =SUM(C48:I48) -> 0
A49: Research Project: Possibilities & Benefits of AI | J49: =SUM(C49:I49) -> 0
A50: Out of Stock Screen Scraping | B50: I-000329 | J50: =SUM(C50:I50) -> 0
A51: Pub Ordering & Receipting Planning | B51: I-000330 | J51: =SUM(C51:I51) -> 0
A52: ResourceLink HCM / Absence Management | B52: I-000321 | D52: 24 | F52: 0.5 | H52: 6.5 | J52: =SUM(C52:I52) -> 31
A53: Suggested Rotas | B53: I-000322 | D53: 7.25 | J53: =SUM(C53:I53) -> 7.25
A54: Security Response Payment Service | B54: I-000323 | J54: =SUM(C54:I54) -> 0
A55: Technical Planning
A56: WordPress Websites | B56: Various | C56: 22 | D56: 31.91 | F56: 0.5 | J56: =SUM(C56:I56) -> 54.41
C57: =SUM(C17:C56) -> 1199.86 | D57: =SUM(D17:D56) -> 717.19 | E57: =SUM(E17:E56) -> 308.75 | F57: =SUM(F17:F56) -> 438.61 | G57: =SUM(G17:G56) -> 62.58 | H57: =SUM(H17:H56) -> 107.58 | I57: =SUM(I17:I56) -> 4.93 | J57: =SUM(C57:I57) -> 2839.5
A60: Support and Maintenance | B60: 24974
A62: Support and Maintenance Hours | B62: Project Code | C62: Customer Support | D62: Project Management, Meetings & Reporting | E62: Maintenance | F62: Systems Admin | G62: Total
A63: Allergens | G63: =SUM(C63:F63) -> 0
A64: Customer Information Screens | G64: =SUM(C64:F64) -> 0
A65: Customer App / PWA / App Manager | C65: 118.84 | E65: 27.45 | G65: =SUM(C65:F65) -> 146.29
A66: myAuth | G66: =SUM(C66:F66) -> 0
A67: myJDW | C67: 20.65 | E67: 19.5 | G67: =SUM(C67:F67) -> 40.15
A68: mySchedule | C68: 4.17 | E68: 2.17 | G68: =SUM(C68:F68) -> 6.34
A69: Sitecore Corporate Website | E69: 2.1 | G69: =SUM(C69:F69) -> 2.1
A70: Support for Franchises | G70: =SUM(C70:F70) -> 0
A71: WordPress Websites | C71: 10.15 | E71: 1.25 | G71: =SUM(C71:F71) -> 11.4
C72: =SUM(C64:C71) -> 153.81 | D72: =SUM(D64:D71) -> 0 | E72: =SUM(E64:E71) -> 52.47 | F72: =SUM(F63:F71) -> 0 | G72: =SUM(C72:F72) -> 206.28
A75: Third Party Services | B75: Variable
A77: Company | B77: Website / Application | D77: Contracted To | E77: Frequency | F77: Per Annum Charge | G77: Per Month Charge | H77: Service Notes
A79: AWS | B79: myJDW, mySchedule, Authentication | D79: JDW | E79: Monthly | H79: Charged directly to JDW. Figures are converted from dollars at 0.82 pound sterling.
A80: AWS | B80: Customer App | D80: JDW | E80: Monthly | H80: Charged directly to JDW. Figures are converted from dollars at 0.82 pound sterling.
A81: AWS | B81: Auth0 Wisdom & Customer Accounts PoC | D81: JDW | E81: Monthly | H81: Charged directly to JDW. Figures are converted from dollars at 0.82 pound sterling.
A82: AWS | B82: Corporate Website Sitecore | D82: JDW | E82: NA | H82: Charged directly to JDW. Figures are converted from dollars at 0.82 pound sterling.
A83: AWS | B83: Rota Automation & ChatBot AWS Costs | D83: JDW | E83: Monthly
A84: Sendbird | B84: myJDW | D84: JDW | E84: Monthly | H84: Charged directly to JDW. Filter don't have sight of this fee.
A86: Elastic Search | B86: myJDW & mySchedule | D86: Filter | E86: Monthly | G86: 57.57 | H86: Fluctuates depending on usage, charged each month. No real increase for mySchedule as there is limited content to search. Not possible to split by service.
A87: Open Weather | B87: mySchedule | D87: Filter | E87: Monthly | H87: Fluctuates depending on usage, charged each month., currently not hitting limits to be charged.
A88: Ionic Enterprise Package | B88: Customer App | D88: Filter | E88: Annual | H88: Enterprise package with live updates.
A89: Ionic Payments | B89: Customer App | D89: Filter | E89: Annual | H89: Annual requirement from Feb 24.
A90: Apple Developer Enterprise Program - One year | B90: myJDW | D90: JDW | E90: Annual | H90: Recharegd by Filter. Traditionally we haven't marked this cost up.
A91: Google Maps API | B91: Customer App, Corporate & Hotels Websites | D91: Filter | E91: Monthly | G91: 16772.33 | H91: Fluctuates depending on usage.
A92: WordPress Plugins Annual Budget | D92: Filter | E92: Annual | H92: In use across WordPress websites. Included Corporate website once live. Plugins include: Gravity Forms Elite, Search Pro, PersonalizeWP Pro, WPRocket, Imagify, Media Library Organiser Pro, Advanced Custom Fields, Advanced Post Type Order, Yoast Duplicate Post, Admin Columns Pro, WP Migrate Premier, Wordfence, WP Activity Log. Potentially need to look at this as more of a package moving forwards across all sites.
A93: WPEngine Website Hosting | B93: Careers | D93: JDW | E93: Monthly | H93: This fee will become obsolete from August, with move to dedicated WPEngine hosting charged directly to JDW.
A94: WPEngine Website Hosting | B94: Investors | D94: JDW | E94: Monthly | H94: This fee will become obsolete from August, with move to dedicated WPEngine hosting charged directly to JDW.
A95: WPEngine Website Hosting | B95: Hotel | D95: JDW | E95: Monthly | H95: This fees will become obsolete if moving to a WP Engine Premier Hosting Solution, see Corporate Website.
A96: WPEngine Website Hosting | B96: Corporate | D96: JDW | E96: Monthly | H96: The re-platforming will involve the set-up of a multi-site solution to pull together all the microsites into a single platform. WP Engine have proposed two options for this, please see WP Engine / JDW - proposal for the details. We can discuss this further, alongside the decision as to whether Filter will contract on behalf of JDW (at 15% admin fee) or you choose to contract directly with WP Engine. Included is single node fee.
A97: Website Cookie Yes | B97: Corporate | D97: Filter | E97: Annual | H97: Outside of standard plugin package.
A98: Website Cookie Yes | B98: Hotel | D98: Filter | E98: Annual | H98: Outside of standard plugin package.
A99: Website Yoast SEO Premium | B99: Hotel | D99: Filter | E99: Annual | F99: 302.28 | H99: Outside of standard plugin package.
A100: Statamic | D100: Filter | E100: Annual | H100: Reduces after one year to c.£60 per year.
A101: AWS Partnership Select Tier Recharge | D101: Filter | E101: Annual | H101: 50% invoiced to JDW at cost
F102: =SUM(F78:F101) -> 302.28 | G102: =SUM(G79:G101) -> 16829.9

Sheet Jan 25
A1: Month: | B1: 45658
A3: Dedicated Team Billing: | B3: =B9+B60 -> 340813
A4: Fixed Team Target Hours: | B4: =SUM(32*8.5)*23 -> 6256 | C4: 32 FTE
A5: Fixed Team Recorded Hours: | B5: =SUM(G72,J57,T13) -> 6266.45
A6: Difference: | B6: =B5-B4 -> 10.45
A9: Planning, Development & Delivery | B9: 315839
C10: R&P | D10: R&P | E10: R&P | F10: R&P | G10: R&P | H10: R&P | I10: TMC | J10: R&P | K10: TMC | L10: TMC | M10: TMC | N10: TMC | O10: TMC | P10: TMC | Q10: TMC | R10: TMC
A11: Programme Management Hours | B11: Project Code | C11: Planning | D11: Project Management, Meetings & Reporting | E11: Design | F11: Admin | G11: Systems Admin | H11: Research | I11: Training | J11: Finance | K11: HR | L11: Recruitment | M11: Travel | N11: Break | O11: Lunch | P11: Holiday | Q11: Bank Holiday | R11: Sick | S11: Other Absence | T11: Total
C13: 87.34 | D13: 372.81 | F13: 34.59 | G13: 126.34 | H13: 16.92 | I13: 19.67 | J13: 7 | K13: 21.75 | L13: 3 | M13: 11.25 | N13: 26 | O13: 502.97 | P13: 334.16 | Q13: 263.33 | R13: 50 | S13: 172.25 | T13: =SUM(C13:S13) -> 2049.38
A16: Projects Hours | B16: Project Code | C16: Development | D16: Project Management, Meetings & Reporting | E16: Testing | F16: Planning | G16: Systems Admin | H16: Design | I16: Release | J16: Total
A17: Allergens Service | B17: I-000300 | J17: =SUM(C17:I17) -> 0
A18: Authentication | B18: I-000312 | C18: 131.36 | D18: 19.89 | E18: 144.95 | F18: 108.32 | G18: 12.42 | J18: =SUM(C18:I18) -> 416.94
A19: Available Ales on TV Screens | J19: =SUM(C19:I19) -> 0
A20: Customer Information Screens | B20: I-000313 | J20: =SUM(C20:I20) -> 0
A21: Corporate Website Replatform Build | B21: I-000300 | J21: =SUM(C21:I21) -> 0
A22: Customer Accounts Planning | B22: I-000311 | C22: 137.67 | D22: 9.42 | E22: 65.25 | F22: 16 | H22: 4.5 | I22: 0.5 | J22: =SUM(C22:I22) -> 233.34
A23: Customer App - Ibersol Franchise Integration
A24: Customer App - Lagardere Franchise Integration
A25: Customer App / PWA / App Manager | B25: I-000287 | C25: 152.28 | D25: 339.49 | E25: 141 | F25: 224.92 | G25: 34.69 | H25: 32 | I25: 0.75 | J25: =SUM(C25:I25) -> 925.13
A26: Customer App UX/UI Redesign | J26: =SUM(C26:I26) -> 0
A27: Customer Planning
A28: Digital Pub Records | B28: I-000314 | C28: 208.33 | D28: 77 | F28: 18.5 | H28: 3.25 | J28: =SUM(C28:I28) -> 307.08
A29: Digital Vouchers | J29: =SUM(C29:I29) -> 0
A30: Disaster Recovery & Business Continuity | B30: I-000315 | D30: 14 | F30: 10.25 | J30: =SUM(C30:I30) -> 24.25
A31: Employee Digital Records | B31: I-000316 | D31: 25.67 | F31: 5 | H31: 24 | J31: =SUM(C31:I31) -> 54.67
A32: Employee Verification (with WISDOM) | B32: I-000274 | J32: =SUM(C32:I32) -> 0
A33: Franchises Customer App | B33: I-000331 | C33: 324 | D33: 19 | F33: 2.75 | H33: 54.09 | J33: =SUM(C33:I33) -> 399.84
A34: Franchises myJDW | D34: 1.75 | F34: 0.25 | J34: =SUM(C34:I34) -> 2
A35: Franchises mySchedule | D35: 3.5 | J35: =SUM(C35:I35) -> 3.5
A36: Franchises WordPress Websites
A37: Hotels HLS Integration | B37: I-000335 | D37: 9 | F37: 6.75 | H37: 0.5 | J37: =SUM(C37:I37) -> 16.25
A38: Hotels Price Comparison | B38: I-000317 | J38: =SUM(C38:I38) -> 0
A39: Intelligence PoC | B39: I-000318 | C39: 251 | D39: 44.25 | F39: 2 | H39: 30.33 | J39: =SUM(C39:I39) -> 327.58
A40: Microsoft Office Replacement | B40: I-000332 | D40: 16 | F40: 4.5 | H40: 46.58 | J40: =SUM(C40:I40) -> 67.08
A41: myETL
A42: myPub | B42: I-000319 | J42: =SUM(C42:I42) -> 0
A43: myDiscounts App | B43: I-000320 | J43: =SUM(C43:I43) -> 0
A44: myJDW | B44: I-000239 | C44: 309.91 | D44: 190.2 | E44: 107.75 | F44: 93.5 | H44: 0.5 | J44: =SUM(C44:I44) -> 701.86
A45: mySchedule | B45: I-000271 | C45: 224.17 | D45: 90.01 | F45: 104.43 | H45: 3.5 | J45: =SUM(C45:I45) -> 422.11
A46: People Planning
A47: PCI DSS Compliance | J47: =SUM(C47:I47) -> 0
A48: QR Code Admin Replatform | J48: =SUM(C48:I48) -> 0
A49: Research Project: Possibilities & Benefits of AI | J49: =SUM(C49:I49) -> 0
A50: Out of Stock Screen Scraping | B50: I-000329 | J50: =SUM(C50:I50) -> 0
A51: Pub Ordering & Receipting Planning | B51: I-000330 | J51: =SUM(C51:I51) -> 0
A52: ResourceLink HCM / Absence Management | B52: I-000321 | D52: 21 | F52: 5.5 | H52: 14.67 | J52: =SUM(C52:I52) -> 41.17
A53: Suggested Rotas | B53: I-000322 | D53: 13.42 | F53: 2 | J53: =SUM(C53:I53) -> 15.42
A54: Security Response Payment Service | B54: I-000323 | J54: =SUM(C54:I54) -> 0
A55: Technical Planning
A56: WordPress Websites | B56: Various | C56: 49.67 | D56: 21.58 | F56: 3.75 | J56: =SUM(C56:I56) -> 75
C57: =SUM(C17:C56) -> 1788.39 | D57: =SUM(D17:D56) -> 915.18 | E57: =SUM(E17:E56) -> 458.95 | F57: =SUM(F17:F56) -> 608.42 | G57: =SUM(G17:G56) -> 47.11 | H57: =SUM(H17:H56) -> 213.92 | I57: =SUM(I17:I56) -> 1.25 | J57: =SUM(C57:I57) -> 4033.22
A60: Support and Maintenance | B60: 24974
A62: Support and Maintenance Hours | B62: Project Code | C62: Customer Support | D62: Project Management, Meetings & Reporting | E62: Maintenance | F62: Systems Admin | G62: Total
A63: Allergens | G63: =SUM(C63:F63) -> 0
A64: Customer Information Screens | G64: =SUM(C64:F64) -> 0
A65: Customer App / PWA / App Manager | C65: 94.41 | E65: 25.58 | G65: =SUM(C65:F65) -> 119.99
A66: myAuth | G66: =SUM(C66:F66) -> 0
A67: myJDW | C67: 14.4 | E67: 37.83 | G67: =SUM(C67:F67) -> 52.23
A68: mySchedule | C68: 6.31 | E68: 4.82 | G68: =SUM(C68:F68) -> 11.13
A69: Sitecore Corporate Website | G69: =SUM(C69:F69) -> 0
A70: Support for Franchises | G70: =SUM(C70:F70) -> 0
A71: WordPress Websites | E71: 0.5 | G71: =SUM(C71:F71) -> 0.5
C72: =SUM(C64:C71) -> 115.12 | D72: =SUM(D64:D71) -> 0 | E72: =SUM(E64:E71) -> 68.73 | F72: =SUM(F63:F71) -> 0 | G72: =SUM(C72:F72) -> 183.85
A75: Third Party Services | B75: Variable
A77: Company | B77: Website / Application | D77: Contracted To | E77: Frequency | F77: Per Annum Charge | G77: Per Month Charge | H77: Service Notes
A79: AWS | B79: myJDW, mySchedule, Authentication | D79: JDW | E79: Monthly | H79: Charged directly to JDW. Figures are converted from dollars at 0.82 pound sterling.
A80: AWS | B80: Customer App | D80: JDW | E80: Monthly | H80: Charged directly to JDW. Figures are converted from dollars at 0.82 pound sterling.
A81: AWS | B81: Auth0 Wisdom & Customer Accounts PoC | D81: JDW | E81: Monthly | H81: Charged directly to JDW. Figures are converted from dollars at 0.82 pound sterling.
A82: AWS | B82: Corporate Website Sitecore | D82: JDW | E82: NA | H82: Charged directly to JDW. Figures are converted from dollars at 0.82 pound sterling.
A83: AWS | B83: Rota Automation & ChatBot AWS Costs | D83: JDW | E83: Monthly
A84: Sendbird | B84: myJDW | D84: JDW | E84: Monthly | H84: Charged directly to JDW. Filter don't have sight of this fee.
A86: Elastic Search | B86: myJDW & mySchedule | D86: Filter | E86: Monthly | G86: 59.16 | H86: Fluctuates depending on usage, charged each month. No real increase for mySchedule as there is limited content to search. Not possible to split by service.
A87: Open Weather | B87: mySchedule | D87: Filter | E87: Monthly | H87: Fluctuates depending on usage, charged each month., currently not hitting limits to be charged.
A88: Ionic Enterprise Package | B88: Customer App | D88: Filter | E88: Annual | H88: Enterprise package with live updates.
A89: Ionic Payments | B89: Customer App | D89: Filter | E89: Annual | H89: Annual requirement from Feb 24.
A90: Apple Developer Enterprise Program - One year | B90: myJDW | D90: JDW | E90: Annual | H90: Recharegd by Filter. Traditionally we haven't marked this cost up.
A91: Google Maps API | B91: Customer App, Corporate & Hotels Websites | D91: Filter | E91: Monthly | G91: 14678.21 | H91: Fluctuates depending on usage.
A92: WordPress Plugins Annual Budget | D92: Filter | E92: Annual | H92: In use across WordPress websites. Included Corporate website once live. Plugins include: Gravity Forms Elite, Search Pro, PersonalizeWP Pro, WPRocket, Imagify, Media Library Organiser Pro, Advanced Custom Fields, Advanced Post Type Order, Yoast Duplicate Post, Admin Columns Pro, WP Migrate Premier, Wordfence, WP Activity Log. Potentially need to look at this as more of a package moving forwards across all sites.
A93: WPEngine Website Hosting | B93: Careers | D93: JDW | E93: Monthly | H93: This fee will become obsolete from August, with move to dedicated WPEngine hosting charged directly to JDW.
A94: WPEngine Website Hosting | B94: Investors | D94: JDW | E94: Monthly | H94: This fee will become obsolete from August, with move to dedicated WPEngine hosting charged directly to JDW.
A95: WPEngine Website Hosting | B95: Hotel | D95: JDW | E95: Monthly | H95: This fees will become obsolete if moving to a WP Engine Premier Hosting Solution, see Corporate Website.
A96: WPEngine Website Hosting | B96: Corporate | D96: JDW | E96: Monthly | H96: The re-platforming will involve the set-up of a multi-site solution to pull together all the microsites into a single platform. WP Engine have proposed two options for this, please see WP Engine / JDW - proposal for the details. We can discuss this further, alongside the decision as to whether Filter will contract on behalf of JDW (at 15% admin fee) or you choose to contract directly with WP Engine. Included is single node fee.
A97: Website Cookie Yes | B97: Corporate | D97: Filter | E97: Annual | H97: Outside of standard plugin package.
A98: Website Cookie Yes | B98: Hotel | D98: Filter | E98: Annual | H98: Outside of standard plugin package.
A99: Website Yoast SEO Premium | B99: Hotel | D99: Filter | E99: Annual | H99: Outside of standard plugin package.
A100: Statamic | D100: Filter | E100: Annual | H100: Reduces after one year to c.£60 per year.
A101: AWS Partnership Select Tier Recharge | D101: Filter | E101: Annual | H101: 50% invoiced to JDW at cost
A102: Cosmic Giant (JDW Forms) | B102: myJDW | D102: Filter | E102: Annual | G102: 263.69 | H102: Outside of standard plugin package.
F103: =SUM(F78:F101) -> 0 | G103: =SUM(G79:G102) -> 15001.06

Sheet Feb 25
A1: Month: | B1: 45689
A3: Dedicated Team Billing: | B3: =B9+B60 -> 340813
A4: Fixed Team Target Hours: | B4: =SUM(32*8.5)*20 -> 5440 | C4: 32 FTE
A5: Fixed Team Recorded Hours: | B5: =SUM(G72,J57,T13) -> 5441.07
A6: Difference: | B6: =B5-B4 -> 1.07
A9: Planning, Development & Delivery | B9: 315839
C10: R&P | D10: R&P | E10: R&P | F10: R&P | G10: R&P | H10: R&P | I10: TMC | J10: R&P | K10: TMC | L10: TMC | M10: TMC | N10: TMC | O10: TMC | P10: TMC | Q10: TMC | R10: TMC
A11: Programme Management Hours | B11: Project Code | C11: Planning | D11: Project Management, Meetings & Reporting | E11: Design | F11: Admin | G11: Systems Admin | H11: Research | I11: Training | J11: Finance | K11: HR | L11: Recruitment | M11: Travel | N11: Break | O11: Lunch | P11: Holiday | Q11: Bank Holiday | R11: Sick | S11: Other Absence | T11: Total
C13: 31.52 | D13: 329.02 | F13: 35.55 | G13: 127.03 | H13: 17.75 | I13: 26.33 | J13: 6.25 | K13: 30.61 | L13: 6 | M13: 2.5 | N13: 26 | O13: 486.47 | P13: 294 | R13: 31.12 | S13: 24 | T13: =SUM(C13:S13) -> 1474.15
A16: Projects Hours | B16: Project Code | C16: Development | D16: Project Management, Meetings & Reporting | E16: Testing | F16: Planning | G16: Systems Admin | H16: Design | I16: Release | J16: Total
A17: Allergens Service | B17: I-000300 | J17: =SUM(C17:I17) -> 0
A18: Authentication | B18: I-000312 | C18: 77.5 | D18: 63.33 | E18: 19.45 | F18: 97.15 | G18: 35.07 | H18: 0.25 | I18: 6.5 | J18: =SUM(C18:I18) -> 299.25
A19: Available Ales on TV Screens | J19: =SUM(C19:I19) -> 0
A20: Customer Information Screens | B20: I-000313 | D20: 0.25 | J20: =SUM(C20:I20) -> 0.25
A21: Corporate Website Replatform Build | B21: I-000300 | D21: 0.25 | H21: 1.5 | J21: =SUM(C21:I21) -> 1.75
A22: Customer Accounts Planning | B22: I-000311 | C22: 135.94 | D22: 17.5 | E22: 25 | F22: 8.85 | G22: 0.43 | J22: =SUM(C22:I22) -> 187.72
A23: Customer App - Ibersol Franchise Integration
A24: Customer App - Lagardere Franchise Integration
A25: Customer App / PWA / App Manager | B25: I-000287 | C25: 206.25 | D25: 292.31 | E25: 130.17 | F25: 164.83 | G25: 23.3 | H25: 49.5 | I25: 0.75 | J25: =SUM(C25:I25) -> 867.11
A26: Customer App UX/UI Redesign | J26: =SUM(C26:I26) -> 0
A27: Customer Planning
A28: Digital Pub Records | B28: I-000314 | C28: 177.5 | D28: 61 | F28: 17 | H28: 5.25 | J28: =SUM(C28:I28) -> 260.75
A29: Digital Vouchers | F29: 32 | J29: =SUM(C29:I29) -> 32
A30: Disaster Recovery & Business Continuity | B30: I-000315 | D30: 3.5 | F30: 1.5 | G30: 24.05 | J30: =SUM(C30:I30) -> 29.05
A31: Employee Digital Records | B31: I-000316 | C31: 2 | D31: 25.52 | F31: 7.5 | H31: 19.3 | J31: =SUM(C31:I31) -> 54.32
A32: Employee Verification (with WISDOM) | B32: I-000274 | J32: =SUM(C32:I32) -> 0
A33: Franchises Customer App | B33: I-000331 | C33: 239 | D33: 76.5 | E33: 68 | F33: 11 | G33: 23.47 | J33: =SUM(C33:I33) -> 417.97
A34: Franchises myJDW | D34: 0.25 | J34: =SUM(C34:I34) -> 0.25
A35: Franchises mySchedule | I35: 0.5 | J35: =SUM(C35:I35) -> 0.5
A36: Franchises WordPress Websites
A37: Hotels HLS Integration | B37: I-000335 | C37: 6 | D37: 7.67 | H37: 1.67 | J37: =SUM(C37:I37) -> 15.34
A38: Hotels Price Comparison | B38: I-000317 | J38: =SUM(C38:I38) -> 0
A39: Intelligence PoC | B39: I-000318 | C39: 84.87 | D39: 58.5 | E39: 37.08 | F39: 1 | H39: 37.35 | J39: =SUM(C39:I39) -> 218.8
A40: Microsoft Office Replacement | B40: I-000332 | D40: 29.92 | F40: 4.5 | H40: 37.42 | J40: =SUM(C40:I40) -> 71.84
A41: myETL
A42: myPub | B42: I-000319 | J42: =SUM(C42:I42) -> 0
A43: myDiscounts App | B43: I-000320 | J43: =SUM(C43:I43) -> 0
A44: myJDW | B44: I-000239 | C44: 347.67 | D44: 149.7 | E44: 22.05 | F44: 80.75 | H44: 21 | I44: 4.45 | J44: =SUM(C44:I44) -> 625.62
A45: mySchedule | B45: I-000271 | C45: 221.39 | D45: 115.57 | F45: 100.01 | G45: 1.5 | H45: 38.25 | I45: 10.5 | J45: =SUM(C45:I45) -> 487.22
A46: People Planning
A47: PCI DSS Compliance | J47: =SUM(C47:I47) -> 0
A48: QR Code Admin Replatform | J48: =SUM(C48:I48) -> 0
A49: Research Project: Possibilities & Benefits of AI | F49: 9 | J49: =SUM(C49:I49) -> 9
A50: Out of Stock Screen Scraping | B50: I-000329 | J50: =SUM(C50:I50) -> 0
A51: Pub Ordering & Receipting Planning | B51: I-000330 | J51: =SUM(C51:I51) -> 0
A52: ResourceLink HCM / Absence Management | B52: I-000321 | D52: 2.5 | J52: =SUM(C52:I52) -> 2.5
A53: Suggested Rotas | B53: I-000322 | C53: 40.67 | D53: 30.58 | F53: 10.67 | H53: 5 | J53: =SUM(C53:I53) -> 86.92
A54: Security Response Payment Service | B54: I-000323 | J54: =SUM(C54:I54) -> 0
A55: Technical Planning
A56: WordPress Websites | B56: Various | C56: 28.83 | D56: 29.76 | J56: =SUM(C56:I56) -> 58.59
C57: =SUM(C17:C56) -> 1567.62 | D57: =SUM(D17:D56) -> 964.61 | E57: =SUM(E17:E56) -> 301.75 | F57: =SUM(F17:F56) -> 545.76 | G57: =SUM(G17:G56) -> 107.82 | H57: =SUM(H17:H56) -> 216.49 | I57: =SUM(I17:I56) -> 22.7 | J57: =SUM(C57:I57) -> 3726.75
A60: Support and Maintenance | B60: 24974
A62: Support and Maintenance Hours | B62: Project Code | C62: Customer Support | D62: Project Management, Meetings & Reporting | E62: Maintenance | F62: Systems Admin | G62: Total
A63: Allergens | G63: =SUM(C63:F63) -> 0
A64: Customer Information Screens | E64: 0.33 | G64: =SUM(C64:F64) -> 0.33
A65: Customer App / PWA / App Manager | C65: 112.11 | E65: 32.83 | G65: =SUM(C65:F65) -> 144.94
A66: myAuth | G66: =SUM(C66:F66) -> 0
A67: myJDW | C67: 4.48 | E67: 46.67 | G67: =SUM(C67:F67) -> 51.15
A68: mySchedule | C68: 26.78 | E68: 16.72 | G68: =SUM(C68:F68) -> 43.5
A69: Sitecore Corporate Website | G69: =SUM(C69:F69) -> 0
A70: Support for Franchises | G70: =SUM(C70:F70) -> 0
A71: WordPress Websites | E71: 0.25 | G71: =SUM(C71:F71) -> 0.25
C72: =SUM(C64:C71) -> 143.37 | D72: =SUM(D64:D71) -> 0 | E72: =SUM(E64:E71) -> 96.8 | F72: =SUM(F63:F71) -> 0 | G72: =SUM(C72:F72) -> 240.17
A75: Third Party Services | B75: Variable
A77: Company | B77: Website / Application | D77: Contracted To | E77: Frequency | F77: Per Annum Charge | G77: Per Month Charge | H77: Service Notes
A79: AWS | B79: myJDW, mySchedule, Authentication | D79: JDW | E79: Monthly | H79: Charged directly to JDW. Figures are converted from dollars at 0.82 pound sterling.
